Workbook

Sheet 00 Indice
A1: Consolidado ICR - datos, calculos e indicadores
A2: Un solo libro con (1) el inventario de bases, (2) el catalogo de todos los calculos, y (3) una hoja por bloque de indicadores. Trazabilidad: las columnas VERDES contienen la FORMULA VIVA de Excel que recomputa el indicador desde sus insumos (con una columna 'dif' que debe dar ~0); las columnas NARANJAS son resultados de algebra matricial (inversas de Leontief/Ghosh) calculados en Python y validados contra INEGI a precision de maquina (~1e-15), con su script y CSV. Ninguna cifra es un numero suelto: o se recomputa aqui, o apunta a su script. Fecha de generacion: 2026-09-28.
A3: Hoja | B3: Contenido | C3: CSV fuente | D3: Script | E3: Tipo de trazabilidad
A4: 01 Bases de datos | B4: Inventario de todas las fuentes originales | C4: varias | D4: - | E4: Catalogo
A5: 02 Catalogo de calculos | B5: Todos los indicadores con formula, script y tipo de traza | C5: varias | D5: varios | E5: Catalogo
A6: 07 HHI numeradores | B6: Participaciones empresa/mina con fuente y pagina; share recomputado | C6: hhi_numeradores.csv | D6: hhi_2024.py / hhi_1994_2003.py | E6: Formula viva (share)
A7: 08 HHI serie | B7: HHI por mineral-anio con metodo/cobertura por fila | C7: hhi_consolidado.csv | D7: hhi_consolidado_2004_2020.py, hhi_2024.py, hhi_1994_2003.py | E7: Resultado + metodo por fila
A8: 09 CCV | B8: CCV por mineral-anio; numerador y denominador con recomputo | C8: ccv_serie.csv | D8: ccv_download.py, ccv_calc.py, ccv_fill_gaps.py | E8: Formula viva
A9: 10 Precios | B9: Precio anual de referencia por mineral con metodo de empalme | C9: precios_usgs_anual_empalmado.csv | D9: (extraccion USGS) | E9: Resultado + procedencia
A10: 11 Peso bloque prod | B10: Valor de produccion del bloque; V=Q*p y share recomputados | C10: peso_bloque_hist_produccion.csv | D10: peso_bloque_historico.py | E10: Formula viva
A11: 12 Peso bloque X | B11: % del bloque en exportaciones nacionales; recomputado | C11: peso_bloque_hist_exportaciones.csv | D11: peso_bloque_historico.py | E11: Formula viva
A12: 13 Peso bloque PIB | B12: PIB/VBP/empleo del bloque y participaciones; recomputado | C12: peso_bloque_mineria.csv | D12: peso_bloque.py | E12: Formula viva
A13: 14 MIP encadenam | B13: VBP, DI/VBP, Leontief/Ghosh y Rasmussen por mineral (2013/2018) | C13: mip_encadenamientos_minerales.csv | D13: mip_calc.py | E13: Resultado validado + Rasmussen formula viva
A14: 15 MIP eslabones | B14: Ghosh por eslabon (L1/L2/L3) por mineral | C14: mip_encadenamientos_eslabones.csv | D14: mip_eslabones.py | E14: Resultado validado
... A31: 24 HEM estatal | B31: HEM backward/forward/total de la mineria por entidad (2018) | C31: hem_estatal_mineria.csv | D31: hem_estatal.py | E31: Resultado validado + total formula viva

Sheet 01 Bases de datos
A1: Bases de datos utilizadas en la ICR
A2: Inventario de todas las fuentes que alimentan los calculos. Detalle por hoja en 10 Datos/Catalogo de Bases de Datos.md. Ademas de estas bases originales, todas las hojas estan exportadas a CSV limpio en 10 Datos/raw/csv/ (40 archivos).
A3: Bloque | B3: Fuente / archivo | C3: Contenido | D3: Periodo | E3: Utilidad | F3: Ubicacion en el repositorio
A4: 01 Criticidad | B4: USGS/Gobierno EE.UU. + Comision Europea (listas de criticidad) | C4: Clasificacion oficial de criticidad por mineral (riesgo de suministro, importancia economica) | D4: 2018-2023 | E4: Directa (criterio 1 del corpus) | F4: Bases Originales/01 Criticidad y Produccion Historica/1. minerales criticos.xlsx
A5: 01 Produccion hist. | B5: INEGI / SGM (hoja Produccion) | C5: Valor de produccion minera nacional, todos los minerales, MDP | D5: 1998-2024 | E5: Indirecta (contexto peso del bloque) | F5: idem, hoja 'Produccion'
A6: 02 Prod. y precios | B6: INEGI Banco de Indicadores | C6: Valor y volumen de produccion MENSUAL de los 10 minerales del corpus | D6: 2000-2025 | E6: Directa (valor de produccion, precio implicito) | F6: Bases Originales/02 Produccion y Precios Nacionales/2. produccion y precios.xlsx
A7: 03 Precios Cochilco | B7: Comision Chilena del Cobre (LME/COMEX) | C7: Precios internacionales mensuales, USD, 5 metales (Cu, Ag, Au, Pb, Zn) | D7: 1960-2024 | E7: Directa (validacion de precios) | F7: Bases Originales/03 Precios Internacionales Cochilco/ (5 archivos)
A8: 04 Comercio ext. | B8: CAMIMEX, Informe Anual (extraccion manual de PDF) | C8: Exportaciones/importaciones/balanza por producto, USD | D8: 2015-2024 | E8: Directa (CCV tramo reciente) | F8: Bases Originales/04 Comercio Exterior/4. balanza comercial.xlsx
A9: 05 Reservas mundo | B9: USGS / fuentes mundiales | C9: Produccion y reservas por pais y mineral, % mundial (una foto) | D9: corte unico | E9: Indirecta (posicion mundial de Mexico) | F9: Bases Originales/05 Reservas y Produccion Mundial/3. reservas y produccion mundial.xlsx
A10: 06 USGS DS-140 | B10: USGS Historical Statistics for Mineral and Material Commodities | C10: Valor unitario anual (USD/t nominal y constante 1998), desde 1900 | D10: 1900-2019 | E10: Directa (denominador CCV, precios de referencia) | F10: Bases Originales/06 USGS DS-140/ (10 archivos ds140-*.xlsx)
A11: 07 USGS MCS/MYB | B11: USGS Mineral Commodity Summaries + Minerals Yearbook Mexico | C11: Estructura de la industria (empresas, capacidades) y produccion nacional; base del HHI 1994-2003 | D11: 1994-2024 | E11: Directa (HHI regimen, estructura industria) | F11: Bases Originales/07 USGS MCS/ (incl. MYB Mexico 1994-2003)
A12: 08 CAMIMEX | B12: Camara Minera de Mexico, Informes Anuales | C12: Produccion por mina/empresa y total nacional; base del HHI 2004-2024 | D12: 2004-2025 | E12: Directa (numeradores HHI) | F12: Bases Originales/08 CAMIMEX Informes Anuales/
A13: 09 SGM Anuarios | B13: Servicio Geologico Mexicano, Anuario Estadistico de la Mineria | C13: Produccion por entidad federativa (georreferenciacion) y valor minero por estado | D13: 2019-2025 | E13: Directa (georref cuantitativa 2024) | F13: Bases Originales/09 SGM Anuarios/
A14: 10 MIP INEGI | B14: INEGI, Matriz Insumo-Producto simetrica producto x producto (clase SCIAN 6d) | C14: Coef. tecnicos (ctec=A) y directos+indirectos (cdi=inversa Leontief); base 2013 y 2018 + ref. 2008 | D14: 2008/2013/2018 | E14: Directa (Leontief, Ghosh, Rasmussen, demanda intermedia) | F14: Bases Originales/10 MIP INEGI/
... A19: 15 Marco instit. | B19: Normativa (Ley Minera, reforma 2023, etc.) | C19: Marco institucional del sector (contexto Cap. IV/VII) | D19: - | E19: Indirecta (contexto) | F19: Bases Originales/15 Marco Institucional/

Sheet 02 Catalogo de calculos
A1: Catalogo de calculos e indicadores
A2: Todos los calculos del proyecto, con su formula, insumos, script reproducible y el tipo de trazabilidad ofrecido en este libro. Base metodologica: 00 Proyecto/Metodologia y auditoria/Auditoria de indicadores.md. VERDE = columna con formula viva de Excel; NARANJA = columna de procedencia (resultado de script validado).
A3: Grupo | B3: Indicador / calculo | C3: Que mide | D3: Formula / matematica | E3: Insumos | F3: Script | G3: CSV fuente | H3: Hoja en este libro | I3: Tipo de traza
A4: 0 Insumos | B4: Precios USGS empalmados | C4: Precio anual de referencia del producto refinado, USD/t (nominal y const. 1998) | D4: Empalme de series USGS por factor de enlace en anios de traslape; deflactor a 1998 | E4: USGS DS-140 / MYB | F4: (extraccion USGS) | G4: precios_usgs_anual_empalmado.csv | H4: 10 Precios | I4: Resultado + procedencia
A5: 0 Insumos | B5: Peso del bloque - produccion | C5: Valor de produccion del bloque y descomposicion precio/volumen | D5: V = Q x p ; indices de volumen y de precio entre t0 y t1 | E5: volumen (USGS/CAMIMEX) x precio empalmado | F5: peso_bloque_historico.py | G5: peso_bloque_hist_produccion.csv | H5: 11 Peso bloque prod | I5: Formula viva
A6: 0 Insumos | B6: Peso del bloque - exportaciones | C6: % del bloque en las exportaciones totales de Mexico | D6: share = X_bloque / X_nacional | E6: Comtrade + Banco Mundial TX.VAL.MRCH.CD.WT | F6: peso_bloque_historico.py | G6: peso_bloque_hist_exportaciones.csv | H6: 12 Peso bloque X | I6: Formula viva
A7: 0 Insumos | B7: Peso del bloque - PIB / empleo | C7: Participacion del bloque en PIB y empleo | D7: pct = valor_bloque / total_nacional | E7: MIP 2013/2018 (B.1bP, P.1, PT) | F7: peso_bloque.py | G7: peso_bloque_mineria.csv | H7: 13 Peso bloque PIB | I7: Formula viva
A8: 1 HHI | B8: HHI de concentracion extractiva | C8: Concentracion de la produccion por mineral (estructura de mercado) | D8: HHI = sum_i (s_i)^2 , s_i en % (escala 0-10000) | E8: participaciones empresa/mina y total nacional | F8: hhi_2024.py, hhi_consolidado_2004_2020.py, hhi_1994_2003.py | G8: hhi_numeradores.csv, hhi_consolidado.csv | H8: 07-08 HHI | I8: Formula viva (participaciones) + resultado (residual/regimen)
A9: 1 HHI | B9: HHI geografico | C9: Concentracion territorial de la extraccion entre entidades | D9: HHI_geo = sum_estado (s_estado)^2 | E9: produccion por estado 2024 (SGM) | F9: georref_regionalizacion.py | G9: georref_regionalizacion.csv | H9: 17 Georref | I9: Formula viva
A10: 2 MIP nacional | B10: Leontief (hacia atras) | C10: Traccion a proveedores de cada mineral | D10: a_ij=z_ij/x_j ; L=(I-A)^-1 ; hacia atras = suma de columna | E10: MIP INEGI 2013/2018 (ctec/cdi) | F10: mip_calc.py | G10: mip_encadenamientos_minerales.csv | H10: 14 MIP encadenam. | I10: Resultado validado (1e-15) + Rasmussen formula viva
A11: 2 MIP nacional | B11: Ghosh (hacia adelante) - central | C11: Distribucion de la produccion; si alimenta industria domestica | D11: b_ij=z_ij/x_i ; G=(I-B)^-1 ; hacia adelante = suma de fila | E11: MIP INEGI 2013/2018 | F11: mip_calc.py | G11: mip_encadenamientos_minerales.csv | H11: 14 MIP encadenam. | I11: Resultado validado + Rasmussen formula viva
A12: 2 MIP nacional | B12: Hirschman-Rasmussen | C12: Encadenamientos comparables entre ramas (media=1) | D12: suma sectorial / promedio de todas las sumas | E12: sumas de fila/columna de L y G | F12: mip_calc.py | G12: mip_encadenamientos_minerales.csv | H12: 14 MIP encadenam. | I12: Formula viva (normalizacion)
A13: 2 MIP nacional | B13: Demanda intermedia (DI/VBP) | C13: Fraccion a uso intermedio interno y sectores compradores | D13: DI/VBP ; share de la fila del mineral | E13: MIP INEGI | F13: mip_calc.py | G13: mip_demanda_intermedia_minerales.csv | H13: 16 Demanda interm. | I13: Formula viva
A14: 2 MIP nacional | B14: Encadenamiento por eslabon | C14: Si el arrastre se sostiene al descender L1->L2->L3 | D14: Ghosh-Rasmussen por clase SCIAN 331... por mineral | E14: MIP INEGI | F14: mip_eslabones.py | G14: mip_encadenamientos_eslabones.csv | H14: 15 MIP eslabones | I14: Resultado + Rasmussen formula viva
... A30: 8 Criticidad | B30: Criticidad por producto | C30: Eslabon de mayor criticidad de cada mineral y si Mexico lo produce/exporta/importa | D30: (clasificacion oficial USGS/UE/IEA) | E30: listas oficiales | F30: (fichado) | G30: criticidad_productos.csv | H30: 22 Criticidad | I30: Clasificacion

Sheet 07 HHI numeradores
A1: HHI - numeradores (participaciones por empresa/mina)
A2: Insumo del HHI: participacion de cada empresa/mina y total nacional, con FUENTE y PAGINA (CAMIMEX/USGS). La columna verde recomputa participacion = volumen / total_nacional x 100 SOLO cuando volumen y total estan en la MISMA unidad; una 'dif' grande marca filas donde la fuente narrativa mezcla unidades (p.ej. oro en 'miles oz' vs total en toneladas) o usa CAPACIDAD, no produccion (barita/fluorita duopolio => >100%). Por eso el HHI final por mineral-anio se arma con residual/'metodo' por fila en '08 HHI serie', no por division directa.
A3: mineral | B3: anio_dato | C3: nivel | D3: unidad_minera | E3: empresa | F3: estado | G3: volumen | H3: unidad_volumen | I3: participacion_pct | J3: total_nacional | K3: unidad_total | L3: fuente | M3: pagina | N3: nota | O3: participacion (=formula) % | P3: dif vs reportada
A4: Barita | B4: 2020 | C4: empresa | E4: Baramin | G4: 235000 | H4: toneladas | I4: 63.1 | J4: 372262 | K4: toneladas | L4: Informe CAMIMEX 2021 | N4: Baramin 235 mil t de 372262 = 63.1pct | O4: =IF(AND(ISNUMBER(G4),ISNUMBER(J4),J4<>0,H4=K4),G4/J4*100,"") | P4: =IF(AND(ISNUMBER(O4),ISNUMBER(I4)),ROUND(O4-I4,2),"")
A5: Barita | B5: 2021 | C5: empresa | E5: Baramin | G5: 264000 | H5: toneladas | I5: 82.3 | J5: 320642 | K5: toneladas | L5: Informe CAMIMEX 2022 p76 | N5: OJO: denominador barita | O5: =IF(AND(ISNUMBER(G5),ISNUMBER(J5),J5<>0,H5=K5),G5/J5*100,"") | P5: =IF(AND(ISNUMBER(O5),ISNUMBER(I5)),ROUND(O5-I5,2),"")
A6: Barita | B6: 2022 | C6: empresa | E6: Baramin | G6: 152000 | H6: toneladas | I6: 49.8 | J6: 305270 | K6: toneladas | L6: Informe CAMIMEX 2023 p74 | N6: Baramin 152k de 305k nacional (CAMIMEX) | O6: =IF(AND(ISNUMBER(G6),ISNUMBER(J6),J6<>0,H6=K6),G6/J6*100,"") | P6: =IF(AND(ISNUMBER(O6),ISNUMBER(I6)),ROUND(O6-I6,2),"")
A7: Barita | B7: 2023 | C7: empresa | E7: Baramin | G7: 109953 | H7: toneladas | I7: 37.1 | J7: 295989 | K7: toneladas | L7: Informe CAMIMEX 2024 p87 | N7: Baramin 109953 de 295989 nacional | O7: =IF(AND(ISNUMBER(G7),ISNUMBER(J7),J7<>0,H7=K7),G7/J7*100,"") | P7: =IF(AND(ISNUMBER(O7),ISNUMBER(I7)),ROUND(O7-I7,2),"")
A8: Barita | B8: 2024 | C8: empresa | E8: Baramin | G8: 59980 | H8: toneladas | I8: 24.6 | J8: 244269 | K8: toneladas | L8: Informe CAMIMEX 2025 p72 | N8: Baramin 59980 de 244269; agotamiento mina Grecia | O8: =IF(AND(ISNUMBER(G8),ISNUMBER(J8),J8<>0,H8=K8),G8/J8*100,"") | P8: =IF(AND(ISNUMBER(O8),ISNUMBER(I8)),ROUND(O8-I8,2),"")
A9: Cobre | B9: 2021 | C9: empresa | E9: Grupo Mexico | H9: 559833 | I9: 76.3 | J9: 734137 | K9: toneladas | L9: Informe CAMIMEX 2022 | M9: 44 | N9: Narrativa: 559833 t = 76.3%; siguen Frisco Santa Maria de la Paz Capstone Aura | O9: =IF(AND(ISNUMBER(G9),ISNUMBER(J9),J9<>0,H9=K9),G9/J9*100,"") | P9: =IF(AND(ISNUMBER(O9),ISNUMBER(I9)),ROUND(O9-I9,2),"")
A10: Cobre | B10: 2021 | C10: mina | D10: Aranzazu | E10: Aura Minerals | F10: Zac. | G10: 14700 | H10: toneladas | J10: 734137 | K10: toneladas | L10: Informe CAMIMEX 2022 | M10: 44 | N10: 14.70 miles t | O10: =IF(AND(ISNUMBER(G10),ISNUMBER(J10),J10<>0,H10=K10),G10/J10*100,"") | P10: =IF(AND(ISNUMBER(O10),ISNUMBER(I10)),ROUND(O10-I10,2),"")
A11: Cobre | B11: 2021 | C11: mina | D11: Bolivar | E11: Sierra Metals | F11: Chih. | G11: 7670 | H11: toneladas | J11: 734137 | K11: toneladas | L11: Informe CAMIMEX 2022 | M11: 44 | N11: 7.67 miles t | O11: =IF(AND(ISNUMBER(G11),ISNUMBER(J11),J11<>0,H11=K11),G11/J11*100,"") | P11: =IF(AND(ISNUMBER(O11),ISNUMBER(I11)),ROUND(O11-I11,2),"")
A12: Cobre | B12: 2021 | C12: mina | D12: Buenavista del Cobre | E12: Grupo Mexico | F12: Son. | G12: 341200 | H12: toneladas | J12: 734137 | K12: toneladas | L12: Informe CAMIMEX 2022 | M12: 44 | N12: Tabla top-15 en miles de t verificada en imagen (341.20) | O12: =IF(AND(ISNUMBER(G12),ISNUMBER(J12),J12<>0,H12=K12),G12/J12*100,"") | P12: =IF(AND(ISNUMBER(O12),ISNUMBER(I12)),ROUND(O12-I12,2),"")
A13: Cobre | B13: 2021 | C13: mina | D13: Capela | E13: Industrias Penoles | F13: Gro. | G13: 3210 | H13: toneladas | J13: 734137 | K13: toneladas | L13: Informe CAMIMEX 2022 | M13: 44 | N13: 3.21 miles t | O13: =IF(AND(ISNUMBER(G13),ISNUMBER(J13),J13<>0,H13=K13),G13/J13*100,"") | P13: =IF(AND(ISNUMBER(O13),ISNUMBER(I13)),ROUND(O13-I13,2),"")
A14: Cobre | B14: 2021 | C14: mina | D14: Charcas | E14: Grupo Mexico | F14: S.L.P. | G14: 3340 | H14: toneladas | J14: 734137 | K14: toneladas | L14: Informe CAMIMEX 2022 | M14: 44 | N14: 3.34 miles t | O14: =IF(AND(ISNUMBER(G14),ISNUMBER(J14),J14<>0,H14=K14),G14/J14*100,"") | P14: =IF(AND(ISNUMBER(O14),ISNUMBER(I14)),ROUND(O14-I14,2),"")
A15: Cobre | B15: 2021 | C15: mina | D15: Cozamin | E15: Capstone Mining | F15: Zac. | G15: 24420 | H15: toneladas | J15: 734137 | K15: toneladas | L15: Informe CAMIMEX 2022 | M15: 44 | N15: 24.42 miles t | O15: =IF(AND(ISNUMBER(G15),ISNUMBER(J15),J15<>0,H15=K15),G15/J15*100,"") | P15: =IF(AND(ISNUMBER(O15),ISNUMBER(I15)),ROUND(O15-I15,2),"")
A16: Cobre | B16: 2021 | C16: mina | D16: La Caridad | E16: Grupo Mexico | F16: Son. | G16: 102690 | H16: toneladas | J16: 734137 | K16: toneladas | L16: Informe CAMIMEX 2022 | M16: 44 | N16: 102.69 miles t | O16: =IF(AND(ISNUMBER(G16),ISNUMBER(J16),J16<>0,H16=K16),G16/J16*100,"") | P16: =IF(AND(ISNUMBER(O16),ISNUMBER(I16)),ROUND(O16-I16,2),"")
A17: Cobre | B17: 2021 | C17: mina | D17: La Paz | E17: Neg. Mra. Sta. Ma. de La Paz y Anexas | F17: S.L.P. | G17: 25210 | H17: toneladas | J17: 734137 | K17: toneladas | L17: Informe CAMIMEX 2022 | M17: 44 | N17: 25.21 miles t | O17: =IF(AND(ISNUMBER(G17),ISNUMBER(J17),J17<>0,H17=K17),G17/J17*100,"") | P17: =IF(AND(ISNUMBER(O17),ISNUMBER(I17)),ROUND(O17-I17,2),"")
A18: Cobre | B18: 2021 | C18: mina | D18: Sabinas | E18: Industrias Penoles | F18: Zac. | G18: 3680 | H18: toneladas | J18: 734137 | K18: toneladas | L18: Informe CAMIMEX 2022 | M18: 44 | N18: 3.68 miles t | O18: =IF(AND(ISNUMBER(G18),ISNUMBER(J18),J18<>0,H18=K18),G18/J18*100,"") | P18: =IF(AND(ISNUMBER(O18),ISNUMBER(I18)),ROUND(O18-I18,2),"")
A19: Cobre | B19: 2021 | C19: mina | D19: San Martin | E19: Grupo Mexico | F19: Zac. | G19: 3080 | H19: toneladas | J19: 734137 | K19: toneladas | L19: Informe CAMIMEX 2022 | M19: 44 | N19: 3.08 miles t | O19: =IF(AND(ISNUMBER(G19),ISNUMBER(J19),J19<>0,H19=K19),G19/J19*100,"") | P19: =IF(AND(ISNUMBER(O19),ISNUMBER(I19)),ROUND(O19-I19,2),"")
A20: Cobre | B20: 2021 | C20: mina | D20: Santa Barbara | E20: Grupo Mexico | F20: Chih. | G20: 2290 | H20: toneladas | J20: 734137 | K20: toneladas | L20: Informe CAMIMEX 2022 | M20: 44 | N20: 2.29 miles t | O20: =IF(AND(ISNUMBER(G20),ISNUMBER(J20),J20<>0,H20=K20),G20/J20*100,"") | P20: =IF(AND(ISNUMBER(O20),ISNUMBER(I20)),ROUND(O20-I20,2),"")
A21: Cobre | B21: 2021 | C21: mina | D21: Tayahua | E21: Minera Frisco | F21: Zac. | G21: 23230 | H21: toneladas | J21: 734137 | K21: toneladas | L21: Informe CAMIMEX 2022 | M21: 44 | N21: 23.23 miles t | O21: =IF(AND(ISNUMBER(G21),ISNUMBER(J21),J21<>0,H21=K21),G21/J21*100,"") | P21: =IF(AND(ISNUMBER(O21),ISNUMBER(I21)),ROUND(O21-I21,2),"")
... A24: Cobre | B24: 2021 | C24: mina | D24: Zimapan | E24: Santacruz Silver | F24: Hgo. | G24: 1820 | H24: toneladas | J24: 734137 | K24: toneladas | L24: Informe CAMIMEX 2022 | M24: 44 | N24: 1.82 miles t | O24: =IF(AND(ISNUMBER(G24),ISNUMBER(J24),J24<>0,H24=K24),G24/J24*100,"") | P24: =IF(AND(ISNUMBER(O24),ISNUMBER(I24)),ROUND(O24-I24,2),"")
A25: Cobre | B25: 2022 | C25: empresa | E25: Grupo Mexico | I25: 73.3 | J25: 753885 | K25: toneladas | L25: Informe CAMIMEX 2023 | M25: 49 | N25: Narrativa: mayor productor 73.3%; siguen Frisco Santa Maria de la Paz Capstone Invecture | O25: =IF(AND(ISNUMBER(G25),ISNUMBER(J25),J25<>0,H25=K25),G25/J25*100,"") | P25: =IF(AND(ISNUMBER(O25),ISNUMBER(I25)),ROUND(O25-I25,2),"")
A26: Cobre | B26: 2022 | C26: mina | D26: Aranzazu Holding | E26: Aura | F26: Zac. | G26: 16241 | H26: toneladas | J26: 753885 | K26: toneladas | L26: Informe CAMIMEX 2023 | M26: 49 | O26: =IF(AND(ISNUMBER(G26),ISNUMBER(J26),J26<>0,H26=K26),G26/J26*100,"") | P26: =IF(AND(ISNUMBER(O26),ISNUMBER(I26)),ROUND(O26-I26,2),"")
A27: Cobre | B27: 2022 | C27: mina | D27: Avino | E27: Avino Silver and Gold | F27: Dgo. | G27: 2950 | H27: toneladas | J27: 753885 | K27: toneladas | L27: Informe CAMIMEX 2023 | M27: 49 | O27: =IF(AND(ISNUMBER(G27),ISNUMBER(J27),J27<>0,H27=K27),G27/J27*100,"") | P27: =IF(AND(ISNUMBER(O27),ISNUMBER(I27)),ROUND(O27-I27,2),"")
A28: Cobre | B28: 2022 | C28: mina | D28: Bolivar | E28: Sierra Metals | F28: Chih. | G28: 5709 | H28: toneladas | J28: 753885 | K28: toneladas | L28: Informe CAMIMEX 2023 | M28: 49 | O28: =IF(AND(ISNUMBER(G28),ISNUMBER(J28),J28<>0,H28=K28),G28/J28*100,"") | P28: =IF(AND(ISNUMBER(O28),ISNUMBER(I28)),ROUND(O28-I28,2),"")
A29: Cobre | B29: 2022 | C29: mina | D29: Buenavista del Cobre | E29: Grupo Mexico | F29: Son. | G29: 338633 | H29: toneladas | J29: 753885 | K29: toneladas | L29: Informe CAMIMEX 2023 | M29: 49 | N29: Tabla top-15 verificada en imagen | O29: =IF(AND(ISNUMBER(G29),ISNUMBER(J29),J29<>0,H29=K29),G29/J29*100,"") | P29: =IF(AND(ISNUMBER(O29),ISNUMBER(I29)),ROUND(O29-I29,2),"")
A30: Cobre | B30: 2022 | C30: mina | D30: Campo Morado | E30: Luca Mining | F30: Gro. | G30: 11158 | H30: toneladas | J30: 753885 | K30: toneladas | L30: Informe CAMIMEX 2023 | M30: 49 | O30: =IF(AND(ISNUMBER(G30),ISNUMBER(J30),J30<>0,H30=K30),G30/J30*100,"") | P30: =IF(AND(ISNUMBER(O30),ISNUMBER(I30)),ROUND(O30-I30,2),"")
A31: Cobre | B31: 2022 | C31: mina | D31: Capela | E31: Industrias Penoles | F31: Gro. | G31: 3377 | H31: toneladas | J31: 753885 | K31: toneladas | L31: Informe CAMIMEX 2023 | M31: 49 | O31: =IF(AND(ISNUMBER(G31),ISNUMBER(J31),J31<>0,H31=K31),G31/J31*100,"") | P31: =IF(AND(ISNUMBER(O31),ISNUMBER(I31)),ROUND(O31-I31,2),"")
A32: Cobre | B32: 2022 | C32: mina | D32: Charcas | E32: Grupo Mexico | F32: S.L.P. | G32: 3257 | H32: toneladas | J32: 753885 | K32: toneladas | L32: Informe CAMIMEX 2023 | M32: 49 | O32: =IF(AND(ISNUMBER(G32),ISNUMBER(J32),J32<>0,H32=K32),G32/J32*100,"") | P32: =IF(AND(ISNUMBER(O32),ISNUMBER(I32)),ROUND(O32-I32,2),"")
A33: Cobre | B33: 2022 | C33: mina | D33: Cozamin | E33: Capstone Copper | F33: Zac. | G33: 24451 | H33: toneladas | J33: 753885 | K33: toneladas | L33: Informe CAMIMEX 2023 | M33: 49 | O33: =IF(AND(ISNUMBER(G33),ISNUMBER(J33),J33<>0,H33=K33),G33/J33*100,"") | P33: =IF(AND(ISNUMBER(O33),ISNUMBER(I33)),ROUND(O33-I33,2),"")
A34: Cobre | B34: 2022 | C34: mina | D34: La Caridad | E34: Grupo Mexico | F34: Son. | G34: 88492 | H34: toneladas | J34: 753885 | K34: toneladas | L34: Informe CAMIMEX 2023 | M34: 49 | O34: =IF(AND(ISNUMBER(G34),ISNUMBER(J34),J34<>0,H34=K34),G34/J34*100,"") | P34: =IF(AND(ISNUMBER(O34),ISNUMBER(I34)),ROUND(O34-I34,2),"")
A35: Cobre | B35: 2022 | C35: mina | D35: La Paz | E35: Nemisa | F35: S.L.P. | G35: 26016 | H35: toneladas | J35: 753885 | K35: toneladas | L35: Informe CAMIMEX 2023 | M35: 49 | O35: =IF(AND(ISNUMBER(G35),ISNUMBER(J35),J35<>0,H35=K35),G35/J35*100,"") | P35: =IF(AND(ISNUMBER(O35),ISNUMBER(I35)),ROUND(O35-I35,2),"")
A36: Cobre | B36: 2022 | C36: mina | D36: Piedras Verdes | E36: Invecture Group | F36: Son. | G36: 5446 | H36: toneladas | J36: 753885 | K36: toneladas | L36: Informe CAMIMEX 2023 | M36: 49 | O36: =IF(AND(ISNUMBER(G36),ISNUMBER(J36),J36<>0,H36=K36),G36/J36*100,"") | P36: =IF(AND(ISNUMBER(O36),ISNUMBER(I36)),ROUND(O36-I36,2),"")
A37: Cobre | B37: 2022 | C37: mina | D37: Sabinas | E37: Industrias Penoles | F37: Zac. | G37: 2771 | H37: toneladas | J37: 753885 | K37: toneladas | L37: Informe CAMIMEX 2023 | M37: 49 | O37: =IF(AND(ISNUMBER(G37),ISNUMBER(J37),J37<>0,H37=K37),G37/J37*100,"") | P37: =IF(AND(ISNUMBER(O37),ISNUMBER(I37)),ROUND(O37-I37,2),"")
A38: Cobre | B38: 2022 | C38: mina | D38: San Martin | E38: Grupo Mexico | F38: Zac. | G38: 3810 | H38: toneladas | J38: 753885 | K38: toneladas | L38: Informe CAMIMEX 2023 | M38: 49 | O38: =IF(AND(ISNUMBER(G38),ISNUMBER(J38),J38<>0,H38=K38),G38/J38*100,"") | P38: =IF(AND(ISNUMBER(O38),ISNUMBER(I38)),ROUND(O38-I38,2),"")
A39: Cobre | B39: 2022 | C39: mina | D39: Tayahua | E39: Minera Frisco | F39: Zac. | G39: 27331 | H39: toneladas | J39: 753885 | K39: toneladas | L39: Informe CAMIMEX 2023 | M39: 49 | O39: =IF(AND(ISNUMBER(G39),ISNUMBER(J39),J39<>0,H39=K39),G39/J39*100,"") | P39: =IF(AND(ISNUMBER(O39),ISNUMBER(I39)),ROUND(O39-I39,2),"")
A40: Cobre | B40: 2022 | C40: mina | D40: Velardena | E40: Industrias Penoles | F40: Dgo. | G40: 2400 | H40: toneladas | J40: 753885 | K40: toneladas | L40: Informe CAMIMEX 2023 | M40: 49 | N40: Top-15 suma 562042 | O40: =IF(AND(ISNUMBER(G40),ISNUMBER(J40),J40<>0,H40=K40),G40/J40*100,"") | P40: =IF(AND(ISNUMBER(O40),ISNUMBER(I40)),ROUND(O40-I40,2),"")
A41: Cobre | B41: 2023 | C41: empresa | E41: Grupo Mexico | I41: 76.8 | J41: 699118 | K41: toneladas | L41: Informe CAMIMEX 2024 | M41: 57 | N41: Narrativa: mayor productor 76.8%; siguen Nemisa Invecture Capstone Penoles | O41: =IF(AND(ISNUMBER(G41),ISNUMBER(J41),J41<>0,H41=K41),G41/J41*100,"") | P41: =IF(AND(ISNUMBER(O41),ISNUMBER(I41)),ROUND(O41-I41,2),"")
A42: Cobre | B42: 2023 | C42: mina | D42: Aranzazu | E42: Aura Minerals | F42: Zac. | G42: 16507 | H42: toneladas | J42: 699118 | K42: toneladas | L42: Informe CAMIMEX 2024 | M42: 57 | O42: =IF(AND(ISNUMBER(G42),ISNUMBER(J42),J42<>0,H42=K42),G42/J42*100,"") | P42: =IF(AND(ISNUMBER(O42),ISNUMBER(I42)),ROUND(O42-I42,2),"")
A43: Cobre | B43: 2023 | C43: mina | D43: Avino | E43: Avino Silver and Gold | F43: Dgo. | G43: 2406 | H43: toneladas | J43: 699118 | K43: toneladas | L43: Informe CAMIMEX 2024 | M43: 57 | O43: =IF(AND(ISNUMBER(G43),ISNUMBER(J43),J43<>0,H43=K43),G43/J43*100,"") | P43: =IF(AND(ISNUMBER(O43),ISNUMBER(I43)),ROUND(O43-I43,2),"")
A44: Cobre | B44: 2023 | C44: mina | D44: Bolivar | E44: Sierra Metals | F44: Chih. | G44: 11690 | H44: toneladas | J44: 699118 | K44: toneladas | L44: Informe CAMIMEX 2024 | M44: 57 | O44: =IF(AND(ISNUMBER(G44),ISNUMBER(J44),J44<>0,H44=K44),G44/J44*100,"") | P44: =IF(AND(ISNUMBER(O44),ISNUMBER(I44)),ROUND(O44-I44,2),"")
A45: Cobre | B45: 2023 | C45: mina | D45: Buenavista del Cobre | E45: Grupo Mexico | F45: Son. | G45: 328953 | H45: toneladas | J45: 699118 | K45: toneladas | L45: Informe CAMIMEX 2024 | M45: 57 | N45: Tabla top-15 verificada en imagen | O45: =IF(AND(ISNUMBER(G45),ISNUMBER(J45),J45<>0,H45=K45),G45/J45*100,"") | P45: =IF(AND(ISNUMBER(O45),ISNUMBER(I45)),ROUND(O45-I45,2),"")
A46: Cobre | B46: 2023 | C46: mina | D46: Campo Morado | E46: Luca Mining | F46: Gro. | G46: 2507 | H46: toneladas | J46: 699118 | K46: toneladas | L46: Informe CAMIMEX 2024 | M46: 57 | O46: =IF(AND(ISNUMBER(G46),ISNUMBER(J46),J46<>0,H46=K46),G46/J46*100,"") | P46: =IF(AND(ISNUMBER(O46),ISNUMBER(I46)),ROUND(O46-I46,2),"")
A47: Cobre | B47: 2023 | C47: mina | D47: Capela | E47: Industrias Penoles | F47: Gro. | G47: 2467 | H47: toneladas | J47: 699118 | K47: toneladas | L47: Informe CAMIMEX 2024 | M47: 57 | O47: =IF(AND(ISNUMBER(G47),ISNUMBER(J47),J47<>0,H47=K47),G47/J47*100,"") | P47: =IF(AND(ISNUMBER(O47),ISNUMBER(I47)),ROUND(O47-I47,2),"")
A48: Cobre | B48: 2023 | C48: mina | D48: Charcas | E48: Grupo Mexico | F48: S.L.P. | G48: 2791 | H48: toneladas | J48: 699118 | K48: toneladas | L48: Informe CAMIMEX 2024 | M48: 57 | O48: =IF(AND(ISNUMBER(G48),ISNUMBER(J48),J48<>0,H48=K48),G48/J48*100,"") | P48: =IF(AND(ISNUMBER(O48),ISNUMBER(I48)),ROUND(O48-I48,2),"")
A49: Cobre | B49: 2023 | C49: mina | D49: Cozamin | E49: Capstone Copper | F49: Zac. | G49: 24340 | H49: toneladas | J49: 699118 | K49: toneladas | L49: Informe CAMIMEX 2024 | M49: 57 | O49: =IF(AND(ISNUMBER(G49),ISNUMBER(J49),J49<>0,H49=K49),G49/J49*100,"") | P49: =IF(AND(ISNUMBER(O49),ISNUMBER(I49)),ROUND(O49-I49,2),"")
A50: Cobre | B50: 2023 | C50: mina | D50: La Caridad | E50: Grupo Mexico | F50: Son. | G50: 87814 | H50: toneladas | J50: 699118 | K50: toneladas | L50: Informe CAMIMEX 2024 | M50: 57 | O50: =IF(AND(ISNUMBER(G50),ISNUMBER(J50),J50<>0,H50=K50),G50/J50*100,"") | P50: =IF(AND(ISNUMBER(O50),ISNUMBER(I50)),ROUND(O50-I50,2),"")
A51: Cobre | B51: 2023 | C51: mina | D51: La Paz | E51: Nemisa | F51: S.L.P. | G51: 25791 | H51: toneladas | J51: 699118 | K51: toneladas | L51: Informe CAMIMEX 2024 | M51: 57 | O51: =IF(AND(ISNUMBER(G51),ISNUMBER(J51),J51<>0,H51=K51),G51/J51*100,"") | P51: =IF(AND(ISNUMBER(O51),ISNUMBER(I51)),ROUND(O51-I51,2),"")
A52: Cobre | B52: 2023 | C52: mina | D52: Sabinas | E52: Industrias Penoles | F52: Zac. | G52: 2529 | H52: toneladas | J52: 699118 | K52: toneladas | L52: Informe CAMIMEX 2024 | M52: 57 | O52: =IF(AND(ISNUMBER(G52),ISNUMBER(J52),J52<>0,H52=K52),G52/J52*100,"") | P52: =IF(AND(ISNUMBER(O52),ISNUMBER(I52)),ROUND(O52-I52,2),"")
A53: Cobre | B53: 2023 | C53: mina | D53: San Martin | E53: Grupo Mexico | F53: Zac. | G53: 4647 | H53: toneladas | J53: 699118 | K53: toneladas | L53: Informe CAMIMEX 2024 | M53: 57 | O53: =IF(AND(ISNUMBER(G53),ISNUMBER(J53),J53<>0,H53=K53),G53/J53*100,"") | P53: =IF(AND(ISNUMBER(O53),ISNUMBER(I53)),ROUND(O53-I53,2),"")
A54: Cobre | B54: 2023 | C54: mina | D54: Santa Barbara | E54: Grupo Mexico | F54: Chih. | G54: 2125 | H54: toneladas | J54: 699118 | K54: toneladas | L54: Informe CAMIMEX 2024 | M54: 57 | N54: Top-15 suma 539244 | O54: =IF(AND(ISNUMBER(G54),ISNUMBER(J54),J54<>0,H54=K54),G54/J54*100,"") | P54: =IF(AND(ISNUMBER(O54),ISNUMBER(I54)),ROUND(O54-I54,2),"")
A55: Cobre | B55: 2023 | C55: mina | D55: Tayahua | E55: Minera Frisco | F55: Zac. | G55: 21754 | H55: toneladas | J55: 699118 | K55: toneladas | L55: Informe CAMIMEX 2024 | M55: 57 | O55: =IF(AND(ISNUMBER(G55),ISNUMBER(J55),J55<>0,H55=K55),G55/J55*100,"") | P55: =IF(AND(ISNUMBER(O55),ISNUMBER(I55)),ROUND(O55-I55,2),"")
A56: Cobre | B56: 2023 | C56: mina | D56: Velardena | E56: Industrias Penoles | F56: Dgo. | G56: 2923 | H56: toneladas | J56: 699118 | K56: toneladas | L56: Informe CAMIMEX 2024 | M56: 57 | O56: =IF(AND(ISNUMBER(G56),ISNUMBER(J56),J56<>0,H56=K56),G56/J56*100,"") | P56: =IF(AND(ISNUMBER(O56),ISNUMBER(I56)),ROUND(O56-I56,2),"")
A57: Cobre | B57: 2024 | C57: empresa | E57: Grupo Mexico | I57: 78 | L57: Informe CAMIMEX 2025 | M57: 49 | N57: Narrativa: mayor productor 78%; siguen Capstone Nemisa Penoles Frisco | O57: =IF(AND(ISNUMBER(G57),ISNUMBER(J57),J57<>0,H57=K57),G57/J57*100,"") | P57: =IF(AND(ISNUMBER(O57),ISNUMBER(I57)),ROUND(O57-I57,2),"")
A58: Cobre | B58: 2024 | C58: mina | D58: Aranzazu | E58: Aura Minerals | F58: Zac. | G58: 19924 | H58: toneladas | L58: Informe CAMIMEX 2025 | M58: 49 | O58: =IF(AND(ISNUMBER(G58),ISNUMBER(J58),J58<>0,H58=K58),G58/J58*100,"") | P58: =IF(AND(ISNUMBER(O58),ISNUMBER(I58)),ROUND(O58-I58,2),"")
A59: Cobre | B59: 2024 | C59: mina | D59: Bolivar | E59: Sierra Metals | F59: Chih. | G59: 12452 | H59: toneladas | L59: Informe CAMIMEX 2025 | M59: 49 | O59: =IF(AND(ISNUMBER(G59),ISNUMBER(J59),J59<>0,H59=K59),G59/J59*100,"") | P59: =IF(AND(ISNUMBER(O59),ISNUMBER(I59)),ROUND(O59-I59,2),"")
A60: Cobre | B60: 2024 | C60: mina | D60: Buenavista del Cobre | E60: Grupo Mexico | F60: Son. | G60: 348959 | H60: toneladas | L60: Informe CAMIMEX 2025 | M60: 49 | N60: Tabla top-10 verificada en imagen | O60: =IF(AND(ISNUMBER(G60),ISNUMBER(J60),J60<>0,H60=K60),G60/J60*100,"") | P60: =IF(AND(ISNUMBER(O60),ISNUMBER(I60)),ROUND(O60-I60,2),"")
A61: Cobre | B61: 2024 | C61: mina | D61: Capela | E61: Industrias Penoles | F61: Gro. | G61: 5324 | H61: toneladas | L61: Informe CAMIMEX 2025 | M61: 49 | O61: =IF(AND(ISNUMBER(G61),ISNUMBER(J61),J61<>0,H61=K61),G61/J61*100,"") | P61: =IF(AND(ISNUMBER(O61),ISNUMBER(I61)),ROUND(O61-I61,2),"")
A62: Cobre | B62: 2024 | C62: mina | D62: Cozamin | E62: Capstone Copper | F62: Zac. | G62: 24907 | H62: toneladas | L62: Informe CAMIMEX 2025 | M62: 49 | O62: =IF(AND(ISNUMBER(G62),ISNUMBER(J62),J62<>0,H62=K62),G62/J62*100,"") | P62: =IF(AND(ISNUMBER(O62),ISNUMBER(I62)),ROUND(O62-I62,2),"")
A63: Cobre | B63: 2024 | C63: mina | D63: La Caridad | E63: Grupo Mexico | F63: Son. | G63: 93725 | H63: toneladas | L63: Informe CAMIMEX 2025 | M63: 49 | O63: =IF(AND(ISNUMBER(G63),ISNUMBER(J63),J63<>0,H63=K63),G63/J63*100,"") | P63: =IF(AND(ISNUMBER(O63),ISNUMBER(I63)),ROUND(O63-I63,2),"")
A64: Cobre | B64: 2024 | C64: mina | D64: La Paz | E64: Nemisa | F64: S.L.P. | G64: 24498 | H64: toneladas | L64: Informe CAMIMEX 2025 | M64: 49 | O64: =IF(AND(ISNUMBER(G64),ISNUMBER(J64),J64<>0,H64=K64),G64/J64*100,"") | P64: =IF(AND(ISNUMBER(O64),ISNUMBER(I64)),ROUND(O64-I64,2),"")
A65: Cobre | B65: 2024 | C65: mina | D65: San Martin | E65: Grupo Mexico | F65: Zac. | G65: 5025 | H65: toneladas | L65: Informe CAMIMEX 2025 | M65: 49 | O65: =IF(AND(ISNUMBER(G65),ISNUMBER(J65),J65<>0,H65=K65),G65/J65*100,"") | P65: =IF(AND(ISNUMBER(O65),ISNUMBER(I65)),ROUND(O65-I65,2),"")
A66: Cobre | B66: 2024 | C66: mina | D66: Tayahua | E66: Minera Frisco | F66: Zac. | G66: 21609 | H66: toneladas | L66: Informe CAMIMEX 2025 | M66: 49 | O66: =IF(AND(ISNUMBER(G66),ISNUMBER(J66),J66<>0,H66=K66),G66/J66*100,"") | P66: =IF(AND(ISNUMBER(O66),ISNUMBER(I66)),ROUND(O66-I66,2),"")
A67: Cobre | B67: 2024 | C67: mina | D67: Tizapa | E67: Industrias Penoles | F67: Edo. de Mex. | G67: 3570 | H67: toneladas | L67: Informe CAMIMEX 2025 | M67: 49 | N67: Top-10 suma 559993 | O67: =IF(AND(ISNUMBER(G67),ISNUMBER(J67),J67<>0,H67=K67),G67/J67*100,"") | P67: =IF(AND(ISNUMBER(O67),ISNUMBER(I67)),ROUND(O67-I67,2),"")
A68: Fluorita | B68: 2020 | C68: empresa | E68: Koura | H68: toneladas | J68: 914597 | K68: toneladas | L68: INEGI + CAMIMEX | N68: Koura unica extractora de Las Cuevas; ~95-100pct | O68: =IF(AND(ISNUMBER(G68),ISNUMBER(J68),J68<>0,H68=K68),G68/J68*100,"") | P68: =IF(AND(ISNUMBER(O68),ISNUMBER(I68)),ROUND(O68-I68,2),"")
A69: Fluorita | B69: 2021 | C69: empresa | E69: Koura | G69: 1100000 | H69: toneladas | I69: 100 | J69: 1007118 | K69: toneladas | L69: Informe CAMIMEX 2022 p79 | N69: Koura ~1.1Mt aprox = total INEGI 1.007Mt -> ~100pct (monopolio) | O69: =IF(AND(ISNUMBER(G69),ISNUMBER(J69),J69<>0,H69=K69),G69/J69*100,"") | P69: =IF(AND(ISNUMBER(O69),ISNUMBER(I69)),ROUND(O69-I69,2),"")
A70: Fluorita | B70: 2022 | C70: empresa | E70: Koura | H70: toneladas | I70: 100 | J70: 1000626 | K70: toneladas | L70: Informe CAMIMEX 2023 p91 | N70: Koura unica empresa que extrae el crudo de la mina mas grande del mundo | O70: =IF(AND(ISNUMBER(G70),ISNUMBER(J70),J70<>0,H70=K70),G70/J70*100,"") | P70: =IF(AND(ISNUMBER(O70),ISNUMBER(I70)),ROUND(O70-I70,2),"")
A71: Fluorita | B71: 2023 | C71: empresa | E71: Koura | H71: toneladas | I71: 100 | J71: 1162591 | K71: toneladas | L71: Informe CAMIMEX 2024 p91 | N71: Koura reservas 66.2 Mt; produccion + | O71: =IF(AND(ISNUMBER(G71),ISNUMBER(J71),J71<>0,H71=K71),G71/J71*100,"") | P71: =IF(AND(ISNUMBER(O71),ISNUMBER(I71)),ROUND(O71-I71,2),"")
A72: Fluorita | B72: 2024 | C72: empresa | E72: Koura | H72: toneladas | I72: 100 | J72: 1505071 | K72: toneladas | L72: Informe CAMIMEX 2025 p74 | N72: Koura principal; reservas 108.25 Mt | O72: =IF(AND(ISNUMBER(G72),ISNUMBER(J72),J72<>0,H72=K72),G72/J72*100,"") | P72: =IF(AND(ISNUMBER(O72),ISNUMBER(I72)),ROUND(O72-I72,2),"")
A73: Grafito | B73: 2020 | C73: empresa | E73: ninguno | H73: toneladas | K73: toneladas | L73: CAMIMEX no desglosa | N73: Caso de contraste; HHI bajo por Anuario SGM (num. productores) | O73: =IF(AND(ISNUMBER(G73),ISNUMBER(J73),J73<>0,H73=K73),G73/J73*100,"") | P73: =IF(AND(ISNUMBER(O73),ISNUMBER(I73)),ROUND(O73-I73,2),"")
A74: Grafito | B74: 2021 | C74: empresa | E74: ninguno | H74: toneladas | K74: toneladas | L74: CAMIMEX no desglosa | N74: Caso de contraste | O74: =IF(AND(ISNUMBER(G74),ISNUMBER(J74),J74<>0,H74=K74),G74/J74*100,"") | P74: =IF(AND(ISNUMBER(O74),ISNUMBER(I74)),ROUND(O74-I74,2),"")
A75: Grafito | B75: 2022 | C75: empresa | E75: ninguno | H75: toneladas | K75: toneladas | L75: CAMIMEX no desglosa | N75: Caso de contraste | O75: =IF(AND(ISNUMBER(G75),ISNUMBER(J75),J75<>0,H75=K75),G75/J75*100,"") | P75: =IF(AND(ISNUMBER(O75),ISNUMBER(I75)),ROUND(O75-I75,2),"")
A76: Grafito | B76: 2023 | C76: empresa | E76: ninguno | H76: toneladas | K76: toneladas | L76: CAMIMEX no desglosa | N76: Caso de contraste | O76: =IF(AND(ISNUMBER(G76),ISNUMBER(J76),J76<>0,H76=K76),G76/J76*100,"") | P76: =IF(AND(ISNUMBER(O76),ISNUMBER(I76)),ROUND(O76-I76,2),"")
A77: Grafito | B77: 2024 | C77: empresa | E77: ninguno | H77: toneladas | K77: toneladas | L77: CAMIMEX no desglosa | N77: Caso de contraste | O77: =IF(AND(ISNUMBER(G77),ISNUMBER(J77),J77<>0,H77=K77),G77/J77*100,"") | P77: =IF(AND(ISNUMBER(O77),ISNUMBER(I77)),ROUND(O77-I77,2),"")
A78: Manganeso | B78: 2020 | C78: empresa | E78: Compania Minera Autlan | H78: toneladas | I78: 100 | K78: toneladas | L78: Informe CAMIMEX | N78: Productor unico nacional (monopolio 1993-2025) | O78: =IF(AND(ISNUMBER(G78),ISNUMBER(J78),J78<>0,H78=K78),G78/J78*100,"") | P78: =IF(AND(ISNUMBER(O78),ISNUMBER(I78)),ROUND(O78-I78,2),"")
A79: Manganeso | B79: 2021 | C79: empresa | E79: Compania Minera Autlan | H79: toneladas | I79: 100 | K79: toneladas | L79: Informe CAMIMEX | N79: Productor unico nacional (monopolio 1993-2025) | O79: =IF(AND(ISNUMBER(G79),ISNUMBER(J79),J79<>0,H79=K79),G79/J79*100,"") | P79: =IF(AND(ISNUMBER(O79),ISNUMBER(I79)),ROUND(O79-I79,2),"")
A80: Manganeso | B80: 2022 | C80: empresa | E80: Compania Minera Autlan | H80: toneladas | I80: 100 | K80: toneladas | L80: Informe CAMIMEX | N80: Productor unico nacional (monopolio 1993-2025) | O80: =IF(AND(ISNUMBER(G80),ISNUMBER(J80),J80<>0,H80=K80),G80/J80*100,"") | P80: =IF(AND(ISNUMBER(O80),ISNUMBER(I80)),ROUND(O80-I80,2),"")
A81: Manganeso | B81: 2023 | C81: empresa | E81: Compania Minera Autlan | H81: toneladas | I81: 100 | K81: toneladas | L81: Informe CAMIMEX | N81: Productor unico nacional (monopolio 1993-2025) | O81: =IF(AND(ISNUMBER(G81),ISNUMBER(J81),J81<>0,H81=K81),G81/J81*100,"") | P81: =IF(AND(ISNUMBER(O81),ISNUMBER(I81)),ROUND(O81-I81,2),"")
A82: Manganeso | B82: 2024 | C82: empresa | E82: Compania Minera Autlan | H82: toneladas | I82: 100 | K82: toneladas | L82: Informe CAMIMEX | N82: Productor unico nacional (monopolio 1993-2025) | O82: =IF(AND(ISNUMBER(G82),ISNUMBER(J82),J82<>0,H82=K82),G82/J82*100,"") | P82: =IF(AND(ISNUMBER(O82),ISNUMBER(I82)),ROUND(O82-I82,2),"")
A83: Oro | B83: 2021 | C83: empresa | E83: top5 | I83: 57 | J83: 4010 | K83: miles oz | L83: Informe CAMIMEX 2022 | M83: 32 | N83: Narrativa: top-5 (Fresnillo Newmont Torex Agnico Equinox) = 57% nacional | O83: =IF(AND(ISNUMBER(G83),ISNUMBER(J83),J83<>0,H83=K83),G83/J83*100,"") | P83: =IF(AND(ISNUMBER(O83),ISNUMBER(I83)),ROUND(O83-I83,2),"")
A84: Oro | B84: 2021 | C84: mina | D84: Concheno | E84: Minera Frisco | F84: Chih. | G84: 50.07 | H84: miles oz | J84: 4010 | K84: miles oz | L84: Informe CAMIMEX 2022 | M84: 32 | N84: Top-15 suma 2753.42 | O84: =IF(AND(ISNUMBER(G84),ISNUMBER(J84),J84<>0,H84=K84),G84/J84*100,"") | P84: =IF(AND(ISNUMBER(O84),ISNUMBER(I84)),ROUND(O84-I84,2),"")
A85: Oro | B85: 2021 | C85: mina | D85: Dolores | E85: Pan American Silver | F85: Chih. | G85: 160.1 | H85: miles oz | J85: 4010 | K85: miles oz | L85: Informe CAMIMEX 2022 | M85: 32 | O85: =IF(AND(ISNUMBER(G85),ISNUMBER(J85),J85<>0,H85=K85),G85/J85*100,"") | P85: =IF(AND(ISNUMBER(O85),ISNUMBER(I85)),ROUND(O85-I85,2),"")
A86: Oro | B86: 2021 | C86: mina | D86: El Herrero | E86: Minas de Bacis | F86: Dgo. | G86: 66.05 | H86: miles oz | J86: 4010 | K86: miles oz | L86: Informe CAMIMEX 2022 | M86: 32 | O86: =IF(AND(ISNUMBER(G86),ISNUMBER(J86),J86<>0,H86=K86),G86/J86*100,"") | P86: =IF(AND(ISNUMBER(O86),ISNUMBER(I86)),ROUND(O86-I86,2),"")
A87: Oro | B87: 2021 | C87: mina | D87: La Colorada | E87: Argonaut Gold | F87: Son. | G87: 64.86 | H87: miles oz | J87: 4010 | K87: miles oz | L87: Informe CAMIMEX 2022 | M87: 32 | O87: =IF(AND(ISNUMBER(G87),ISNUMBER(J87),J87<>0,H87=K87),G87/J87*100,"") | P87: =IF(AND(ISNUMBER(O87),ISNUMBER(I87)),ROUND(O87-I87,2),"")
A88: Oro | B88: 2021 | C88: mina | D88: La Herradura | E88: Fresnillo plc | F88: Son. | G88: 421.54 | H88: miles oz | J88: 4010 | K88: miles oz | L88: Informe CAMIMEX 2022 | M88: 32 | O88: =IF(AND(ISNUMBER(G88),ISNUMBER(J88),J88<>0,H88=K88),G88/J88*100,"") | P88: =IF(AND(ISNUMBER(O88),ISNUMBER(I88)),ROUND(O88-I88,2),"")
A89: Oro | B89: 2021 | C89: mina | D89: Limon-Guajes | E89: Torex Gold | F89: Gro. | G89: 468.2 | H89: miles oz | J89: 4010 | K89: miles oz | L89: Informe CAMIMEX 2022 | M89: 32 | O89: =IF(AND(ISNUMBER(G89),ISNUMBER(J89),J89<>0,H89=K89),G89/J89*100,"") | P89: =IF(AND(ISNUMBER(O89),ISNUMBER(I89)),ROUND(O89-I89,2),"")
A90: Oro | B90: 2021 | C90: mina | D90: Los Filos | E90: Equinox Gold | F90: Gro. | G90: 144.1 | H90: miles oz | J90: 4010 | K90: miles oz | L90: Informe CAMIMEX 2022 | M90: 32 | O90: =IF(AND(ISNUMBER(G90),ISNUMBER(J90),J90<>0,H90=K90),G90/J90*100,"") | P90: =IF(AND(ISNUMBER(O90),ISNUMBER(I90)),ROUND(O90-I90,2),"")
A91: Oro | B91: 2021 | C91: mina | D91: Mulatos | E91: Alamos Gold | F91: Son. | G91: 121.3 | H91: miles oz | J91: 4010 | K91: miles oz | L91: Informe CAMIMEX 2022 | M91: 32 | O91: =IF(AND(ISNUMBER(G91),ISNUMBER(J91),J91<>0,H91=K91),G91/J91*100,"") | P91: =IF(AND(ISNUMBER(O91),ISNUMBER(I91)),ROUND(O91-I91,2),"")
A92: Oro | B92: 2021 | C92: mina | D92: Noche Buena | E92: Fresnillo plc | F92: Son. | G92: 96.84 | H92: miles oz | J92: 4010 | K92: miles oz | L92: Informe CAMIMEX 2022 | M92: 32 | O92: =IF(AND(ISNUMBER(G92),ISNUMBER(J92),J92<>0,H92=K92),G92/J92*100,"") | P92: =IF(AND(ISNUMBER(O92),ISNUMBER(I92)),ROUND(O92-I92,2),"")
A93: Oro | B93: 2021 | C93: mina | D93: Palmarejo | E93: Coeur Mining | F93: Chih. | G93: 109.2 | H93: miles oz | J93: 4010 | K93: miles oz | L93: Informe CAMIMEX 2022 | M93: 32 | O93: =IF(AND(ISNUMBER(G93),ISNUMBER(J93),J93<>0,H93=K93),G93/J93*100,"") | P93: =IF(AND(ISNUMBER(O93),ISNUMBER(I93)),ROUND(O93-I93,2),"")
A94: Oro | B94: 2021 | C94: mina | D94: Penasquito | E94: Newmont | F94: Zac. | G94: 685.92 | H94: miles oz | J94: 4010 | K94: miles oz | L94: Informe CAMIMEX 2022 | M94: 32 | N94: Tabla top-15 verificada en imagen | O94: =IF(AND(ISNUMBER(G94),ISNUMBER(J94),J94<>0,H94=K94),G94/J94*100,"") | P94: =IF(AND(ISNUMBER(O94),ISNUMBER(I94)),ROUND(O94-I94,2),"")
A95: Oro | B95: 2021 | C95: mina | D95: Pinos Altos | E95: Agnico Eagle Mines | F95: Chih. | G95: 139.73 | H95: miles oz | J95: 4010 | K95: miles oz | L95: Informe CAMIMEX 2022 | M95: 32 | O95: =IF(AND(ISNUMBER(G95),ISNUMBER(J95),J95<>0,H95=K95),G95/J95*100,"") | P95: =IF(AND(ISNUMBER(O95),ISNUMBER(I95)),ROUND(O95-I95,2),"")
A96: Oro | B96: 2021 | C96: mina | D96: San Dimas | E96: First Majestic Silver | F96: Dgo. | G96: 81.24 | H96: miles oz | J96: 4010 | K96: miles oz | L96: Informe CAMIMEX 2022 | M96: 32 | O96: =IF(AND(ISNUMBER(G96),ISNUMBER(J96),J96<>0,H96=K96),G96/J96*100,"") | P96: =IF(AND(ISNUMBER(O96),ISNUMBER(I96)),ROUND(O96-I96,2),"")
A97: Oro | B97: 2021 | C97: mina | D97: San Julian | E97: Fresnillo plc | F97: Chih. | G97: 55.85 | H97: miles oz | J97: 4010 | K97: miles oz | L97: Informe CAMIMEX 2022 | M97: 32 | O97: =IF(AND(ISNUMBER(G97),ISNUMBER(J97),J97<>0,H97=K97),G97/J97*100,"") | P97: =IF(AND(ISNUMBER(O97),ISNUMBER(I97)),ROUND(O97-I97,2),"")
A98: Oro | B98: 2021 | C98: mina | D98: Saucito | E98: Fresnillo plc | F98: Zac. | G98: 88.44 | H98: miles oz | J98: 4010 | K98: miles oz | L98: Informe CAMIMEX 2022 | M98: 32 | O98: =IF(AND(ISNUMBER(G98),ISNUMBER(J98),J98<>0,H98=K98),G98/J98*100,"") | P98: =IF(AND(ISNUMBER(O98),ISNUMBER(I98)),ROUND(O98-I98,2),"")
A99: Oro | B99: 2022 | C99: empresa | E99: Fresnillo plc | J99: 4770 | K99: miles oz | L99: Informe CAMIMEX 2023 | M99: 37 | N99: Ranking narrativo: Fresnillo mayor productor (sin % publicado) | O99: =IF(AND(ISNUMBER(G99),ISNUMBER(J99),J99<>0,H99=K99),G99/J99*100,"") | P99: =IF(AND(ISNUMBER(O99),ISNUMBER(I99)),ROUND(O99-I99,2),"")
A100: Oro | B100: 2022 | C100: mina | D100: Dolores | E100: Pan American Silver | F100: Chih. | G100: 136.9 | H100: miles oz | J100: 4770 | K100: miles oz | L100: Informe CAMIMEX 2023 | M100: 37 | O100: =IF(AND(ISNUMBER(G100),ISNUMBER(J100),J100<>0,H100=K100),G100/J100*100,"") | P100: =IF(AND(ISNUMBER(O100),ISNUMBER(I100)),ROUND(O100-I100,2),"")
A101: Oro | B101: 2022 | C101: mina | D101: El Herrero | E101: Minas de Bacis | F101: Dgo. | G101: 52.7 | H101: miles oz | J101: 4770 | K101: miles oz | L101: Informe CAMIMEX 2023 | M101: 37 | N101: Top-15 suma 2519.9 | O101: =IF(AND(ISNUMBER(G101),ISNUMBER(J101),J101<>0,H101=K101),G101/J101*100,"") | P101: =IF(AND(ISNUMBER(O101),ISNUMBER(I101)),ROUND(O101-I101,2),"")
A102: Oro | B102: 2022 | C102: mina | D102: La Herradura | E102: Fresnillo plc | F102: Son. | G102: 349.7 | H102: miles oz | J102: 4770 | K102: miles oz | L102: Informe CAMIMEX 2023 | M102: 37 | O102: =IF(AND(ISNUMBER(G102),ISNUMBER(J102),J102<>0,H102=K102),G102/J102*100,"") | P102: =IF(AND(ISNUMBER(O102),ISNUMBER(I102)),ROUND(O102-I102,2),"")
...

Sheet 08 HHI serie
A1: HHI - serie consolidada por mineral-anio (1994-2024)
A2: HHI = suma de cuotas al cuadrado (0-10000). Cada fila trae su 'metodo' y 'cobertura_pct': 2021-2024 por mina (comparable); 2004-2020 por regimen (cota inferior); 1994-2003 reconstruido de USGS MYB. Los niveles 1994-2020 se leen por TRAYECTORIA, no por nivel exacto. Resultado del script (incluye residual atomistico).
A3: mineral | B3: anio | C3: hhi | D3: cobertura_pct | E3: lider | F3: metodo | G3: nota
A4: cobre | B4: 1997 | C4: 6241 | D4: 79 | E4: Grupo Mexico ~79% | F4: lider-grupo Grupo Mexico (narrativa USGS) | G4: USGS MYB Mexico 1994-2003, Tabla 2 + narrativa: La Caridad+Cananea 79% del cobre mina nacional; cota inferior; nivel grupo (no comparable con 2004+)
A5: cobre | B5: 1998 | C5: 6724 | D5: 82 | E5: Grupo Mexico ~82% | F5: lider-grupo Grupo Mexico (narrativa USGS) | G5: USGS MYB Mexico 1994-2003, Tabla 2 + narrativa: La Caridad+Cananea 82% del cobre mina nacional; cota inferior; nivel grupo (no comparable con 2004+)
A6: cobre | B6: 2000 | C6: 6400 | D6: 80 | E6: Grupo Mexico ~80% | F6: lider-grupo Grupo Mexico (narrativa USGS) | G6: USGS MYB Mexico 1994-2003, Tabla 2 + narrativa: La Caridad+Cananea 80% del cobre mina nacional; cota inferior; nivel grupo (no comparable con 2004+)
A7: cobre | B7: 2001 | C7: 7225 | D7: 85 | E7: Grupo Mexico ~85% | F7: lider-grupo Grupo Mexico (narrativa USGS) | G7: USGS MYB Mexico 1994-2003, Tabla 2 + narrativa: La Caridad+Cananea 85% del cobre mina nacional; cota inferior; nivel grupo (no comparable con 2004+)
A8: cobre | B8: 2002 | C8: 6889 | D8: 83 | E8: Grupo Mexico ~83% | F8: lider-grupo Grupo Mexico (narrativa USGS) | G8: USGS MYB Mexico 1994-2003, Tabla 2 + narrativa: La Caridad+Cananea 83% del cobre mina nacional; cota inferior; nivel grupo (no comparable con 2004+)
A9: cobre | B9: 2003 | C9: 6400 | D9: 80 | E9: Grupo Mexico ~80% | F9: lider-grupo Grupo Mexico (narrativa USGS) | G9: USGS MYB Mexico 1994-2003, Tabla 2 + narrativa: La Caridad+Cananea 80% del cobre mina nacional; cota inferior; nivel grupo (no comparable con 2004+)
A10: cobre | B10: 2005 | C10: 7500 | D10: 87 | E10: Grupo Mexico 86.6% | F10: lider/grupos conocidos + residual atomistico (aprox.) | G10: cota inferior: solo participaciones documentadas; residual tratado como atomistico
A11: cobre | B11: 2006 | C11: 6806 | D11: 82 | E11: Grupo Mexico 82.5% | F11: lider/grupos conocidos + residual atomistico (aprox.) | G11: cota inferior: solo participaciones documentadas; residual tratado como atomistico
A12: cobre | B12: 2008 | C12: 2570 | D12: 51 | E12: Grupo Mexico 50.7% | F12: lider/grupos conocidos + residual atomistico (aprox.) | G12: cota inferior: solo participaciones documentadas; residual tratado como atomistico
A13: cobre | B13: 2010 | C13: 2621 | D13: 51 | E13: Grupo Mexico 51.2% | F13: lider/grupos conocidos + residual atomistico (aprox.) | G13: cota inferior: solo participaciones documentadas; residual tratado como atomistico
A14: cobre | B14: 2011 | C14: 4356 | D14: 66 | E14: Grupo Mexico 66.0% | F14: lider/grupos conocidos + residual atomistico (aprox.) | G14: cota inferior: solo participaciones documentadas; residual tratado como atomistico
A15: cobre | B15: 2013 | C15: 4147 | D15: 64 | E15: Grupo Mexico 64.4% | F15: lider/grupos conocidos + residual atomistico (aprox.) | G15: cota inferior: solo participaciones documentadas; residual tratado como atomistico
... A18: cobre | B18: 2020 | C18: 6209 | D18: 79 | E18: Grupo Mexico 78.8% | F18: lider/grupos conocidos + residual atomistico (aprox.) | G18: cota inferior: solo participaciones documentadas; residual tratado como atomistico
A19: cobre | B19: 2021 | C19: 3841 | D19: 76 | E19: Grupo Mexico 62% | F19: mina->grupo vs total nacional
A20: cobre | B20: 2022 | C20: 3362 | D20: 75 | E20: Grupo Mexico 58% | F20: mina->grupo vs total nacional
A21: cobre | B21: 2023 | C21: 3764 | D21: 77 | E21: Grupo Mexico 61% | F21: mina->grupo vs total nacional
A22: cobre | B22: 2024 | C22: 3557 | D22: 74 | E22: Grupo Mexico 59% | F22: mina->grupo vs total nacional (total cobre estimado) | G22: detalle por mina 2024 (CAMIMEX/SGM); total nacional 2024 estimado ~755,000 t (grafico SGM)
A23: zinc | B23: 2009 | C23: 1149 | D23: 34 | E23: Industrias Penoles 33.9% | F23: lider/grupos conocidos + residual atomistico (aprox.) | G23: cota inferior: solo participaciones documentadas; residual tratado como atomistico
A24: zinc | B24: 2010 | C24: 773 | D24: 28 | E24: Industrias Penoles 27.8% | F24: lider/grupos conocidos + residual atomistico (aprox.) | G24: cota inferior: solo participaciones documentadas; residual tratado como atomistico
A25: zinc | B25: 2011 | C25: 635 | D25: 25 | E25: Industrias Penoles 25.2% | F25: lider/grupos conocidos + residual atomistico (aprox.) | G25: cota inferior: solo participaciones documentadas; residual tratado como atomistico
A26: zinc | B26: 2012 | C26: 566 | D26: 24 | E26: Industrias Penoles 23.8% | F26: lider/grupos conocidos + residual atomistico (aprox.) | G26: cota inferior: solo participaciones documentadas; residual tratado como atomistico
A27: zinc | B27: 2015 | C27: 1024 | D27: 32 | E27: Industrias Penoles 32.0% | F27: lider/grupos conocidos + residual atomistico (aprox.) | G27: cota inferior: solo participaciones documentadas; residual tratado como atomistico
A28: zinc | B28: 2020 | C28: 692 | D28: 26 | E28: Industrias Penoles 26.3% | F28: lider/grupos conocidos + residual atomistico (aprox.) | G28: cota inferior: solo participaciones documentadas; residual tratado como atomistico
A29: zinc | B29: 2021 | C29: 1591 | D29: 83 | E29: Newmont 28% | F29: mina->grupo vs total nacional
A30: zinc | B30: 2022 | C30: 1199 | D30: 80 | E30: Newmont 23% | F30: mina->grupo vs total nacional
A31: zinc | B31: 2023 | C31: 1551 | D31: 87 | E31: Industrias Penoles 28% | F31: mina->grupo vs total nacional
A32: zinc | B32: 2024 | C32: 1683 | D32: 81 | E32: Newmont 33% | F32: mina->grupo vs total nacional | G32: detalle por mina 2024 (CAMIMEX/SGM)
A33: plomo | B33: 2010 | C33: 524 | D33: 23 | E33: Goldcorp 22.9% | F33: lider/grupos conocidos + residual atomistico (aprox.) | G33: cota inferior: solo participaciones documentadas; residual tratado como atomistico
A34: plomo | B34: 2011 | C34: 986 | D34: 31 | E34: Goldcorp 31.4% | F34: lider/grupos conocidos + residual atomistico (aprox.) | G34: cota inferior: solo participaciones documentadas; residual tratado como atomistico
A35: plomo | B35: 2012 | C35: 858 | D35: 29 | E35: Goldcorp 29.3% | F35: lider/grupos conocidos + residual atomistico (aprox.) | G35: cota inferior: solo participaciones documentadas; residual tratado como atomistico
A36: plomo | B36: 2013 | C36: 812 | D36: 28 | E36: Goldcorp 28.5% | F36: lider/grupos conocidos + residual atomistico (aprox.) | G36: cota inferior: solo participaciones documentadas; residual tratado como atomistico
A37: plomo | B37: 2015 | C37: 961 | D37: 31 | E37: Goldcorp 31.0% | F37: lider/grupos conocidos + residual atomistico (aprox.) | G37: cota inferior: solo participaciones documentadas; residual tratado como atomistico
A38: plomo | B38: 2016 | C38: 441 | D38: 21 | E38: Goldcorp 21.0% | F38: lider/grupos conocidos + residual atomistico (aprox.) | G38: cota inferior: solo participaciones documentadas; residual tratado como atomistico
A39: plomo | B39: 2020 | C39: 973 | D39: 31 | E39: Newmont 31.2% | F39: lider/grupos conocidos + residual atomistico (aprox.) | G39: cota inferior: solo participaciones documentadas; residual tratado como atomistico
A40: plomo | B40: 2021 | C40: 1448 | D40: 80 | E40: Newmont 29% | F40: mina->grupo vs total nacional
A41: plomo | B41: 2022 | C41: 1090 | D41: 76 | E41: Newmont 25% | F41: mina->grupo vs total nacional
A42: plomo | B42: 2023 | C42: 1823 | D42: 100 | E42: Newmont 28% | F42: mina->grupo vs total nacional
A43: plomo | B43: 2024 | C43: 2465 | D43: 94 | E43: Newmont 41% | F43: mina->grupo vs total nacional | G43: detalle por mina 2024 (CAMIMEX/SGM)
A44: oro | B44: 2004 | C44: 2043 | D44: 45 | E44: Industrias Penoles 45.2% | F44: lider/grupos conocidos + residual atomistico (aprox.) | G44: cota inferior: solo participaciones documentadas; residual tratado como atomistico
A45: oro | B45: 2005 | C45: 1197 | D45: 35 | E45: Industrias Penoles 34.6% | F45: lider/grupos conocidos + residual atomistico (aprox.) | G45: cota inferior: solo participaciones documentadas; residual tratado como atomistico
A46: oro | B46: 2007 | C46: 702 | D46: 26 | E46: Industrias Penoles 26.5% | F46: lider/grupos conocidos + residual atomistico (aprox.) | G46: cota inferior: solo participaciones documentadas; residual tratado como atomistico
A47: oro | B47: 2008 | C47: 1296 | D47: 36 | E47: Goldcorp 36.0% | F47: lider/grupos conocidos + residual atomistico (aprox.) | G47: cota inferior: solo participaciones documentadas; residual tratado como atomistico
A48: oro | B48: 2009 | C48: 1296 | D48: 36 | E48: Goldcorp 36.0% | F48: lider/grupos conocidos + residual atomistico (aprox.) | G48: cota inferior: solo participaciones documentadas; residual tratado como atomistico
A49: oro | B49: 2010 | C49: 708 | D49: 27 | E49: Goldcorp 26.6% | F49: lider/grupos conocidos + residual atomistico (aprox.) | G49: cota inferior: solo participaciones documentadas; residual tratado como atomistico
A50: oro | B50: 2011 | C50: 590 | D50: 24 | E50: Goldcorp 24.3% | F50: lider/grupos conocidos + residual atomistico (aprox.) | G50: cota inferior: solo participaciones documentadas; residual tratado como atomistico
A51: oro | B51: 2012 | C51: 676 | D51: 26 | E51: Goldcorp 26.0% | F51: lider/grupos conocidos + residual atomistico (aprox.) | G51: cota inferior: solo participaciones documentadas; residual tratado como atomistico
A52: oro | B52: 2021 | C52: 771 | D52: 69 | E52: Newmont 17% | F52: mina->grupo vs total nacional
A53: oro | B53: 2022 | C53: 409 | D53: 53 | E53: Newmont 12% | F53: mina->grupo vs total nacional
A54: oro | B54: 2023 | C54: 312 | D54: 49 | E54: Fresnillo plc 11% | F54: mina->grupo vs total nacional
A55: oro | B55: 2024 | C55: 429 | D55: 53 | E55: Torex Gold 12% | F55: mina->grupo vs total nacional | G55: detalle por mina 2024 (CAMIMEX/SGM)
A56: plata | B56: 2005 | C56: 1318 | D56: 36 | E56: Industrias Penoles 36.3% | F56: lider/grupos conocidos + residual atomistico (aprox.) | G56: cota inferior: solo participaciones documentadas; residual tratado como atomistico
A57: plata | B57: 2006 | C57: 1218 | D57: 35 | E57: Industrias Penoles 34.9% | F57: lider/grupos conocidos + residual atomistico (aprox.) | G57: cota inferior: solo participaciones documentadas; residual tratado como atomistico
A58: plata | B58: 2007 | C58: 1109 | D58: 33 | E58: Industrias Penoles 33.3% | F58: lider/grupos conocidos + residual atomistico (aprox.) | G58: cota inferior: solo participaciones documentadas; residual tratado como atomistico
A59: plata | B59: 2008 | C59: 1005 | D59: 32 | E59: Fresnillo plc 31.7% | F59: lider/grupos conocidos + residual atomistico (aprox.) | G59: cota inferior: solo participaciones documentadas; residual tratado como atomistico
A60: plata | B60: 2009 | C60: 1102 | D60: 33 | E60: Fresnillo plc 33.2% | F60: lider/grupos conocidos + residual atomistico (aprox.) | G60: cota inferior: solo participaciones documentadas; residual tratado como atomistico
A61: plata | B61: 2010 | C61: 640 | D61: 25 | E61: Fresnillo plc 25.3% | F61: lider/grupos conocidos + residual atomistico (aprox.) | G61: cota inferior: solo participaciones documentadas; residual tratado como atomistico
A62: plata | B62: 2011 | C62: 610 | D62: 25 | E62: Fresnillo plc 24.7% | F62: lider/grupos conocidos + residual atomistico (aprox.) | G62: cota inferior: solo participaciones documentadas; residual tratado como atomistico
A63: plata | B63: 2012 | C63: 562 | D63: 24 | E63: Fresnillo plc 23.7% | F63: lider/grupos conocidos + residual atomistico (aprox.) | G63: cota inferior: solo participaciones documentadas; residual tratado como atomistico
A64: plata | B64: 2018 | C64: 1109 | D64: 33 | E64: Fresnillo plc 33.3% | F64: lider/grupos conocidos + residual atomistico (aprox.) | G64: cota inferior: solo participaciones documentadas; residual tratado como atomistico
A65: plata | B65: 2019 | C65: 762 | D65: 28 | E65: Fresnillo plc 27.6% | F65: lider/grupos conocidos + residual atomistico (aprox.) | G65: cota inferior: solo participaciones documentadas; residual tratado como atomistico
A66: plata | B66: 2020 | C66: 864 | D66: 29 | E66: Fresnillo plc 29.4% | F66: lider/grupos conocidos + residual atomistico (aprox.) | G66: cota inferior: solo participaciones documentadas; residual tratado como atomistico
A67: plata | B67: 2021 | C67: 926 | D67: 69 | E67: Fresnillo plc 24% | F67: mina->grupo vs total nacional
A68: plata | B68: 2022 | C68: 820 | D68: 64 | E68: Fresnillo plc 23% | F68: mina->grupo vs total nacional
A69: plata | B69: 2023 | C69: 914 | D69: 68 | E69: Fresnillo plc 27% | F69: mina->grupo vs total nacional
A70: plata | B70: 2024 | C70: 1147 | D70: 63 | E70: Fresnillo plc 27% | F70: mina->grupo vs total nacional | G70: detalle por mina 2024 (CAMIMEX/SGM)
A71: barita | B71: 2004 | C71: 3069 | D71: 55 | E71: Baramin 55.4% | F71: lider/grupos conocidos + residual atomistico (aprox.) | G71: cota inferior: solo participaciones documentadas; residual tratado como atomistico
A72: barita | B72: 2006 | C72: 5655 | D72: 75 | E72: Baramin 75.2% | F72: lider/grupos conocidos + residual atomistico (aprox.) | G72: cota inferior: solo participaciones documentadas; residual tratado como atomistico
A73: barita | B73: 2007 | C73: 3576 | D73: 60 | E73: Baramin 59.8% | F73: lider/grupos conocidos + residual atomistico (aprox.) | G73: cota inferior: solo participaciones documentadas; residual tratado como atomistico
A74: barita | B74: 2009 | C74: 6257 | D74: 79 | E74: Baramin 79.1% | F74: lider/grupos conocidos + residual atomistico (aprox.) | G74: cota inferior: solo participaciones documentadas; residual tratado como atomistico
A75: barita | B75: 2011 | C75: 5141 | D75: 72 | E75: Baramin 71.7% | F75: lider/grupos conocidos + residual atomistico (aprox.) | G75: cota inferior: solo participaciones documentadas; residual tratado como atomistico
A76: barita | B76: 2012 | C76: 10000 | D76: 100 | E76: Baramin 100.0% | F76: lider/grupos conocidos + residual atomistico (aprox.) | G76: cota inferior: solo participaciones documentadas; residual tratado como atomistico
A77: barita | B77: 2013 | C77: 7022 | D77: 84 | E77: Baramin 83.8% | F77: lider/grupos conocidos + residual atomistico (aprox.) | G77: cota inferior: solo participaciones documentadas; residual tratado como atomistico
A78: barita | B78: 2014 | C78: 10000 | D78: 100 | E78: Baramin 100.0% | F78: lider/grupos conocidos + residual atomistico (aprox.) | G78: cota inferior: solo participaciones documentadas; residual tratado como atomistico
A79: barita | B79: 2017 | C79: 4638 | D79: 68 | E79: Baramin 68.1% | F79: lider/grupos conocidos + residual atomistico (aprox.) | G79: cota inferior: solo participaciones documentadas; residual tratado como atomistico
A80: barita | B80: 2018 | C80: 6400 | D80: 80 | E80: Baramin 80.0% | F80: lider/grupos conocidos + residual atomistico (aprox.) | G80: cota inferior: solo participaciones documentadas; residual tratado como atomistico
A81: barita | B81: 2019 | C81: 8317 | D81: 91 | E81: Baramin 91.2% | F81: lider/grupos conocidos + residual atomistico (aprox.) | G81: cota inferior: solo participaciones documentadas; residual tratado como atomistico
A82: barita | B82: 2020 | C82: 3982 | D82: 63 | E82: Baramin 63.1% | F82: lider/grupos conocidos + residual atomistico (aprox.) | G82: cota inferior: solo participaciones documentadas; residual tratado como atomistico
A83: barita | B83: 2021 | C83: 6779 | D83: 82 | E83: Baramin 82% | F83: mina->grupo vs total nacional
A84: barita | B84: 2022 | C84: 2479 | D84: 50 | E84: Baramin 50% | F84: mina->grupo vs total nacional
A85: barita | B85: 2023 | C85: 1380 | D85: 37 | E85: Baramin 37% | F85: mina->grupo vs total nacional
A86: barita | B86: 2024 | C86: 605 | D86: 25 | E86: Baramin 25% | F86: lider + residual atomistico (aprox., solo lider 2024) | G86: cota inferior: solo participacion del lider disponible en 2024
A87: silice | B87: 2006 | C87: 5271 | D87: 73 | E87: Grupo Materias Primas 72.6% | F87: lider/grupos conocidos + residual atomistico (aprox.) | G87: cota inferior: solo participaciones documentadas; residual tratado como atomistico
A88: silice | B88: 2007 | C88: 4409 | D88: 66 | E88: Grupo Materias Primas 66.4% | F88: lider/grupos conocidos + residual atomistico (aprox.) | G88: cota inferior: solo participaciones documentadas; residual tratado como atomistico
A89: silice | B89: 2009 | C89: 4147 | D89: 64 | E89: Grupo Materias Primas 64.4% | F89: lider/grupos conocidos + residual atomistico (aprox.) | G89: cota inferior: solo participaciones documentadas; residual tratado como atomistico
A90: silice | B90: 2010 | C90: 4251 | D90: 65 | E90: Grupo Materias Primas 65.2% | F90: lider/grupos conocidos + residual atomistico (aprox.) | G90: cota inferior: solo participaciones documentadas; residual tratado como atomistico
A91: silice | B91: 2011 | C91: 5242 | D91: 72 | E91: Grupo Materias Primas 72.4% | F91: lider/grupos conocidos + residual atomistico (aprox.) | G91: cota inferior: solo participaciones documentadas; residual tratado como atomistico
A92: silice | B92: 2012 | C92: 2884 | D92: 54 | E92: Grupo Materias Primas 53.7% | F92: lider/grupos conocidos + residual atomistico (aprox.) | G92: cota inferior: solo participaciones documentadas; residual tratado como atomistico
A93: silice | B93: 2013 | C93: 4356 | D93: 66 | E93: Grupo Materias Primas 66.0% | F93: lider/grupos conocidos + residual atomistico (aprox.) | G93: cota inferior: solo participaciones documentadas; residual tratado como atomistico
A94: silice | B94: 2018 | C94: 10000 | D94: 100 | E94: Grupo Materias Primas 100.0% | F94: lider/grupos conocidos + residual atomistico (aprox.) | G94: cota inferior: solo participaciones documentadas; residual tratado como atomistico
A95: silice | B95: 2019 | C95: 10000 | D95: 100 | E95: Grupo Materias Primas (Covia) 100.0% | F95: lider/grupos conocidos + residual atomistico (aprox.) | G95: cota inferior: solo participaciones documentadas; residual tratado como atomistico
A96: silice | B96: 2020 | C96: 8519 | D96: 92 | E96: Grupo Materias Primas (Covia) 92.3% | F96: lider/grupos conocidos + residual atomistico (aprox.) | G96: cota inferior: solo participaciones documentadas; residual tratado como atomistico
A97: silice | B97: 2021 | C97: 9742 | D97: 99 | E97: Grupo Materias Primas (Covia) 99% | F97: mina->grupo vs total nacional
A98: silice | B98: 2022 | C98: 5519 | D98: 74 | E98: Grupo Materias Primas (Covia) 74% | F98: mina->grupo vs total nacional
A99: silice | B99: 2023 | C99: 6670 | D99: 82 | E99: Grupo Materias Primas (Covia) 82% | F99: mina->grupo vs total nacional
A100: fluorita | B100: 1994 | C100: 6001 | D100: 95 | E100: Cia. Minera Las Cuevas ~75-80% | F100: lider dominante + fringe (narrativa USGS) | G100: USGS MYB Mexico 1994-2003, Tabla 2 + narrativa: Las Cuevas ~75% (1999/2001), 76% (2002), >80% (2003); cota inferior
A101: fluorita | B101: 1995 | C101: 6001 | D101: 95 | E101: Cia. Minera Las Cuevas ~75-80% | F101: lider dominante + fringe (narrativa USGS) | G101: USGS MYB Mexico 1994-2003, Tabla 2 + narrativa: Las Cuevas ~75% (1999/2001), 76% (2002), >80% (2003); cota inferior
A102: fluorita | B102: 1996 | C102: 6001 | D102: 95 | E102: Cia. Minera Las Cuevas ~75-80% | F102: lider dominante + fringe (narrativa USGS) | G102: USGS MYB Mexico 1994-2003, Tabla 2 + narrativa: Las Cuevas ~75% (1999/2001), 76% (2002), >80% (2003); cota inferior
...

Sheet 09 CCV
A1: CCV - Coeficiente de captura de valor (serie 1992-2025)
A2: CCV = valor_unitario_E1 / precio_refinado_USGS ; valor_unitario_E1 = valor_export_E1 / peso_export_E1. Columnas verdes: recomputo con formula de Excel y diferencia vs valor almacenado. La columna 'dif vu' marca (>0) las ~5 filas en que el valor unitario se corrigio por tonelaje minimo/atipico (silice 2016, fluorita 2018/2020, grafito 2017/2018): ahi el vu limpio != valor/peso, a proposito. 'dif CCV' debe ser ~0. Informativo en metales base (Cu~0.22, Zn~0.30); NO informativo en oro/plata (artefacto de ley). 'fuente_numerador': propio vs espejo (CIF).
A3: mineral | B3: grupo_ccv | C3: anio | D3: hs_e1 | E3: valor_export_e1_usd | F3: peso_export_e1_t | G3: valor_unitario_export_usd_t | H3: precio_refinado_usgs_usd_t | I3: ccv | J3: fuente_numerador | K3: nota | L3: valor_unitario (=formula) | M3: dif vu | N3: CCV (=formula) | O3: dif CCV
A4: barita | B4: no metalico/industrial | C4: 1992 | D4: 251110 | E4: 1244000 | F4: 19904.52 | G4: 62.5 | H4: 51.8 | I4: 1.2065 | J4: propio | L4: =IF(F4=0,"",E4/F4) | M4: =IF(ISNUMBER(L4),ROUND(L4-G4,4),"") | N4: =IF(H4=0,"",G4/H4) | O4: =IF(ISNUMBER(N4),ROUND(N4-I4,4),"")
A5: barita | B5: no metalico/industrial | C5: 1993 | D5: 251110 | E5: 4213000 | F5: 68263.624 | G5: 61.72 | H5: 45.8 | I5: 1.3475 | J5: propio | L5: =IF(F5=0,"",E5/F5) | M5: =IF(ISNUMBER(L5),ROUND(L5-G5,4),"") | N5: =IF(H5=0,"",G5/H5) | O5: =IF(ISNUMBER(N5),ROUND(N5-I5,4),"")
A6: barita | B6: no metalico/industrial | C6: 1994 | D6: 251110 | E6: 4690693 | F6: 89615.144 | G6: 52.34 | H6: 38.8 | I6: 1.349 | J6: propio | L6: =IF(F6=0,"",E6/F6) | M6: =IF(ISNUMBER(L6),ROUND(L6-G6,4),"") | N6: =IF(H6=0,"",G6/H6) | O6: =IF(ISNUMBER(N6),ROUND(N6-I6,4),"")
A7: barita | B7: no metalico/industrial | C7: 1995 | D7: 251110 | E7: 6854000 | F7: 129536.18 | G7: 52.91 | H7: 42.9 | I7: 1.2334 | J7: propio | L7: =IF(F7=0,"",E7/F7) | M7: =IF(ISNUMBER(L7),ROUND(L7-G7,4),"") | N7: =IF(H7=0,"",G7/H7) | O7: =IF(ISNUMBER(N7),ROUND(N7-I7,4),"")
A8: barita | B8: no metalico/industrial | C8: 1996 | D8: 251110 | E8: 7762014 | F8: 124343.76 | G8: 62.42 | H8: 42.7 | I8: 1.4619 | J8: propio | L8: =IF(F8=0,"",E8/F8) | M8: =IF(ISNUMBER(L8),ROUND(L8-G8,4),"") | N8: =IF(H8=0,"",G8/H8) | O8: =IF(ISNUMBER(N8),ROUND(N8-I8,4),"")
A9: barita | B9: no metalico/industrial | C9: 1997 | D9: 251110 | E9: 4439673 | F9: 65292.48 | G9: 68 | H9: 46.2 | I9: 1.4718 | J9: propio | L9: =IF(F9=0,"",E9/F9) | M9: =IF(ISNUMBER(L9),ROUND(L9-G9,4),"") | N9: =IF(H9=0,"",G9/H9) | O9: =IF(ISNUMBER(N9),ROUND(N9-I9,4),"")
A10: barita | B10: no metalico/industrial | C10: 1998 | D10: 251110 | E10: 1469473 | F10: 18144.56 | G10: 80.99 | H10: 57.1 | I10: 1.4183 | J10: propio | L10: =IF(F10=0,"",E10/F10) | M10: =IF(ISNUMBER(L10),ROUND(L10-G10,4),"") | N10: =IF(H10=0,"",G10/H10) | O10: =IF(ISNUMBER(N10),ROUND(N10-I10,4),"")
A11: barita | B11: no metalico/industrial | C11: 1999 | D11: 251110 | E11: 1030666 | F11: 15367.835 | G11: 67.07 | H11: 52.5 | I11: 1.2775 | J11: propio | L11: =IF(F11=0,"",E11/F11) | M11: =IF(ISNUMBER(L11),ROUND(L11-G11,4),"") | N11: =IF(H11=0,"",G11/H11) | O11: =IF(ISNUMBER(N11),ROUND(N11-I11,4),"")
A12: barita | B12: no metalico/industrial | C12: 2000 | D12: 251110 | E12: 767826 | F12: 8081.87 | G12: 95.01 | H12: 46.3 | I12: 2.052 | J12: propio | L12: =IF(F12=0,"",E12/F12) | M12: =IF(ISNUMBER(L12),ROUND(L12-G12,4),"") | N12: =IF(H12=0,"",G12/H12) | O12: =IF(ISNUMBER(N12),ROUND(N12-I12,4),"")
A13: barita | B13: no metalico/industrial | C13: 2001 | D13: 251110 | E13: 560838 | F13: 3698.588 | G13: 151.64 | H13: 45.4 | I13: 3.34 | J13: propio | L13: =IF(F13=0,"",E13/F13) | M13: =IF(ISNUMBER(L13),ROUND(L13-G13,4),"") | N13: =IF(H13=0,"",G13/H13) | O13: =IF(ISNUMBER(N13),ROUND(N13-I13,4),"")
A14: barita | B14: no metalico/industrial | C14: 2002 | D14: 251110 | E14: 295067 | F14: 1972.292 | G14: 149.61 | H14: 46.6 | I14: 3.2104 | J14: propio | L14: =IF(F14=0,"",E14/F14) | M14: =IF(ISNUMBER(L14),ROUND(L14-G14,4),"") | N14: =IF(H14=0,"",G14/H14) | O14: =IF(ISNUMBER(N14),ROUND(N14-I14,4),"")
A15: barita | B15: no metalico/industrial | C15: 2003 | D15: 251110 | E15: 158568 | F15: 789.517 | G15: 200.84 | H15: 45.6 | I15: 4.4044 | J15: propio | L15: =IF(F15=0,"",E15/F15) | M15: =IF(ISNUMBER(L15),ROUND(L15-G15,4),"") | N15: =IF(H15=0,"",G15/H15) | O15: =IF(ISNUMBER(N15),ROUND(N15-I15,4),"")
... A25: barita | B25: no metalico/industrial | C25: 2013 | D25: 251110 | E25: 28863901 | F25: 285870.78 | G25: 100.97 | H25: 133 | I25: 0.7592 | J25: propio | L25: =IF(F25=0,"",E25/F25) | M25: =IF(ISNUMBER(L25),ROUND(L25-G25,4),"") | N25: =IF(H25=0,"",G25/H25) | O25: =IF(ISNUMBER(N25),ROUND(N25-I25,4),"")
A26: barita | B26: no metalico/industrial | C26: 2014 | D26: 251110 | E26: 41902901 | F26: 132223.31 | G26: 316.91 | H26: 130 | I26: 2.4378 | J26: espejo | K26: numerador por ESPEJO (importaciones de socios desde Mexico; CIF, posible sesgo al alza) | L26: =IF(F26=0,"",E26/F26) | M26: =IF(ISNUMBER(L26),ROUND(L26-G26,4),"") | N26: =IF(H26=0,"",G26/H26) | O26: =IF(ISNUMBER(N26),ROUND(N26-I26,4),"")
A27: barita | B27: no metalico/industrial | C27: 2015 | D27: 251110 | E27: 1595323 | F27: 6381.292 | G27: 250 | H27: 125 | I27: 2 | J27: propio | L27: =IF(F27=0,"",E27/F27) | M27: =IF(ISNUMBER(L27),ROUND(L27-G27,4),"") | N27: =IF(H27=0,"",G27/H27) | O27: =IF(ISNUMBER(N27),ROUND(N27-I27,4),"")
A28: barita | B28: no metalico/industrial | C28: 2016 | D28: 251110 | E28: 17601565 | F28: 139552.84 | G28: 126.13 | H28: 130 | I28: 0.9702 | J28: espejo | K28: numerador por ESPEJO (importaciones de socios desde Mexico; CIF, posible sesgo al alza) | L28: =IF(F28=0,"",E28/F28) | M28: =IF(ISNUMBER(L28),ROUND(L28-G28,4),"") | N28: =IF(H28=0,"",G28/H28) | O28: =IF(ISNUMBER(N28),ROUND(N28-I28,4),"")
A29: barita | B29: no metalico/industrial | C29: 2017 | D29: 251110 | E29: 41792987 | F29: 328307.02 | G29: 127.3 | H29: 100 | I29: 1.273 | J29: espejo | K29: numerador por ESPEJO (importaciones de socios desde Mexico; CIF, posible sesgo al alza) | L29: =IF(F29=0,"",E29/F29) | M29: =IF(ISNUMBER(L29),ROUND(L29-G29,4),"") | N29: =IF(H29=0,"",G29/H29) | O29: =IF(ISNUMBER(N29),ROUND(N29-I29,4),"")
A30: barita | B30: no metalico/industrial | C30: 2018 | D30: 251110 | E30: 46377152 | F30: 339574.45 | G30: 136.57 | H30: 110 | I30: 1.2416 | J30: espejo | K30: numerador por ESPEJO (importaciones de socios desde Mexico; CIF, posible sesgo al alza) | L30: =IF(F30=0,"",E30/F30) | M30: =IF(ISNUMBER(L30),ROUND(L30-G30,4),"") | N30: =IF(H30=0,"",G30/H30) | O30: =IF(ISNUMBER(N30),ROUND(N30-I30,4),"")
A31: barita | B31: no metalico/industrial | C31: 2019 | D31: 251110 | E31: 49841739 | F31: 378413.32 | G31: 131.71 | H31: 113 | I31: 1.1656 | J31: espejo | K31: numerador por ESPEJO (importaciones de socios desde Mexico; CIF, posible sesgo al alza) | L31: =IF(F31=0,"",E31/F31) | M31: =IF(ISNUMBER(L31),ROUND(L31-G31,4),"") | N31: =IF(H31=0,"",G31/H31) | O31: =IF(ISNUMBER(N31),ROUND(N31-I31,4),"")
A32: barita | B32: no metalico/industrial | C32: 2020 | D32: 251110 | E32: 34531482 | F32: 249004.05 | G32: 138.68 | H32: 115.53 | I32: 1.2004 | J32: espejo | K32: numerador por ESPEJO (importaciones de socios desde Mexico; CIF, posible sesgo al alza) | L32: =IF(F32=0,"",E32/F32) | M32: =IF(ISNUMBER(L32),ROUND(L32-G32,4),"") | N32: =IF(H32=0,"",G32/H32) | O32: =IF(ISNUMBER(N32),ROUND(N32-I32,4),"")
A33: barita | B33: no metalico/industrial | C33: 2021 | D33: 251110 | E33: 19124233 | F33: 183157.85 | G33: 104.41 | H33: 105.42 | I33: 0.9904 | J33: propio | L33: =IF(F33=0,"",E33/F33) | M33: =IF(ISNUMBER(L33),ROUND(L33-G33,4),"") | N33: =IF(H33=0,"",G33/H33) | O33: =IF(ISNUMBER(N33),ROUND(N33-I33,4),"")
A34: barita | B34: no metalico/industrial | C34: 2022 | D34: 251110 | E34: 27236605 | F34: 231514.31 | G34: 117.65 | H34: 91.54 | I34: 1.2852 | J34: propio | L34: =IF(F34=0,"",E34/F34) | M34: =IF(ISNUMBER(L34),ROUND(L34-G34,4),"") | N34: =IF(H34=0,"",G34/H34) | O34: =IF(ISNUMBER(N34),ROUND(N34-I34,4),"")
A35: barita | B35: no metalico/industrial | C35: 2023 | D35: 251110 | E35: 26073174 | F35: 217538.9 | G35: 119.86 | H35: 137.62 | I35: 0.8709 | J35: propio | L35: =IF(F35=0,"",E35/F35) | M35: =IF(ISNUMBER(L35),ROUND(L35-G35,4),"") | N35: =IF(H35=0,"",G35/H35) | O35: =IF(ISNUMBER(N35),ROUND(N35-I35,4),"")
A36: barita | B36: no metalico/industrial | C36: 2024 | D36: 251110 | E36: 13093040 | F36: 106562.4 | G36: 122.87 | H36: 132.57 | I36: 0.9268 | J36: propio | L36: =IF(F36=0,"",E36/F36) | M36: =IF(ISNUMBER(L36),ROUND(L36-G36,4),"") | N36: =IF(H36=0,"",G36/H36) | O36: =IF(ISNUMBER(N36),ROUND(N36-I36,4),"")
A37: barita | B37: no metalico/industrial | C37: 2025 | D37: 251110 | E37: 27730976 | F37: 255119.24 | G37: 108.7 | H37: 132.57 | I37: 0.8199 | J37: propio | L37: =IF(F37=0,"",E37/F37) | M37: =IF(ISNUMBER(L37),ROUND(L37-G37,4),"") | N37: =IF(H37=0,"",G37/H37) | O37: =IF(ISNUMBER(N37),ROUND(N37-I37,4),"")
A38: cobre | B38: metal base | C38: 1992 | D38: 2603 | E38: 31605000 | F38: 67482.216 | G38: 468.35 | H38: 2370 | I38: 0.1976 | J38: propio | L38: =IF(F38=0,"",E38/F38) | M38: =IF(ISNUMBER(L38),ROUND(L38-G38,4),"") | N38: =IF(H38=0,"",G38/H38) | O38: =IF(ISNUMBER(N38),ROUND(N38-I38,4),"")
A39: cobre | B39: metal base | C39: 1993 | D39: 2603 | E39: 61000 | F39: 82.925 | G39: 735.6 | H39: 2020 | I39: 0.3642 | J39: propio | L39: =IF(F39=0,"",E39/F39) | M39: =IF(ISNUMBER(L39),ROUND(L39-G39,4),"") | N39: =IF(H39=0,"",G39/H39) | O39: =IF(ISNUMBER(N39),ROUND(N39-I39,4),"")
A40: cobre | B40: metal base | C40: 1994 | D40: 2603 | E40: 4748557 | F40: 8304.535 | G40: 571.8 | H40: 2450 | I40: 0.2334 | J40: propio | L40: =IF(F40=0,"",E40/F40) | M40: =IF(ISNUMBER(L40),ROUND(L40-G40,4),"") | N40: =IF(H40=0,"",G40/H40) | O40: =IF(ISNUMBER(N40),ROUND(N40-I40,4),"")
A41: cobre | B41: metal base | C41: 1995 | D41: 2603 | E41: 20182000 | F41: 31652.52 | G41: 637.61 | H41: 3050 | I41: 0.2091 | J41: propio | L41: =IF(F41=0,"",E41/F41) | M41: =IF(ISNUMBER(L41),ROUND(L41-G41,4),"") | N41: =IF(H41=0,"",G41/H41) | O41: =IF(ISNUMBER(N41),ROUND(N41-I41,4),"")
A42: cobre | B42: metal base | C42: 1996 | D42: 2603 | E42: 15994984 | F42: 53179.452 | G42: 300.77 | H42: 2400 | I42: 0.1253 | J42: propio | L42: =IF(F42=0,"",E42/F42) | M42: =IF(ISNUMBER(L42),ROUND(L42-G42,4),"") | N42: =IF(H42=0,"",G42/H42) | O42: =IF(ISNUMBER(N42),ROUND(N42-I42,4),"")
A43: cobre | B43: metal base | C43: 1997 | D43: 2603 | E43: 18588480 | F43: 44533.856 | G43: 417.4 | H43: 2360 | I43: 0.1769 | J43: propio | L43: =IF(F43=0,"",E43/F43) | M43: =IF(ISNUMBER(L43),ROUND(L43-G43,4),"") | N43: =IF(H43=0,"",G43/H43) | O43: =IF(ISNUMBER(N43),ROUND(N43-I43,4),"")
A44: cobre | B44: metal base | C44: 1998 | D44: 2603 | E44: 25456432 | F44: 68722.216 | G44: 370.43 | H44: 1730 | I44: 0.2141 | J44: propio | L44: =IF(F44=0,"",E44/F44) | M44: =IF(ISNUMBER(L44),ROUND(L44-G44,4),"") | N44: =IF(H44=0,"",G44/H44) | O44: =IF(ISNUMBER(N44),ROUND(N44-I44,4),"")
... A60: cobre | B60: metal base | C60: 2014 | D60: 2603 | E60: 1170641398 | F60: 659351.02 | G60: 1775.44 | H60: 7010 | I60: 0.2533 | J60: propio | L60: =IF(F60=0,"",E60/F60) | M60: =IF(ISNUMBER(L60),ROUND(L60-G60,4),"") | N60: =IF(H60=0,"",G60/H60) | O60: =IF(ISNUMBER(N60),ROUND(N60-I60,4),"")
A61: cobre | B61: metal base | C61: 2015 | D61: 2603 | E61: 2.3460378e+09 | F61: 1467244.6 | G61: 1598.94 | H61: 5650 | I61: 0.283 | J61: espejo | K61: numerador por ESPEJO (importaciones de socios desde Mexico; CIF, posible sesgo al alza) | L61: =IF(F61=0,"",E61/F61) | M61: =IF(ISNUMBER(L61),ROUND(L61-G61,4),"") | N61: =IF(H61=0,"",G61/H61) | O61: =IF(ISNUMBER(N61),ROUND(N61-I61,4),"")
A62: cobre | B62: metal base | C62: 2016 | D62: 2603 | E62: 1323559500 | F62: 1097421.1 | G62: 1206.06 | H62: 4960 | I62: 0.2432 | J62: propio | L62: =IF(F62=0,"",E62/F62) | M62: =IF(ISNUMBER(L62),ROUND(L62-G62,4),"") | N62: =IF(H62=0,"",G62/H62) | O62: =IF(ISNUMBER(N62),ROUND(N62-I62,4),"")
A63: cobre | B63: metal base | C63: 2017 | D63: 2603 | E63: 1568943333 | F63: 1218662.5 | G63: 1287.43 | H63: 6290 | I63: 0.2047 | J63: propio | L63: =IF(F63=0,"",E63/F63) | M63: =IF(ISNUMBER(L63),ROUND(L63-G63,4),"") | N63: =IF(H63=0,"",G63/H63) | O63: =IF(ISNUMBER(N63),ROUND(N63-I63,4),"")
A64: cobre | B64: metal base | C64: 2018 | D64: 2603 | E64: 2318095785 | F64: 1583502.4 | G64: 1463.9 | H64: 6590 | I64: 0.2221 | J64: propio | L64: =IF(F64=0,"",E64/F64) | M64: =IF(ISNUMBER(L64),ROUND(L64-G64,4),"") | N64: =IF(H64=0,"",G64/H64) | O64: =IF(ISNUMBER(N64),ROUND(N64-I64,4),"")
A65: cobre | B65: metal base | C65: 2019 | D65: 2603 | E65: 2339268612 | F65: 1838532.2 | G65: 1272.36 | H65: 6160 | I65: 0.2066 | J65: propio | L65: =IF(F65=0,"",E65/F65) | M65: =IF(ISNUMBER(L65),ROUND(L65-G65,4),"") | N65: =IF(H65=0,"",G65/H65) | O65: =IF(ISNUMBER(N65),ROUND(N65-I65,4),"")
A66: cobre | B66: metal base | C66: 2020 | D66: 2603 | E66: 2878626776 | F66: 1816661.2 | G66: 1584.57 | H66: 6320 | I66: 0.2507 | J66: propio | L66: =IF(F66=0,"",E66/F66) | M66: =IF(ISNUMBER(L66),ROUND(L66-G66,4),"") | N66: =IF(H66=0,"",G66/H66) | O66: =IF(ISNUMBER(N66),ROUND(N66-I66,4),"")
A67: cobre | B67: metal base | C67: 2021 | D67: 2603 | E67: 3420948513 | F67: 1551769.3 | G67: 2204.55 | H67: 9543.37 | I67: 0.231 | J67: propio | L67: =IF(F67=0,"",E67/F67) | M67: =IF(ISNUMBER(L67),ROUND(L67-G67,4),"") | N67: =IF(H67=0,"",G67/H67) | O67: =IF(ISNUMBER(N67),ROUND(N67-I67,4),"")
A68: cobre | B68: metal base | C68: 2022 | D68: 2603 | E68: 3137587661 | F68: 1566996.2 | G68: 2002.29 | H68: 9030.98 | I68: 0.2217 | J68: propio | L68: =IF(F68=0,"",E68/F68) | M68: =IF(ISNUMBER(L68),ROUND(L68-G68,4),"") | N68: =IF(H68=0,"",G68/H68) | O68: =IF(ISNUMBER(N68),ROUND(N68-I68,4),"")
A69: cobre | B69: metal base | C69: 2023 | D69: 2603 | E69: 3715931601 | F69: 2729478 | G69: 1361.41 | H69: 8693.06 | I69: 0.1566 | J69: propio | L69: =IF(F69=0,"",E69/F69) | M69: =IF(ISNUMBER(L69),ROUND(L69-G69,4),"") | N69: =IF(H69=0,"",G69/H69) | O69: =IF(ISNUMBER(N69),ROUND(N69-I69,4),"")
A70: cobre | B70: metal base | C70: 2024 | D70: 2603 | E70: 3718889902 | F70: 1722560 | G70: 2158.93 | H70: 9368.53 | I70: 0.2304 | J70: propio | L70: =IF(F70=0,"",E70/F70) | M70: =IF(ISNUMBER(L70),ROUND(L70-G70,4),"") | N70: =IF(H70=0,"",G70/H70) | O70: =IF(ISNUMBER(N70),ROUND(N70-I70,4),"")
A71: cobre | B71: metal base | C71: 2025 | D71: 2603 | E71: 4122406903 | F71: 1602679.4 | G71: 2572.2 | H71: 9938.43 | I71: 0.2588 | J71: propio | L71: =IF(F71=0,"",E71/F71) | M71: =IF(ISNUMBER(L71),ROUND(L71-G71,4),"") | N71: =IF(H71=0,"",G71/H71) | O71: =IF(ISNUMBER(N71),ROUND(N71-I71,4),"")
A72: fluorita | B72: no metalico/industrial | C72: 1992 | D72: 252921;252922 | E72: 13929000 | F72: 150281.26 | G72: 92.69 | H72: 193 | I72: 0.4802 | J72: propio | L72: =IF(F72=0,"",E72/F72) | M72: =IF(ISNUMBER(L72),ROUND(L72-G72,4),"") | N72: =IF(H72=0,"",G72/H72) | O72: =IF(ISNUMBER(N72),ROUND(N72-I72,4),"")
A73: fluorita | B73: no metalico/industrial | C73: 1993 | D73: 252921;252922 | E73: 9385000 | F73: 111686.32 | G73: 84.03 | H73: 95 | I73: 0.8845 | J73: propio | L73: =IF(F73=0,"",E73/F73) | M73: =IF(ISNUMBER(L73),ROUND(L73-G73,4),"") | N73: =IF(H73=0,"",G73/H73) | O73: =IF(ISNUMBER(N73),ROUND(N73-I73,4),"")
... A97: fluorita | B97: no metalico/industrial | C97: 2017 | D97: 252921;252922 | E97: 71003890 | F97: 211708.16 | G97: 335.39 | H97: 249.77 | I97: 1.3428 | J97: propio | L97: =IF(F97=0,"",E97/F97) | M97: =IF(ISNUMBER(L97),ROUND(L97-G97,4),"") | N97: =IF(H97=0,"",G97/H97) | O97: =IF(ISNUMBER(N97),ROUND(N97-I97,4),"")
A98: fluorita | B98: no metalico/industrial | C98: 2018 | D98: 252921;252922 | E98: 73420659 | F98: 126901.47 | G98: 439.84 | H98: 258.19 | I98: 1.7035 | J98: propio | K98: valor unit. sobre 1/2 fracciones E1 con peso | L98: =IF(F98=0,"",E98/F98) | M98: =IF(ISNUMBER(L98),ROUND(L98-G98,4),"") | N98: =IF(H98=0,"",G98/H98) | O98: =IF(ISNUMBER(N98),ROUND(N98-I98,4),"")
A99: fluorita | B99: no metalico/industrial | C99: 2019 | D99: 252921;252922 | E99: 107197953 | F99: 219192.22 | G99: 489.06 | H99: 303.1 | I99: 1.6135 | J99: propio | L99: =IF(F99=0,"",E99/F99) | M99: =IF(ISNUMBER(L99),ROUND(L99-G99,4),"") | N99: =IF(H99=0,"",G99/H99) | O99: =IF(ISNUMBER(N99),ROUND(N99-I99,4),"")
A100: fluorita | B100: no metalico/industrial | C100: 2020 | D100: 252921;252922 | E100: 77026577 | F100: 66078.615 | G100: 246.41 | H100: 299.35 | I100: 0.8232 | J100: propio | K100: valor unit. sobre 1/2 fracciones E1 con peso | L100: =IF(F100=0,"",E100/F100) | M100: =IF(ISNUMBER(L100),ROUND(L100-G100,4),"") | N100: =IF(H100=0,"",G100/H100) | O100: =IF(ISNUMBER(N100),ROUND(N100-I100,4),"")
A101: fluorita | B101: no metalico/industrial | C101: 2021 | D101: 252921;252922 | E101: 91633901 | F101: 288867.6 | G101: 317.22 | H101: 301.23 | I101: 1.0531 | J101: propio | L101: =IF(F101=0,"",E101/F101) | M101: =IF(ISNUMBER(L101),ROUND(L101-G101,4),"") | N101: =IF(H101=0,"",G101/H101) | O101: =IF(ISNUMBER(N101),ROUND(N101-I101,4),"")
A102: fluorita | B102: no metalico/industrial | C102: 2022 | D102: 252921;252922 | E102: 55800331 | F102: 159212.27 | G102: 350.48 | H102: 362.03 | I102: 0.9681 | J102: propio | L102: =IF(F102=0,"",E102/F102) | M102: =IF(ISNUMBER(L102),ROUND(L102-G102,4),"") | N102: =IF(H102=0,"",G102/H102) | O102: =IF(ISNUMBER(N102),ROUND(N102-I102,4),"")
A103: fluorita | B103: no metalico/industrial | C103: 2023 | D103: 252921;252922 | E103: 66031726 | F103: 152897.89 | G103: 431.87 | H103: 400.39 | I103: 1.0786 | J103: propio | L103: =IF(F103=0,"",E103/F103) | M103: =IF(ISNUMBER(L103),ROUND(L103-G103,4),"") | N103: =IF(H103=0,"",G103/H103) | O103: =IF(ISNUMBER(N103),ROUND(N103-I103,4),"")
A104: fluorita | B104: no metalico/industrial | C104: 2024 | D104: 252921;252922 | E104: 25305600 | F104: 54376.586 | G104: 465.38 | H104: 434.06 | I104: 1.0721 | J104: propio | L104: =IF(F104=0,"",E104/F104) | M104: =IF(ISNUMBER(L104),ROUND(L104-G104,4),"") | N104: =IF(H104=0,"",G104/H104) | O104: =IF(ISNUMBER(N104),ROUND(N104-I104,4),"")
A105: fluorita | B105: no metalico/industrial | C105: 2025 | D105: 252921;252922 | E105: 51346506 | F105: 103272.11 | G105: 497.2 | H105: 439.68 | I105: 1.1308 | J105: propio | L105: =IF(F105=0,"",E105/F105) | M105: =IF(ISNUMBER(L105),ROUND(L105-G105,4),"") | N105: =IF(H105=0,"",G105/H105) | O105: =IF(ISNUMBER(N105),ROUND(N105-I105,4),"")
A106: grafito | B106: no metalico/industrial | C106: 1992 | D106: 250410;250490 | E106: 3073000 | F106: 14265.073 | G106: 215.42 | H106: 513.1 | I106: 0.4198 | J106: propio | L106: =IF(F106=0,"",E106/F106) | M106: =IF(ISNUMBER(L106),ROUND(L106-G106,4),"") | N106: =IF(H106=0,"",G106/H106) | O106: =IF(ISNUMBER(N106),ROUND(N106-I106,4),"")
A107: grafito | B107: no metalico/industrial | C107: 1993 | D107: 250410;250490 | E107: 1995000 | F107: 13901.475 | G107: 143.51 | H107: 572.8 | I107: 0.2505 | J107: propio | L107: =IF(F107=0,"",E107/F107) | M107: =IF(ISNUMBER(L107),ROUND(L107-G107,4),"") | N107: =IF(H107=0,"",G107/H107) | O107: =IF(ISNUMBER(N107),ROUND(N107-I107,4),"")
A108: grafito | B108: no metalico/industrial | C108: 1994 | D108: 250410;250490 | E108: 2376785 | F108: 17042.182 | G108: 139.46 | H108: 506.6 | I108: 0.2753 | J108: propio | L108: =IF(F108=0,"",E108/F108) | M108: =IF(ISNUMBER(L108),ROUND(L108-G108,4),"") | N108: =IF(H108=0,"",G108/H108) | O108: =IF(ISNUMBER(N108),ROUND(N108-I108,4),"")
A109: grafito | B109: no metalico/industrial | C109: 1995 | D109: 250410;250490 | E109: 2264000 | F109: 15107.803 | G109: 149.86 | H109: 495.9 | I109: 0.3022 | J109: propio | L109: =IF(F109=0,"",E109/F109) | M109: =IF(ISNUMBER(L109),ROUND(L109-G109,4),"") | N109: =IF(H109=0,"",G109/H109) | O109: =IF(ISNUMBER(N109),ROUND(N109-I109,4),"")
A110: grafito | B110: no metalico/industrial | C110: 1996 | D110: 250410;250490 | E110: 2075280 | F110: 16366.437 | G110: 126.8 | H110: 535.6 | I110: 0.2367 | J110: propio | L110: =IF(F110=0,"",E110/F110) | M110: =IF(ISNUMBER(L110),ROUND(L110-G110,4),"") | N110: =IF(H110=0,"",G110/H110) | O110: =IF(ISNUMBER(N110),ROUND(N110-I110,4),"")
A111: grafito | B111: no metalico/industrial | C111: 1997 | D111: 250410;250490 | E111: 2299340 | F111: 16651.105 | G111: 138.09 | H111: 557.7 | I111: 0.2476 | J111: propio | L111: =IF(F111=0,"",E111/F111) | M111: =IF(ISNUMBER(L111),ROUND(L111-G111,4),"") | N111: =IF(H111=0,"",G111/H111) | O111: =IF(ISNUMBER(N111),ROUND(N111-I111,4),"")
A112: grafito | B112: no metalico/industrial | C112: 1998 | D112: 250410;250490 | E112: 2571031 | F112: 16973.697 | G112: 151.47 | H112: 565 | I112: 0.2681 | J112: propio | L112: =IF(F112=0,"",E112/F112) | M112: =IF(ISNUMBER(L112),ROUND(L112-G112,4),"") | N112: =IF(H112=0,"",G112/H112) | O112: =IF(ISNUMBER(N112),ROUND(N112-I112,4),"")
... A130: grafito | B130: no metalico/industrial | C130: 2016 | D130: 250410;250490 | E130: 3889142 | F130: 2879.762 | G130: 1350.51 | H130: 1220 | I130: 1.107 | J130: propio | L130: =IF(F130=0,"",E130/F130) | M130: =IF(ISNUMBER(L130),ROUND(L130-G130,4),"") | N130: =IF(H130=0,"",G130/H130) | O130: =IF(ISNUMBER(N130),ROUND(N130-I130,4),"")
A131: grafito | B131: no metalico/industrial | C131: 2017 | D131: 250410;250490 | E131: 5527568 | F131: 3520.239 | G131: 1431.98 | H131: 1130 | I131: 1.2672 | J131: propio | K131: valor unit. sobre 1/2 fracciones E1 con peso | L131: =IF(F131=0,"",E131/F131) | M131: =IF(ISNUMBER(L131),ROUND(L131-G131,4),"") | N131: =IF(H131=0,"",G131/H131) | O131: =IF(ISNUMBER(N131),ROUND(N131-I131,4),"")
A132: grafito | B132: no metalico/industrial | C132: 2018 | D132: 250410;250490 | E132: 5558473 | F132: 1939.376 | G132: 2625.37 | H132: 913 | I132: 2.8755 | J132: propio | K132: valor unit. sobre 1/2 fracciones E1 con peso | L132: =IF(F132=0,"",E132/F132) | M132: =IF(ISNUMBER(L132),ROUND(L132-G132,4),"") | N132: =IF(H132=0,"",G132/H132) | O132: =IF(ISNUMBER(N132),ROUND(N132-I132,4),"")
A133: grafito | B133: no metalico/industrial | C133: 2019 | D133: 250410;250490 | E133: 5686693.2 | F133: 11515.498 | G133: 493.83 | H133: 1120 | I133: 0.4409 | J133: espejo | K133: numerador por ESPEJO (importaciones de socios desde Mexico; CIF, posible sesgo al alza) | L133: =IF(F133=0,"",E133/F133) | M133: =IF(ISNUMBER(L133),ROUND(L133-G133,4),"") | N133: =IF(H133=0,"",G133/H133) | O133: =IF(ISNUMBER(N133),ROUND(N133-I133,4),"")
A134: grafito | B134: no metalico/industrial | C134: 2020 | D134: 250410;250490 | E134: 4000535.8 | F134: 6135.968 | G134: 651.98 | H134: 1240 | I134: 0.5258 | J134: espejo | K134: numerador por ESPEJO (importaciones de socios desde Mexico; CIF, posible sesgo al alza) | L134: =IF(F134=0,"",E134/F134) | M134: =IF(ISNUMBER(L134),ROUND(L134-G134,4),"") | N134: =IF(H134=0,"",G134/H134) | O134: =IF(ISNUMBER(N134),ROUND(N134-I134,4),"")
A135: grafito | B135: no metalico/industrial | C135: 2021 | D135: 250410;250490 | E135: 2113261 | F135: 3830.399 | G135: 551.71 | H135: 1340 | I135: 0.4117 | J135: propio | L135: =IF(F135=0,"",E135/F135) | M135: =IF(ISNUMBER(L135),ROUND(L135-G135,4),"") | N135: =IF(H135=0,"",G135/H135) | O135: =IF(ISNUMBER(N135),ROUND(N135-I135,4),"")
A136: grafito | B136: no metalico/industrial | C136: 2022 | D136: 250410;250490 | E136: 3434484 | F136: 6152.964 | G136: 558.18 | H136: 2090 | I136: 0.2671 | J136: propio | L136: =IF(F136=0,"",E136/F136) | M136: =IF(ISNUMBER(L136),ROUND(L136-G136,4),"") | N136: =IF(H136=0,"",G136/H136) | O136: =IF(ISNUMBER(N136),ROUND(N136-I136,4),"")
A137: grafito | B137: no metalico/industrial | C137: 2023 | D137: 250410;250490 | E137: 1818565 | F137: 2882.65 | G137: 630.87 | H137: 1881 | I137: 0.3354 | J137: propio | L137: =IF(F137=0,"",E137/F137) | M137: =IF(ISNUMBER(L137),ROUND(L137-G137,4),"") | N137: =IF(H137=0,"",G137/H137) | O137: =IF(ISNUMBER(N137),ROUND(N137-I137,4),"")
A138: grafito | B138: no metalico/industrial | C138: 2024 | D138: 250410;250490 | E138: 3808739 | F138: 5247.998 | G138: 725.75 | H138: 1828.75 | I138: 0.3969 | J138: propio | L138: =IF(F138=0,"",E138/F138) | M138: =IF(ISNUMBER(L138),ROUND(L138-G138,4),"") | N138: =IF(H138=0,"",G138/H138) | O138: =IF(ISNUMBER(N138),ROUND(N138-I138,4),"")
A139: grafito | B139: no metalico/industrial | C139: 2025 | D139: 250410;250490 | E139: 4341426 | F139: 6109.474 | G139: 710.61 | H139: 1741.67 | I139: 0.408 | J139: propio | L139: =IF(F139=0,"",E139/F139) | M139: =IF(ISNUMBER(L139),ROUND(L139-G139,4),"") | N139: =IF(H139=0,"",G139/H139) | O139: =IF(ISNUMBER(N139),ROUND(N139-I139,4),"")
A140: manganeso | B140: no metalico/industrial | C140: 1992 | D140: 2602 | E140: 6044000 | F140: 32175.024 | G140: 187.85 | H140: 654.23 | I140: 0.2871 | J140: propio | L140: =IF(F140=0,"",E140/F140) | M140: =IF(ISNUMBER(L140),ROUND(L140-G140,4),"") | N140: =IF(H140=0,"",G140/H140) | O140: =IF(ISNUMBER(N140),ROUND(N140-I140,4),"")
A141: manganeso | B141: no metalico/industrial | C141: 1993 | D141: 2602 | E141: 8842000 | F141: 66490 | G141: 132.98 | H141: 605 | I141: 0.2198 | J141: propio | L141: =IF(F141=0,"",E141/F141) | M141: =IF(ISNUMBER(L141),ROUND(L141-G141,4),"") | N141: =IF(H141=0,"",G141/H141) | O141: =IF(ISNUMBER(N141),ROUND(N141-I141,4),"")
A142: manganeso | B142: no metalico/industrial | C142: 1994 | D142: 2602 | E142: 3910169 | F142: 40587.264 | G142: 96.34 | H142: 602 | I142: 0.16 | J142: propio | L142: =IF(F142=0,"",E142/F142) | M142: =IF(ISNUMBER(L142),ROUND(L142-G142,4),"") | N142: =IF(H142=0,"",G142/H142) | O142: =IF(ISNUMBER(N142),ROUND(N142-I142,4),"")
A143: manganeso | B143: no metalico/industrial | C143: 1995 | D143: 2602 | E143: 9596000 | F143: 144360.66 | G143: 66.47 | H143: 599 | I143: 0.111 | J143: propio | L143: =IF(F143=0,"",E143/F143) | M143: =IF(ISNUMBER(L143),ROUND(L143-G143,4),"") | N143: =IF(H143=0,"",G143/H143) | O143: =IF(ISNUMBER(N143),ROUND(N143-I143,4),"")
A144: manganeso | B144: no metalico/industrial | C144: 1996 | D144: 2602 | E144: 4363511 | F144: 58511.132 | G144: 74.58 | H144: 650 | I144: 0.1147 | J144: propio | L144: =IF(F144=0,"",E144/F144) | M144: =IF(ISNUMBER(L144),ROUND(L144-G144,4),"") | N144: =IF(H144=0,"",G144/H144) | O144: =IF(ISNUMBER(N144),ROUND(N144-I144,4),"")
A145: manganeso | B145: no metalico/industrial | C145: 1997 | D145: 2602 | E145: 6756622 | F145: 89307.32 | G145: 75.66 | H145: 635 | I145: 0.1191 | J145: propio | L145: =IF(F145=0,"",E145/F145) | M145: =IF(ISNUMBER(L145),ROUND(L145-G145,4),"") | N145: =IF(H145=0,"",G145/H145) | O145: =IF(ISNUMBER(N145),ROUND(N145-I145,4),"")
A146: manganeso | B146: no metalico/industrial | C146: 1998 | D146: 2602 | E146: 5560749 | F146: 48713.176 | G146: 114.15 | H146: 591 | I146: 0.1932 | J146: propio | L146: =IF(F146=0,"",E146/F146) | M146: =IF(ISNUMBER(L146),ROUND(L146-G146,4),"") | N146: =IF(H146=0,"",G146/H146) | O146: =IF(ISNUMBER(N146),ROUND(N146-I146,4),"")
... A162: manganeso | B162: no metalico/industrial | C162: 2014 | D162: 2602 | E162: 81079 | F162: 338.366 | G162: 239.62 | H162: 1330 | I162: 0.1802 | J162: propio | L162: =IF(F162=0,"",E162/F162) | M162: =IF(ISNUMBER(L162),ROUND(L162-G162,4),"") | N162: =IF(H162=0,"",G162/H162) | O162: =IF(ISNUMBER(N162),ROUND(N162-I162,4),"")
A163: manganeso | B163: no metalico/industrial | C163: 2015 | D163: 2602 | E163: 21165201 | F163: 158857.87 | G163: 133.23 | H163: 1140 | I163: 0.1169 | J163: espejo | K163: numerador por ESPEJO (importaciones de socios desde Mexico; CIF, posible sesgo al alza) | L163: =IF(F163=0,"",E163/F163) | M163: =IF(ISNUMBER(L163),ROUND(L163-G163,4),"") | N163: =IF(H163=0,"",G163/H163) | O163: =IF(ISNUMBER(N163),ROUND(N163-I163,4),"")
A164: manganeso | B164: no metalico/industrial | C164: 2016 | D164: 2602 | E164: 19841006 | F164: 26917.131 | G164: 737.11 | H164: 920 | I164: 0.8012 | J164: espejo | K164: numerador por ESPEJO (importaciones de socios desde Mexico; CIF, posible sesgo al alza) | L164: =IF(F164=0,"",E164/F164) | M164: =IF(ISNUMBER(L164),ROUND(L164-G164,4),"") | N164: =IF(H164=0,"",G164/H164) | O164: =IF(ISNUMBER(N164),ROUND(N164-I164,4),"")
A165: manganeso | B165: no metalico/industrial | C165: 2017 | D165: 2602 | E165: 49083913 | F165: 162750.93 | G165: 301.59 | H165: 1420 | I165: 0.2124 | J165: espejo | K165: numerador por ESPEJO (importaciones de socios desde Mexico; CIF, posible sesgo al alza) | L165: =IF(F165=0,"",E165/F165) | M165: =IF(ISNUMBER(L165),ROUND(L165-G165,4),"") | N165: =IF(H165=0,"",G165/H165) | O165: =IF(ISNUMBER(N165),ROUND(N165-I165,4),"")
A166: manganeso | B166: no metalico/industrial | C166: 2018 | D166: 2602 | E166: 17622860 | F166: 56188.982 | G166: 313.64 | H166: 1500 | I166: 0.2091 | J166: espejo | K166: numerador por ESPEJO (importaciones de socios desde Mexico; CIF, posible sesgo al alza) | L166: =IF(F166=0,"",E166/F166) | M166: =IF(ISNUMBER(L166),ROUND(L166-G166,4),"") | N166: =IF(H166=0,"",G166/H166) | O166: =IF(ISNUMBER(N166),ROUND(N166-I166,4),"")
A167: manganeso | B167: no metalico/industrial | C167: 2019 | D167: 2602 | E167: 19027206 | F167: 84720.989 | G167: 224.59 | H167: 1300 | I167: 0.1728 | J167: espejo | K167: numerador por ESPEJO (importaciones de socios desde Mexico; CIF, posible sesgo al alza) | L167: =IF(F167=0,"",E167/F167) | M167: =IF(ISNUMBER(L167),ROUND(L167-G167,4),"") | N167: =IF(H167=0,"",G167/H167) | O167: =IF(ISNUMBER(N167),ROUND(N167-I167,4),"")
A168: manganeso | B168: no metalico/industrial | C168: 2020 | D168: 2602 | E168: 40217084 | F168: 159230.42 | G168: 252.57 | H168: 1110 | I168: 0.2275 | J168: espejo | K168: numerador por ESPEJO (importaciones de socios desde Mexico; CIF, posible sesgo al alza) | L168: =IF(F168=0,"",E168/F168) | M168: =IF(ISNUMBER(L168),ROUND(L168-G168,4),"") | N168: =IF(H168=0,"",G168/H168) | O168: =IF(ISNUMBER(N168),ROUND(N168-I168,4),"")
A169: manganeso | B169: no metalico/industrial | C169: 2021 | D169: 2602 | E169: 19055714 | F169: 52740.984 | G169: 361.31 | H169: 1420 | I169: 0.2544 | J169: espejo | K169: numerador por ESPEJO (importaciones de socios desde Mexico; CIF, posible sesgo al alza) | L169: =IF(F169=0,"",E169/F169) | M169: =IF(ISNUMBER(L169),ROUND(L169-G169,4),"") | N169: =IF(H169=0,"",G169/H169) | O169: =IF(ISNUMBER(N169),ROUND(N169-I169,4),"")
A170: manganeso | B170: no metalico/industrial | C170: 2022 | D170: 2602 | E170: 20023026 | F170: 32426.854 | G170: 617.48 | H170: 2000 | I170: 0.3087 | J170: espejo | K170: numerador por ESPEJO (importaciones de socios desde Mexico; CIF, posible sesgo al alza) | L170: =IF(F170=0,"",E170/F170) | M170: =IF(ISNUMBER(L170),ROUND(L170-G170,4),"") | N170: =IF(H170=0,"",G170/H170) | O170: =IF(ISNUMBER(N170),ROUND(N170-I170,4),"")
A171: manganeso | B171: no metalico/industrial | C171: 2023 | D171: 2602 | E171: 12522832 | F171: 62074.869 | G171: 201.74 | H171: 1608.04 | I171: 0.1255 | J171: espejo | K171: numerador por ESPEJO (importaciones de socios desde Mexico; CIF, posible sesgo al alza) | L171: =IF(F171=0,"",E171/F171) | M171: =IF(ISNUMBER(L171),ROUND(L171-G171,4),"") | N171: =IF(H171=0,"",G171/H171) | O171: =IF(ISNUMBER(N171),ROUND(N171-I171,4),"")
A172: manganeso | B172: no metalico/industrial | C172: 2024 | D172: 2602 | E172: 29630504 | F172: 142910.59 | G172: 207.34 | H172: 1852.6 | I172: 0.1119 | J172: espejo | K172: numerador por ESPEJO (importaciones de socios desde Mexico; CIF, posible sesgo al alza) | L172: =IF(F172=0,"",E172/F172) | M172: =IF(ISNUMBER(L172),ROUND(L172-G172,4),"") | N172: =IF(H172=0,"",G172/H172) | O172: =IF(ISNUMBER(N172),ROUND(N172-I172,4),"")
A173: manganeso | B173: no metalico/industrial | C173: 2025 | D173: 2602 | E173: 36523729 | F173: 183428.05 | G173: 199.12 | H173: 1507.54 | I173: 0.1321 | J173: espejo | K173: numerador por ESPEJO (importaciones de socios desde Mexico; CIF, posible sesgo al alza) | L173: =IF(F173=0,"",E173/F173) | M173: =IF(ISNUMBER(L173),ROUND(L173-G173,4),"") | N173: =IF(H173=0,"",G173/H173) | O173: =IF(ISNUMBER(N173),ROUND(N173-I173,4),"")
A174: oro | B174: metal precioso | C174: 1992 | D174: 261610 | E174: 71000 | F174: 2864.11 | G174: 24.79 | H174: 11100000 | I174: 0 | J174: propio | L174: =IF(F174=0,"",E174/F174) | M174: =IF(ISNUMBER(L174),ROUND(L174-G174,4),"") | N174: =IF(H174=0,"",G174/H174) | O174: =IF(ISNUMBER(N174),ROUND(N174-I174,4),"")
A175: oro | B175: metal precioso | C175: 1993 | D175: 261610 | E175: 75000 | F175: 1917.997 | G175: 39.1 | H175: 11600000 | I175: 0 | J175: propio | L175: =IF(F175=0,"",E175/F175) | M175: =IF(ISNUMBER(L175),ROUND(L175-G175,4),"") | N175: =IF(H175=0,"",G175/H175) | O175: =IF(ISNUMBER(N175),ROUND(N175-I175,4),"")
A176: oro | B176: metal precioso | C176: 1994 | D176: 261610 | E176: 13441 | F176: 104.514 | G176: 128.6 | H176: 12400000 | I176: 0 | J176: propio | L176: =IF(F176=0,"",E176/F176) | M176: =IF(ISNUMBER(L176),ROUND(L176-G176,4),"") | N176: =IF(H176=0,"",G176/H176) | O176: =IF(ISNUMBER(N176),ROUND(N176-I176,4),"")
A177: oro | B177: metal precioso | C177: 1995 | D177: 261610 | E177: 13000 | F177: 370.65 | G177: 35.07 | H177: 12400000 | I177: 0 | J177: propio | L177: =IF(F177=0,"",E177/F177) | M177: =IF(ISNUMBER(L177),ROUND(L177-G177,4),"") | N177: =IF(H177=0,"",G177/H177) | O177: =IF(ISNUMBER(N177),ROUND(N177-I177,4),"")
A178: oro | B178: metal precioso | C178: 1996 | D178: 261610 | E178: 8439 | F178: 774 | G178: 10.9 | H178: 12500000 | I178: 0 | J178: propio | L178: =IF(F178=0,"",E178/F178) | M178: =IF(ISNUMBER(L178),ROUND(L178-G178,4),"") | N178: =IF(H178=0,"",G178/H178) | O178: =IF(ISNUMBER(N178),ROUND(N178-I178,4),"")
A179: oro | B179: metal precioso | C179: 1997 | D179: 261610 | E179: 2865503 | F179: 1378.586 | G179: 2078.58 | H179: 10700000 | I179: 0.0002 | J179: propio | L179: =IF(F179=0,"",E179/F179) | M179: =IF(ISNUMBER(L179),ROUND(L179-G179,4),"") | N179: =IF(H179=0,"",G179/H179) | O179: =IF(ISNUMBER(N179),ROUND(N179-I179,4),"")
...

Sheet 10 Precios
A1: Precios USGS anuales empalmados (denominador del CCV y valuacion de produccion)
A2: Precio de referencia del producto refinado, USD/t nominal y constante 1998. 'metodo'/'serie_fuente'/'factor' documentan el empalme entre ediciones del USGS. Resultado de la extraccion USGS (no aritmetico simple: enlace por factor).
A3: mineral | B3: anio | C3: precio_usd_t_nominal | D3: precio_usd_t_const1998 | E3: metodo | F3: serie_fuente | G3: factor
A4: Barita | B4: 1990 | C4: 46.7 | D4: 58.2 | E4: DS-140 | F4: USGS DS-140 valor unitario consumo aparente
A5: Barita | B5: 1991 | C5: 51.6 | D5: 61.8 | E5: DS-140 | F5: USGS DS-140 valor unitario consumo aparente
A6: Barita | B6: 1992 | C6: 51.8 | D6: 60.1 | E6: DS-140 | F6: USGS DS-140 valor unitario consumo aparente
A7: Barita | B7: 1993 | C7: 45.8 | D7: 51.6 | E7: DS-140 | F7: USGS DS-140 valor unitario consumo aparente
A8: Barita | B8: 1994 | C8: 38.8 | D8: 42.7 | E8: DS-140 | F8: USGS DS-140 valor unitario consumo aparente
A9: Barita | B9: 1995 | C9: 42.9 | D9: 45.9 | E9: DS-140 | F9: USGS DS-140 valor unitario consumo aparente
A10: Barita | B10: 1996 | C10: 42.7 | D10: 44.4 | E10: DS-140 | F10: USGS DS-140 valor unitario consumo aparente
A11: Barita | B11: 1997 | C11: 46.2 | D11: 46.9 | E11: DS-140 | F11: USGS DS-140 valor unitario consumo aparente
A12: Barita | B12: 1998 | C12: 57.1 | D12: 57.1 | E12: DS-140 | F12: USGS DS-140 valor unitario consumo aparente
A13: Barita | B13: 1999 | C13: 52.5 | D13: 51.4 | E13: DS-140 | F13: USGS DS-140 valor unitario consumo aparente
A14: Barita | B14: 2000 | C14: 46.3 | D14: 43.8 | E14: DS-140 | F14: USGS DS-140 valor unitario consumo aparente
A15: Barita | B15: 2001 | C15: 45.4 | D15: 41.8 | E15: DS-140 | F15: USGS DS-140 valor unitario consumo aparente
... A310: Zinc | B310: 2022 | C310: 4190 | D310: 2330 | E310: DS-140 | F310: USGS DS-140 valor unitario consumo aparente
A311: Oro | B311: 2023 | C311: 62454119 | D311: 33409762 | E311: empalme | F311: Cochilco London Fix AM anual (enc. 2022) | G311: 32139.229
A312: Oro | B312: 2024 | C312: 76727948 | D312: 39869602 | E312: empalme | F312: Cochilco London Fix AM anual (enc. 2022) | G312: 32139.229
A313: Oro | B313: 2025 | C313: 1.0605946e+08 | D313: 53605245 | E313: empalme | F313: MCS 2026 Engelhard 2025e (enc. 2022) | G313: 32139.229
A314: Plata | B314: 2022 | C314: 701028.12 | D314: 390451.5 | E314: empalme | F314: Cochilco London Fix anual (enc. 2021) | G314: 32226.924
A315: Plata | B315: 2023 | C315: 753678.95 | D315: 403179.73 | E315: empalme | F315: Cochilco London Fix anual (enc. 2021) | G315: 32226.924
A316: Plata | B316: 2024 | C316: 910220.06 | D316: 472971.22 | E316: empalme | F316: Cochilco London Fix anual (enc. 2021) | G316: 32226.924
A317: Plata | B317: 2025 | C317: 1224623.1 | D317: 618956.8 | E317: empalme | F317: MCS 2026 precio bullion 2025e (enc. 2021) | G317: 32226.924
A318: Cobre | B318: 2021 | C318: 9543.3688 | D318: 5740.7429 | E318: empalme | F318: Cochilco BML anual (enc. 2020) | G318: 22.587347
A319: Cobre | B319: 2022 | C319: 9030.9842 | D319: 5029.9856 | E319: empalme | F319: Cochilco BML anual (enc. 2020) | G319: 22.587347
A320: Cobre | B320: 2023 | C320: 8693.0568 | D320: 4650.3412 | E320: empalme | F320: Cochilco BML anual (enc. 2020) | G320: 22.587347
A321: Cobre | B321: 2024 | C321: 9368.5333 | D321: 4868.1048 | E321: empalme | F321: Cochilco BML anual (enc. 2020) | G321: 22.587347
A322: Cobre | B322: 2025 | C322: 9938.4328 | D322: 5023.1459 | E322: empalme | F322: MCS 2026 LME cash 2025e (enc. 2020) | G322: 22.587347
... A363: Fluorita | B363: 2025 | C363: 439.67742 | D363: 222.22456 | E363: empalme | F363: MCS valor unitario imports grado acido CIF (enc. 2006) | G363: 0.93548387

Sheet 11 Peso bloque prod
A1: Peso del bloque - valor de produccion (1992-2022)
A2: valor_prod = vol_t x precio_usd_t. share_bloque = valor_prod / (suma del bloque ese anio) x 100. Columnas verdes recomputan ambas con formula de Excel (SUMIFS por anio) y su diferencia vs script. Nota: 'precio_usd_t' se muestra redondeado a 1 decimal, por lo que 'dif valor' puede mostrar diferencias <0.02% (redondeo de despliegue, no error); el share cuadra exacto.
A3: anio | B3: mineral | C3: vol_t | D3: precio_usd_t | E3: valor_prod_usd | F3: share_bloque_pct | G3: anio_completo | H3: valor_prod (=formula) | I3: dif valor | J3: share_bloque (=formula) % | K3: dif share
A4: 1992 | B4: barita | C4: 188000 | D4: 51.8 | E4: 9738400 | F4: 0.56 | G4: si | H4: =C4*D4 | I4: =ROUND(H4-E4,0) | J4: =ROUND(E4/SUMIFS($E$4:$E$313,$A$4:$A$313,A4)*100,2) | K4: =ROUND(J4-F4,2)
A5: 1993 | B5: barita | C5: 136000 | D5: 45.8 | E5: 6228800 | F5: 0.38 | G5: si | H5: =C5*D5 | I5: =ROUND(H5-E5,0) | J5: =ROUND(E5/SUMIFS($E$4:$E$313,$A$4:$A$313,A5)*100,2) | K5: =ROUND(J5-F5,2)
A6: 1994 | B6: barita | C6: 86605 | D6: 38.8 | E6: 3360274 | F6: 0.17 | G6: si | H6: =C6*D6 | I6: =ROUND(H6-E6,0) | J6: =ROUND(E6/SUMIFS($E$4:$E$313,$A$4:$A$313,A6)*100,2) | K6: =ROUND(J6-F6,2)
A7: 1995 | B7: barita | C7: 248367 | D7: 42.9 | E7: 10654944 | F7: 0.43 | G7: si | H7: =C7*D7 | I7: =ROUND(H7-E7,0) | J7: =ROUND(E7/SUMIFS($E$4:$E$313,$A$4:$A$313,A7)*100,2) | K7: =ROUND(J7-F7,2)
A8: 1996 | B8: barita | C8: 470028 | D8: 42.7 | E8: 20070196 | F8: 0.83 | G8: si | H8: =C8*D8 | I8: =ROUND(H8-E8,0) | J8: =ROUND(E8/SUMIFS($E$4:$E$313,$A$4:$A$313,A8)*100,2) | K8: =ROUND(J8-F8,2)
A9: 1997 | B9: barita | C9: 236606 | D9: 46.2 | E9: 10931197 | F9: 0.42 | G9: si | H9: =C9*D9 | I9: =ROUND(H9-E9,0) | J9: =ROUND(E9/SUMIFS($E$4:$E$313,$A$4:$A$313,A9)*100,2) | K9: =ROUND(J9-F9,2)
A10: 1998 | B10: barita | C10: 161555 | D10: 57.1 | E10: 9224790 | F10: 0.41 | G10: si | H10: =C10*D10 | I10: =ROUND(H10-E10,0) | J10: =ROUND(E10/SUMIFS($E$4:$E$313,$A$4:$A$313,A10)*100,2) | K10: =ROUND(J10-F10,2)
A11: 1999 | B11: barita | C11: 157953 | D11: 52.5 | E11: 8292532 | F11: 0.41 | G11: si | H11: =C11*D11 | I11: =ROUND(H11-E11,0) | J11: =ROUND(E11/SUMIFS($E$4:$E$313,$A$4:$A$313,A11)*100,2) | K11: =ROUND(J11-F11,2)
A12: 2000 | B12: barita | C12: 127420 | D12: 46.3 | E12: 5899546 | F12: 0.27 | G12: si | H12: =C12*D12 | I12: =ROUND(H12-E12,0) | J12: =ROUND(E12/SUMIFS($E$4:$E$313,$A$4:$A$313,A12)*100,2) | K12: =ROUND(J12-F12,2)
A13: 2001 | B13: barita | C13: 142017 | D13: 45.4 | E13: 6447572 | F13: 0.33 | G13: si | H13: =C13*D13 | I13: =ROUND(H13-E13,0) | J13: =ROUND(E13/SUMIFS($E$4:$E$313,$A$4:$A$313,A13)*100,2) | K13: =ROUND(J13-F13,2)
A14: 2002 | B14: barita | C14: 163620 | D14: 46.6 | E14: 7624692 | F14: 0.41 | G14: si | H14: =C14*D14 | I14: =ROUND(H14-E14,0) | J14: =ROUND(E14/SUMIFS($E$4:$E$313,$A$4:$A$313,A14)*100,2) | K14: =ROUND(J14-F14,2)
A15: 2003 | B15: barita | C15: 287451 | D15: 45.6 | E15: 13107766 | F15: 0.64 | G15: si | H15: =C15*D15 | I15: =ROUND(H15-E15,0) | J15: =ROUND(E15/SUMIFS($E$4:$E$313,$A$4:$A$313,A15)*100,2) | K15: =ROUND(J15-F15,2)
... A313: 2022 | B313: zinc | C313: 744341 | D313: 4190 | E313: 3118788790 | F313: 13.65 | G313: si | H313: =C313*D313 | I313: =ROUND(H313-E313,0) | J313: =ROUND(E313/SUMIFS($E$4:$E$313,$A$4:$A$313,A313)*100,2) | K313: =ROUND(J313-F313,2)

Sheet 12 Peso bloque X
A1: Peso del bloque - exportaciones (1992-2024)
A2: share_bloque = X_bloque / X_nacional x 100. Columna verde recomputa con formula de Excel y su diferencia. X_bloque de Comtrade; X_nacional del Banco Mundial (TX.VAL.MRCH.CD.WT, coincide con INEGI).
A3: anio | B3: X_bloque_musd | C3: X_nacional_musd | D3: share_bloque_pct | E3: share (=formula) % | F3: dif
A4: 1992 | B4: 1139.7 | C4: 46196 | D4: 2.467 | E4: =ROUND(B4/C4*100,2) | F4: =ROUND(E4-D4,2)
A5: 1993 | B5: 1214.1 | C5: 51886 | D5: 2.34 | E5: =ROUND(B5/C5*100,2) | F5: =ROUND(E5-D5,2)
A6: 1994 | B6: 1290.4 | C6: 60882 | D6: 2.12 | E6: =ROUND(B6/C6*100,2) | F6: =ROUND(E6-D6,2)
A7: 1995 | B7: 1894.5 | C7: 79542 | D7: 2.382 | E7: =ROUND(B7/C7*100,2) | F7: =ROUND(E7-D7,2)
A8: 1996 | B8: 1906.9 | C8: 96000 | D8: 1.986 | E8: =ROUND(B8/C8*100,2) | F8: =ROUND(E8-D8,2)
A9: 1997 | B9: 2057.5 | C9: 110431 | D9: 1.863 | E9: =ROUND(B9/C9*100,2) | F9: =ROUND(E9-D9,2)
A10: 1998 | B10: 2062.5 | C10: 117460 | D10: 1.756 | E10: =ROUND(B10/C10*100,2) | F10: =ROUND(E10-D10,2)
A11: 1999 | B11: 1964.2 | C11: 136391 | D11: 1.44 | E11: =ROUND(B11/C11*100,2) | F11: =ROUND(E11-D11,2)
A12: 2000 | B12: 2189.1 | C12: 166367 | D12: 1.316 | E12: =ROUND(B12/C12*100,2) | F12: =ROUND(E12-D12,2)
A13: 2001 | B13: 1926.9 | C13: 158547 | D13: 1.215 | E13: =ROUND(B13/C13*100,2) | F13: =ROUND(E13-D13,2)
A14: 2002 | B14: 1892.2 | C14: 160682 | D14: 1.178 | E14: =ROUND(B14/C14*100,2) | F14: =ROUND(E14-D14,2)
A15: 2003 | B15: 1995.5 | C15: 165396 | D15: 1.206 | E15: =ROUND(B15/C15*100,2) | F15: =ROUND(E15-D15,2)
... A36: 2024 | B36: 13725.7 | C36: 617677 | D36: 2.222 | E36: =ROUND(B36/C36*100,2) | F36: =ROUND(E36-D36,2)

Sheet 13 Peso bloque PIB
A1: Peso del bloque - PIB, VBP y empleo (MIP 2013 / 2018)
A2: Filas 'mineral' = cada mineral; 'BLOQUE_10' = suma; 'referencia' = TOTAL_economia / mineria_212 / mineria_21. pct_pib_economia = pib_mmp / PIB_total x 100 (columna verde recomputa contra la fila de referencia del mismo anio).
A3: anio | B3: nivel | C3: codigo | D3: mineral | E3: pib_mmp | F3: vbp_mmp | G3: pt_empleos | H3: remun_mmp | I3: pct_pib_economia | J3: pct_pib_mineria212 | K3: pct_vbp_economia | L3: pct_vbp_mineria212 | M3: pct_empleo_economia | N3: pct_empleo_mineria212 | O3: pct_pib_economia (=formula) | P3: dif
A4: 2013 | B4: mineral | C4: 212393 | D4: barita | E4: 222.8 | F4: 368.3 | G4: 1003 | H4: 125.1 | I4: 0.0014 | J4: 0.132 | K4: 0.0013 | L4: 0.139 | M4: 0.0017 | N4: 0.403 | O4: =IFERROR(ROUND(E4/SUMIFS($E$4:$E$29,$A$4:$A$29,A4,$D$4:$D$29,"TOTAL_economia")*100,4),"") | P4: =IF(ISNUMBER(O4),ROUND(O4-I4,4),"")
A5: 2013 | B5: mineral | C5: 212231 | D5: cobre | E5: 28083.9 | F5: 39971.4 | G5: 12523 | H5: 1105.6 | I5: 0.1794 | J5: 16.697 | K5: 0.1446 | L5: 15.135 | M5: 0.0218 | N5: 5.031 | O5: =IFERROR(ROUND(E5/SUMIFS($E$4:$E$29,$A$4:$A$29,A5,$D$4:$D$29,"TOTAL_economia")*100,4),"") | P5: =IF(ISNUMBER(O5),ROUND(O5-I5,4),"")
A6: 2013 | B6: mineral | C6: 212395 | D6: fluorita | E6: 1562.8 | F6: 2218.2 | G6: 1713 | H6: 208.2 | I6: 0.01 | J6: 0.929 | K6: 0.008 | L6: 0.84 | M6: 0.003 | N6: 0.688 | O6: =IFERROR(ROUND(E6/SUMIFS($E$4:$E$29,$A$4:$A$29,A6,$D$4:$D$29,"TOTAL_economia")*100,4),"") | P6: =IF(ISNUMBER(O6),ROUND(O6-I6,4),"")
A7: 2013 | B7: mineral | C7: 212396 | D7: grafito | E7: 123.7 | F7: 164.1 | G7: 229 | H7: 31 | I7: 0.0008 | J7: 0.074 | K7: 0.0006 | L7: 0.062 | M7: 0.0004 | N7: 0.092 | O7: =IFERROR(ROUND(E7/SUMIFS($E$4:$E$29,$A$4:$A$29,A7,$D$4:$D$29,"TOTAL_economia")*100,4),"") | P7: =IF(ISNUMBER(O7),ROUND(O7-I7,4),"")
A8: 2013 | B8: mineral | C8: 212291 | D8: manganeso | E8: 373.9 | F8: 486 | G8: 672 | H8: 107.5 | I8: 0.0024 | J8: 0.222 | K8: 0.0018 | L8: 0.184 | M8: 0.0012 | N8: 0.27 | O8: =IFERROR(ROUND(E8/SUMIFS($E$4:$E$29,$A$4:$A$29,A8,$D$4:$D$29,"TOTAL_economia")*100,4),"") | P8: =IF(ISNUMBER(O8),ROUND(O8-I8,4),"")
A9: 2013 | B9: mineral | C9: 212221 | D9: oro | E9: 32499 | F9: 49607.2 | G9: 12310 | H9: 169.2 | I9: 0.2076 | J9: 19.321 | K9: 0.1795 | L9: 18.783 | M9: 0.0214 | N9: 4.946 | O9: =IFERROR(ROUND(E9/SUMIFS($E$4:$E$29,$A$4:$A$29,A9,$D$4:$D$29,"TOTAL_economia")*100,4),"") | P9: =IF(ISNUMBER(O9),ROUND(O9-I9,4),"")
A10: 2013 | B10: mineral | C10: 212222 | D10: plata | E10: 29754.2 | F10: 44680.4 | G10: 17983 | H10: 1614.3 | I10: 0.1901 | J10: 17.69 | K10: 0.1616 | L10: 16.918 | M10: 0.0313 | N10: 7.225 | O10: =IFERROR(ROUND(E10/SUMIFS($E$4:$E$29,$A$4:$A$29,A10,$D$4:$D$29,"TOTAL_economia")*100,4),"") | P10: =IF(ISNUMBER(O10),ROUND(O10-I10,4),"")
A11: 2013 | B11: mineral | C11: 212232 | D11: plomo-zinc | E11: 13865.2 | F11: 20045.8 | G11: 10178 | H11: 1509.7 | I11: 0.0886 | J11: 8.243 | K11: 0.0725 | L11: 7.59 | M11: 0.0177 | N11: 4.089 | O11: =IFERROR(ROUND(E11/SUMIFS($E$4:$E$29,$A$4:$A$29,A11,$D$4:$D$29,"TOTAL_economia")*100,4),"") | P11: =IF(ISNUMBER(O11),ROUND(O11-I11,4),"")
A12: 2013 | B12: mineral | C12: 212324 | D12: silice | E12: 3154.1 | F12: 4898.3 | G12: 2863 | H12: 391 | I12: 0.0202 | J12: 1.875 | K12: 0.0177 | L12: 1.855 | M12: 0.005 | N12: 1.15 | O12: =IFERROR(ROUND(E12/SUMIFS($E$4:$E$29,$A$4:$A$29,A12,$D$4:$D$29,"TOTAL_economia")*100,4),"") | P12: =IF(ISNUMBER(O12),ROUND(O12-I12,4),"")
A13: 2013 | B13: BLOQUE_10 | D13: bloque 10 minerales | E13: 109639.6 | F13: 162439.8 | G13: 59474 | H13: 5261.6 | I13: 0.7005 | J13: 65.183 | K13: 0.5876 | L13: 61.506 | M13: 0.1035 | N13: 23.894 | O13: =IFERROR(ROUND(E13/SUMIFS($E$4:$E$29,$A$4:$A$29,A13,$D$4:$D$29,"TOTAL_economia")*100,4),"") | P13: =IF(ISNUMBER(O13),ROUND(O13-I13,4),"")
A14: 2013 | B14: referencia | D14: TOTAL_economia | E14: 15652079 | F14: 27642648 | G14: 57465990 | I14: 100 | K14: 100 | M14: 100 | O14: =IFERROR(ROUND(E14/SUMIFS($E$4:$E$29,$A$4:$A$29,A14,$D$4:$D$29,"TOTAL_economia")*100,4),"") | P14: =IF(ISNUMBER(O14),ROUND(O14-I14,4),"")
A15: 2013 | B15: referencia | D15: mineria_212 | E15: 168202.3 | F15: 264101.8 | G15: 248908 | I15: 1.075 | K15: 0.955 | M15: 0.433 | O15: =IFERROR(ROUND(E15/SUMIFS($E$4:$E$29,$A$4:$A$29,A15,$D$4:$D$29,"TOTAL_economia")*100,4),"") | P15: =IF(ISNUMBER(O15),ROUND(O15-I15,4),"")
A16: 2013 | B16: referencia | D16: mineria_21 | E16: 1147243.6 | F16: 1463213.4 | G16: 0 | I16: 7.33 | K16: 5.293 | M16: 0 | O16: =IFERROR(ROUND(E16/SUMIFS($E$4:$E$29,$A$4:$A$29,A16,$D$4:$D$29,"TOTAL_economia")*100,4),"") | P16: =IF(ISNUMBER(O16),ROUND(O16-I16,4),"")
A17: 2018 | B17: mineral | C17: 212393 | D17: barita | E17: 452.4 | F17: 685.6 | G17: 1713 | H17: 228.5 | I17: 0.002 | J17: 0.169 | K17: 0.0016 | L17: 0.163 | M17: 0.0029 | N17: 0.864 | O17: =IFERROR(ROUND(E17/SUMIFS($E$4:$E$29,$A$4:$A$29,A17,$D$4:$D$29,"TOTAL_economia")*100,4),"") | P17: =IF(ISNUMBER(O17),ROUND(O17-I17,4),"")
A18: 2018 | B18: mineral | C18: 212231 | D18: cobre | E18: 62412.4 | F18: 92893 | G18: 8718 | H18: 3230.4 | I18: 0.2692 | J18: 23.257 | K18: 0.2214 | L18: 22.101 | M18: 0.0147 | N18: 4.397 | O18: =IFERROR(ROUND(E18/SUMIFS($E$4:$E$29,$A$4:$A$29,A18,$D$4:$D$29,"TOTAL_economia")*100,4),"") | P18: =IF(ISNUMBER(O18),ROUND(O18-I18,4),"")
A19: 2018 | B19: mineral | C19: 212395 | D19: fluorita | E19: 3717.5 | F19: 5861.8 | G19: 740 | H19: 78.5 | I19: 0.016 | J19: 1.385 | K19: 0.014 | L19: 1.395 | M19: 0.0012 | N19: 0.373 | O19: =IFERROR(ROUND(E19/SUMIFS($E$4:$E$29,$A$4:$A$29,A19,$D$4:$D$29,"TOTAL_economia")*100,4),"") | P19: =IF(ISNUMBER(O19),ROUND(O19-I19,4),"")
A20: 2018 | B20: mineral | C20: 212396 | D20: grafito | E20: 568.1 | F20: 719.8 | G20: 627 | H20: 112 | I20: 0.0025 | J20: 0.212 | K20: 0.0017 | L20: 0.171 | M20: 0.0011 | N20: 0.316 | O20: =IFERROR(ROUND(E20/SUMIFS($E$4:$E$29,$A$4:$A$29,A20,$D$4:$D$29,"TOTAL_economia")*100,4),"") | P20: =IF(ISNUMBER(O20),ROUND(O20-I20,4),"")
A21: 2018 | B21: mineral | C21: 212291 | D21: manganeso | E21: 309.3 | F21: 635 | G21: 523 | H21: 204.2 | I21: 0.0013 | J21: 0.115 | K21: 0.0015 | L21: 0.151 | M21: 0.0009 | N21: 0.264 | O21: =IFERROR(ROUND(E21/SUMIFS($E$4:$E$29,$A$4:$A$29,A21,$D$4:$D$29,"TOTAL_economia")*100,4),"") | P21: =IF(ISNUMBER(O21),ROUND(O21-I21,4),"")
A22: 2018 | B22: mineral | C22: 212221 | D22: oro | E22: 39301.9 | F22: 69491.1 | G22: 4931 | H22: 1274.5 | I22: 0.1695 | J22: 14.645 | K22: 0.1656 | L22: 16.534 | M22: 0.0083 | N22: 2.487 | O22: =IFERROR(ROUND(E22/SUMIFS($E$4:$E$29,$A$4:$A$29,A22,$D$4:$D$29,"TOTAL_economia")*100,4),"") | P22: =IF(ISNUMBER(O22),ROUND(O22-I22,4),"")
A23: 2018 | B23: mineral | C23: 212222 | D23: plata | E23: 30917.3 | F23: 49784.4 | G23: 7598 | H23: 1783.5 | I23: 0.1333 | J23: 11.521 | K23: 0.1186 | L23: 11.845 | M23: 0.0128 | N23: 3.832 | O23: =IFERROR(ROUND(E23/SUMIFS($E$4:$E$29,$A$4:$A$29,A23,$D$4:$D$29,"TOTAL_economia")*100,4),"") | P23: =IF(ISNUMBER(O23),ROUND(O23-I23,4),"")
A24: 2018 | B24: mineral | C24: 212232 | D24: plomo-zinc | E24: 21683.1 | F24: 34724.7 | G24: 11667 | H24: 3103.1 | I24: 0.0935 | J24: 8.08 | K24: 0.0828 | L24: 8.262 | M24: 0.0196 | N24: 5.884 | O24: =IFERROR(ROUND(E24/SUMIFS($E$4:$E$29,$A$4:$A$29,A24,$D$4:$D$29,"TOTAL_economia")*100,4),"") | P24: =IF(ISNUMBER(O24),ROUND(O24-I24,4),"")
A25: 2018 | B25: mineral | C25: 212324 | D25: silice | E25: 4388.1 | F25: 6959.1 | G25: 5642 | H25: 1324.5 | I25: 0.0189 | J25: 1.635 | K25: 0.0166 | L25: 1.656 | M25: 0.0095 | N25: 2.846 | O25: =IFERROR(ROUND(E25/SUMIFS($E$4:$E$29,$A$4:$A$29,A25,$D$4:$D$29,"TOTAL_economia")*100,4),"") | P25: =IF(ISNUMBER(O25),ROUND(O25-I25,4),"")
A26: 2018 | B26: BLOQUE_10 | D26: bloque 10 minerales | E26: 163750 | F26: 261754.4 | G26: 42159 | H26: 11339.1 | I26: 0.7062 | J26: 61.019 | K26: 0.6238 | L26: 62.277 | M26: 0.0708 | N26: 21.264 | O26: =IFERROR(ROUND(E26/SUMIFS($E$4:$E$29,$A$4:$A$29,A26,$D$4:$D$29,"TOTAL_economia")*100,4),"") | P26: =IF(ISNUMBER(O26),ROUND(O26-I26,4),"")
A27: 2018 | B27: referencia | D27: TOTAL_economia | E27: 23186147 | F27: 41959242 | G27: 59505022 | I27: 100 | K27: 100 | M27: 100 | O27: =IFERROR(ROUND(E27/SUMIFS($E$4:$E$29,$A$4:$A$29,A27,$D$4:$D$29,"TOTAL_economia")*100,4),"") | P27: =IF(ISNUMBER(O27),ROUND(O27-I27,4),"")
A28: 2018 | B28: referencia | D28: mineria_212 | E28: 268357.7 | F28: 420304.1 | G28: 198267 | I28: 1.157 | K28: 1.002 | M28: 0.333 | O28: =IFERROR(ROUND(E28/SUMIFS($E$4:$E$29,$A$4:$A$29,A28,$D$4:$D$29,"TOTAL_economia")*100,4),"") | P28: =IF(ISNUMBER(O28),ROUND(O28-I28,4),"")
A29: 2018 | B29: referencia | D29: mineria_21 | E29: 955396.1 | F29: 1458602.4 | G29: 0 | I29: 4.121 | K29: 3.476 | M29: 0 | O29: =IFERROR(ROUND(E29/SUMIFS($E$4:$E$29,$A$4:$A$29,A29,$D$4:$D$29,"TOTAL_economia")*100,4),"") | P29: =IF(ISNUMBER(O29),ROUND(O29-I29,4),"")

Sheet 14 MIP encadenam
A1: MIP nacional - encadenamientos por mineral (2013 y 2018)
A2: Leontief L=(I-A)^-1 y Ghosh G=(I-B)^-1 calculados en Python y VALIDADOS contra ctec/cdi de INEGI a 1e-15. Aqui se exponen las sumas (backward_L_colsum, forward_G_rowsum). El paso de normalizacion Rasmussen (media economia=1) SI es formula viva: Rasmussen = suma / media_economia, con la media documentada por anio abajo. di_sobre_vbp tambien es formula viva. Plomo-zinc van combinados (clase 212232).
A3: anio | B3: codigo | C3: mineral | D3: vbp_mmpesos | E3: di_domestica_mmpesos | F3: di_sobre_vbp | G3: backward_L_colsum | H3: forward_G_rowsum | I3: backward_rasmussen | J3: forward_rasmussen | K3: rank_backward | L3: rank_forward | M3: n_sectores | N3: DI/VBP (=formula) | O3: dif DI/VBP | P3: fwd Rasmussen (=formula) | Q3: dif fwd | R3: bwd Rasmussen (=formula) | S3: dif bwd
A4: 2013 | B4: 212393 | C4: barita | D4: 368.345 | E4: 64.719 | F4: 0.1757 | G4: 1.442 | H4: 1.2082 | I4: 0.9554 | J4: 0.764 | K4: 482 | L4: 444 | M4: 822 | N4: =ROUND(E4/D4,4) | O4: =ROUND(N4-F4,4) | P4: =ROUND(H4/INDEX($B$26:$B$27,MATCH(A4,$A$26:$A$27,0)),4) | Q4: =ROUND(P4-J4,4) | R4: =ROUND(G4/INDEX($C$26:$C$27,MATCH(A4,$A$26:$A$27,0)),4) | S4: =ROUND(R4-I4,4)
A5: 2013 | B5: 212231 | C5: cobre | D5: 39971.368 | E5: 18276.824 | F5: 0.4572 | G5: 1.3406 | H5: 1.8677 | I5: 0.8882 | J5: 1.1811 | K5: 634 | L5: 283 | M5: 822 | N5: =ROUND(E5/D5,4) | O5: =ROUND(N5-F5,4) | P5: =ROUND(H5/INDEX($B$26:$B$27,MATCH(A5,$A$26:$A$27,0)),4) | Q5: =ROUND(P5-J5,4) | R5: =ROUND(G5/INDEX($C$26:$C$27,MATCH(A5,$A$26:$A$27,0)),4) | S5: =ROUND(R5-I5,4)
A6: 2013 | B6: 212395 | C6: fluorita | D6: 2218.245 | E6: 489.471 | F6: 0.2207 | G6: 1.2854 | H6: 1.3766 | I6: 0.8517 | J6: 0.8705 | K6: 682 | L6: 383 | M6: 822 | N6: =ROUND(E6/D6,4) | O6: =ROUND(N6-F6,4) | P6: =ROUND(H6/INDEX($B$26:$B$27,MATCH(A6,$A$26:$A$27,0)),4) | Q6: =ROUND(P6-J6,4) | R6: =ROUND(G6/INDEX($C$26:$C$27,MATCH(A6,$A$26:$A$27,0)),4) | S6: =ROUND(R6-I6,4)
A7: 2013 | B7: 212396 | C7: grafito | D7: 164.102 | E7: 97.201 | F7: 0.5923 | G7: 1.2626 | H7: 1.9547 | I7: 0.8366 | J7: 1.2361 | K7: 700 | L7: 257 | M7: 822 | N7: =ROUND(E7/D7,4) | O7: =ROUND(N7-F7,4) | P7: =ROUND(H7/INDEX($B$26:$B$27,MATCH(A7,$A$26:$A$27,0)),4) | Q7: =ROUND(P7-J7,4) | R7: =ROUND(G7/INDEX($C$26:$C$27,MATCH(A7,$A$26:$A$27,0)),4) | S7: =ROUND(R7-I7,4)
A8: 2013 | B8: 212291 | C8: manganeso | D8: 486.019 | E8: 348.529 | F8: 0.7171 | G8: 1.2518 | H8: 2.8289 | I8: 0.8294 | J8: 1.7889 | K8: 709 | L8: 34 | M8: 822 | N8: =ROUND(E8/D8,4) | O8: =ROUND(N8-F8,4) | P8: =ROUND(H8/INDEX($B$26:$B$27,MATCH(A8,$A$26:$A$27,0)),4) | Q8: =ROUND(P8-J8,4) | R8: =ROUND(G8/INDEX($C$26:$C$27,MATCH(A8,$A$26:$A$27,0)),4) | S8: =ROUND(R8-I8,4)
A9: 2013 | B9: 212221 | C9: oro | D9: 49607.237 | E9: 49526.353 | F9: 0.9984 | G9: 1.386 | H9: 2.1296 | I9: 0.9183 | J9: 1.3467 | K9: 570 | L9: 173 | M9: 822 | N9: =ROUND(E9/D9,4) | O9: =ROUND(N9-F9,4) | P9: =ROUND(H9/INDEX($B$26:$B$27,MATCH(A9,$A$26:$A$27,0)),4) | Q9: =ROUND(P9-J9,4) | R9: =ROUND(G9/INDEX($C$26:$C$27,MATCH(A9,$A$26:$A$27,0)),4) | S9: =ROUND(R9-I9,4)
A10: 2013 | B10: 212222 | C10: plata | D10: 44680.402 | E10: 42728.777 | F10: 0.9563 | G10: 1.3761 | H10: 2.0579 | I10: 0.9118 | J10: 1.3014 | K10: 578 | L10: 206 | M10: 822 | N10: =ROUND(E10/D10,4) | O10: =ROUND(N10-F10,4) | P10: =ROUND(H10/INDEX($B$26:$B$27,MATCH(A10,$A$26:$A$27,0)),4) | Q10: =ROUND(P10-J10,4) | R10: =ROUND(G10/INDEX($C$26:$C$27,MATCH(A10,$A$26:$A$27,0)),4) | S10: =ROUND(R10-I10,4)
A11: 2013 | B11: 212232 | C11: plomo-zinc | D11: 20045.785 | E11: 2491.224 | F11: 0.1243 | G11: 1.3486 | H11: 1.1314 | I11: 0.8935 | J11: 0.7154 | K11: 623 | L11: 479 | M11: 822 | N11: =ROUND(E11/D11,4) | O11: =ROUND(N11-F11,4) | P11: =ROUND(H11/INDEX($B$26:$B$27,MATCH(A11,$A$26:$A$27,0)),4) | Q11: =ROUND(P11-J11,4) | R11: =ROUND(G11/INDEX($C$26:$C$27,MATCH(A11,$A$26:$A$27,0)),4) | S11: =ROUND(R11-I11,4)
A12: 2013 | B12: 212324 | C12: silice | D12: 4898.266 | E12: 4845.318 | F12: 0.9892 | G12: 1.3743 | H12: 2.8412 | I12: 0.9106 | J12: 1.7967 | K12: 581 | L12: 31 | M12: 822 | N12: =ROUND(E12/D12,4) | O12: =ROUND(N12-F12,4) | P12: =ROUND(H12/INDEX($B$26:$B$27,MATCH(A12,$A$26:$A$27,0)),4) | Q12: =ROUND(P12-J12,4) | R12: =ROUND(G12/INDEX($C$26:$C$27,MATCH(A12,$A$26:$A$27,0)),4) | S12: =ROUND(R12-I12,4)
A13: 2018 | B13: 212393 | C13: barita | D13: 685.596 | E13: 21.998 | F13: 0.0321 | G13: 1.3834 | H13: 1.0409 | I13: 0.9601 | J13: 0.6438 | K13: 471 | L13: 614 | M13: 834 | N13: =ROUND(E13/D13,4) | O13: =ROUND(N13-F13,4) | P13: =ROUND(H13/INDEX($B$26:$B$27,MATCH(A13,$A$26:$A$27,0)),4) | Q13: =ROUND(P13-J13,4) | R13: =ROUND(G13/INDEX($C$26:$C$27,MATCH(A13,$A$26:$A$27,0)),4) | S13: =ROUND(R13-I13,4)
A14: 2018 | B14: 212231 | C14: cobre | D14: 92892.952 | E14: 49055.907 | F14: 0.5281 | G14: 1.354 | H14: 2.1683 | I14: 0.9397 | J14: 1.3411 | K14: 516 | L14: 185 | M14: 834 | N14: =ROUND(E14/D14,4) | O14: =ROUND(N14-F14,4) | P14: =ROUND(H14/INDEX($B$26:$B$27,MATCH(A14,$A$26:$A$27,0)),4) | Q14: =ROUND(P14-J14,4) | R14: =ROUND(G14/INDEX($C$26:$C$27,MATCH(A14,$A$26:$A$27,0)),4) | S14: =ROUND(R14-I14,4)
A15: 2018 | B15: 212395 | C15: fluorita | D15: 5861.771 | E15: 2954.788 | F15: 0.5041 | G15: 1.4019 | H15: 2.1194 | I15: 0.9729 | J15: 1.3109 | K15: 433 | L15: 200 | M15: 834 | N15: =ROUND(E15/D15,4) | O15: =ROUND(N15-F15,4) | P15: =ROUND(H15/INDEX($B$26:$B$27,MATCH(A15,$A$26:$A$27,0)),4) | Q15: =ROUND(P15-J15,4) | R15: =ROUND(G15/INDEX($C$26:$C$27,MATCH(A15,$A$26:$A$27,0)),4) | S15: =ROUND(R15-I15,4)
... A21: 2018 | B21: 212324 | C21: silice | D21: 6959.054 | E21: 6895.377 | F21: 0.9908 | G21: 1.3517 | H21: 3.0978 | I21: 0.9381 | J21: 1.9159 | K21: 521 | L21: 18 | M21: 834 | N21: =ROUND(E21/D21,4) | O21: =ROUND(N21-F21,4) | P21: =ROUND(H21/INDEX($B$26:$B$27,MATCH(A21,$A$26:$A$27,0)),4) | Q21: =ROUND(P21-J21,4) | R21: =ROUND(G21/INDEX($C$26:$C$27,MATCH(A21,$A$26:$A$27,0)),4) | S21: =ROUND(R21-I21,4)
A24: Medias de la economia (denominador Rasmussen; = promedio de las sumas de las 822 clases, del script)
A25: anio | B25: media_forward_rowsum | C25: media_backward_colsum
A26: 2013 | B26: 1.581368 | C26: 1.509273
A27: 2018 | B27: 1.616847 | C27: 1.440883
A30: Corte de referencia 2008 (base 2008 / SCIAN 2007) - NO comparable en nivel, se lee por patron
A31: anio | B31: codigo | C31: mineral | D31: vbp_mmpesos | E31: di_domestica_mmpesos | F31: di_sobre_vbp | G31: backward_L_colsum | H31: forward_G_rowsum | I31: backward_rasmussen | J31: forward_rasmussen | K31: rank_backward | L31: rank_forward | M31: n_sectores | N31: base_scian | O31: comparabilidad | P31: nota
A32: 2008 | B32: 212393 | C32: barita | D32: 270.007 | E32: 241.821 | F32: 0.8956 | G32: 1.461 | H32: 1.9905 | I32: 0.9631 | J32: 1.288 | K32: 465 | L32: 226 | M32: 814 | N32: SCIAN2007_base2008 | O32: referencia
A33: 2008 | B33: 212231 | C33: cobre | D33: 12361.414 | E33: 9165.077 | F33: 0.7414 | G33: 1.2752 | H33: 2.5131 | I33: 0.8406 | J33: 1.6261 | K33: 699 | L33: 57 | M33: 814 | N33: SCIAN2007_base2008 | O33: referencia
A34: 2008 | B34: 212395 | C34: fluorita | D34: 1286.14 | E34: 456.84 | F34: 0.3552 | G34: 1.4899 | H34: 1.7203 | I34: 0.9821 | J34: 1.1131 | K34: 425 | L34: 292 | M34: 814 | N34: SCIAN2007_base2008 | O34: referencia
A35: 2008 | B35: 212396 | C35: grafito | D35: 403.637 | E35: 368.169 | F35: 0.9121 | G35: 1.4781 | H35: 2.6035 | I35: 0.9743 | J35: 1.6846 | K35: 441 | L35: 41 | M35: 814 | N35: SCIAN2007_base2008 | O35: referencia
A36: 2008 | B36: 212291 | C36: manganeso | D36: 8104.873 | E36: 2215.048 | F36: 0.2733 | G36: 1.308 | H36: 1.5504 | I36: 0.8622 | J36: 1.0032 | K36: 658 | L36: 329 | M36: 814 | N36: SCIAN2007_base2008 | O36: referencia | P36: clase 212291 mas amplia en 2008 (agrega 212292 mercurio/antimonio y 212299 otros metalicos); en 2018 son clases aparte -> nivel no comparable
A37: 2008 | B37: 212221 | C37: oro | D37: 12804.416 | E37: 12531.589 | F37: 0.9787 | G37: 1.4403 | H37: 2.2881 | I37: 0.9494 | J37: 1.4805 | K37: 491 | L37: 115 | M37: 814 | N37: SCIAN2007_base2008 | O37: referencia
A38: 2008 | B38: 212222 | C38: plata | D38: 19037.077 | E38: 3419.443 | F38: 0.1796 | G38: 1.4277 | H38: 1.2303 | I38: 0.9412 | J38: 0.7961 | K38: 505 | L38: 430 | M38: 814 | N38: SCIAN2007_base2008 | O38: referencia
A39: 2008 | B39: 212232 | C39: plomo-zinc | D39: 7929.981 | E39: 6222.117 | F39: 0.7846 | G39: 1.4914 | H39: 2.0911 | I39: 0.9831 | J39: 1.3531 | K39: 422 | L39: 176 | M39: 814 | N39: SCIAN2007_base2008 | O39: referencia
A40: 2008 | B40: 212324 | C40: silice | D40: 1216.574 | E40: 988.052 | F40: 0.8122 | G40: 1.3574 | H40: 2.4723 | I40: 0.8948 | J40: 1.5997 | K40: 605 | L40: 69 | M40: 814 | N40: SCIAN2007_base2008 | O40: referencia

Sheet 15 MIP eslabones
A1: MIP nacional - encadenamiento por eslabon (extraccion / refinacion / semimanufactura)
A2: Ghosh-Rasmussen por clase SCIAN de cada eslabon: prueba si el arrastre hacia adelante se sostiene al descender por la cadena. 'atribuible' indica si la clase SCIAN es propia del mineral o compartida. Resultado del script (mismo metodo validado que la hoja 14).
A3: anio | B3: mineral | C3: eslabon | D3: tipo | E3: scian | F3: clase | G3: atribuible | H3: vbp_mmpesos | I3: forward_G_rowsum | J3: forward_rasmussen | K3: backward_rasmussen | L3: rank_forward | M3: rank_backward | N3: n_sectores
A4: 2008 | B4: barita | C4: L1 | D4: extraccion | E4: 212393 | F4: Minería de barita | G4: si | H4: 270 | I4: 1.9905 | J4: 1.288 | K4: 0.9631 | L4: 226 | M4: 465 | N4: 814
A5: 2008 | B5: barita | C5: L2 | D5: refinacion | E5: 325180 | F5: Fabricación de otros productos químicos básicos | G5: no | H5: 27627.8 | I5: 2.0753 | J5: 1.3428 | K5: 1.125 | L5: 184 | M5: 156 | N5: 814
A6: 2008 | B6: barita | C6: L3 | D6: semimanufactura | F6: (sin clase separable) | G6: - | N6: 814
A7: 2008 | B7: cobre | C7: L1 | D7: extraccion | E7: 212231 | F7: Minería de cobre | G7: si | H7: 12361.4 | I7: 2.5131 | J7: 1.6261 | K7: 0.8406 | L7: 57 | M7: 699 | N7: 814
A8: 2008 | B8: cobre | C8: L2 | D8: refinacion | E8: 331411 | F8: Fundición y refinación de cobre | G8: si | H8: 19380.2 | I8: 2.1006 | J8: 1.3592 | K8: 1.1495 | L8: 172 | M8: 126 | N8: 814
A9: 2008 | B9: cobre | C9: L3 | D9: semimanufactura | E9: 331420 | F9: Laminación secundaria de cobre | G9: si | H9: 32740.1 | I9: 1.7034 | J9: 1.1022 | K9: 1.1042 | L9: 296 | M9: 195 | N9: 814
A10: 2008 | B10: fluorita | C10: L1 | D10: extraccion | E10: 212395 | F10: Minería de fluorita | G10: si | H10: 1286.1 | I10: 1.7203 | J10: 1.1131 | K10: 0.9821 | L10: 292 | M10: 425 | N10: 814
A11: 2008 | B11: fluorita | C11: L2 | D11: refinacion | E11: 325180 | F11: Fabricación de otros productos químicos básicos | G11: no | H11: 27627.8 | I11: 2.0753 | J11: 1.3428 | K11: 1.125 | L11: 184 | M11: 156 | N11: 814
A12: 2008 | B12: fluorita | C12: L3 | D12: semimanufactura | E12: 325211 | F12: Fabricación de resinas sintéticas | G12: no | H12: 50966.7 | I12: 2.1577 | J12: 1.3961 | K12: 1.1319 | L12: 150 | M12: 143 | N12: 814
A13: 2008 | B13: grafito | C13: L1 | D13: extraccion | E13: 212396 | F13: Minería de grafito | G13: si | H13: 403.6 | I13: 2.6035 | J13: 1.6846 | K13: 0.9743 | L13: 41 | M13: 441 | N13: 814
A14: 2008 | B14: grafito | C14: L2 | D14: refinacion | E14: 325180 | F14: Fabricación de otros productos químicos básicos | G14: no | H14: 27627.8 | I14: 2.0753 | J14: 1.3428 | K14: 1.125 | L14: 184 | M14: 156 | N14: 814
A15: 2008 | B15: grafito | C15: L3 | D15: semimanufactura | E15: 327999 | F15: Fabricación de otros productos a base de mineral | G15: no | H15: 4310.1 | I15: 1.821 | J15: 1.1783 | K15: 1.1776 | L15: 273 | M15: 91 | N15: 814
A16: 2008 | B16: manganeso | C16: L1 | D16: extraccion | E16: 212291 | F16: Minería de manganeso (incluye a la 212292 "Miner | G16: si | H16: 8104.9 | I16: 1.5504 | J16: 1.0032 | K16: 0.8622 | L16: 329 | M16: 658 | N16: 814
A17: 2008 | B17: manganeso | C17: L2 | D17: refinacion | E17: 331112 | F17: Fabricación de desbastes primarios y ferroaleaci | G17: comp | H17: 37451.2 | I17: 1.9581 | J17: 1.267 | K17: 1.3342 | L17: 236 | M17: 21 | N17: 814
A18: 2008 | B18: manganeso | C18: L3 | D18: semimanufactura | F18: (sin clase separable) | G18: - | N18: 814
A19: 2008 | B19: oro | C19: L1 | D19: extraccion | E19: 212221 | F19: Minería de oro | G19: si | H19: 12804.4 | I19: 2.2881 | J19: 1.4805 | K19: 0.9494 | L19: 115 | M19: 491 | N19: 814
A20: 2008 | B20: oro | C20: L2 | D20: refinacion | E20: 331412 | F20: Fundición y refinación de metales preciosos | G20: comp | H20: 30578.1 | I20: 1 | J20: 0.6471 | K20: 1.3397 | L20: 752 | M20: 19 | N20: 814
A21: 2008 | B21: oro | C21: L3 | D21: semimanufactura | E21: 331490 | F21: Laminación secundaria de otros metales no ferros | G21: comp | H21: 23564.1 | I21: 1.7144 | J21: 1.1093 | K21: 1.2706 | L21: 295 | M21: 37 | N21: 814
A22: 2008 | B22: plata | C22: L1 | D22: extraccion | E22: 212222 | F22: Minería de plata | G22: si | H22: 19037.1 | I22: 1.2303 | J22: 0.7961 | K22: 0.9412 | L22: 430 | M22: 505 | N22: 814
A23: 2008 | B23: plata | C23: L2 | D23: refinacion | E23: 331412 | F23: Fundición y refinación de metales preciosos | G23: comp | H23: 30578.1 | I23: 1 | J23: 0.6471 | K23: 1.3397 | L23: 752 | M23: 19 | N23: 814
A24: 2008 | B24: plata | C24: L3 | D24: semimanufactura | E24: 331490 | F24: Laminación secundaria de otros metales no ferros | G24: comp | H24: 23564.1 | I24: 1.7144 | J24: 1.1093 | K24: 1.2706 | L24: 295 | M24: 37 | N24: 814
A25: 2008 | B25: plomo-zinc | C25: L1 | D25: extraccion | E25: 212232 | F25: Minería de plomo y zinc | G25: si | H25: 7930 | I25: 2.0911 | J25: 1.3531 | K25: 0.9831 | L25: 176 | M25: 422 | N25: 814
A26: 2008 | B26: plomo-zinc | C26: L2 | D26: refinacion | E26: 331419 | F26: Fundición y refinación de otros metales no ferro | G26: comp | H26: 7252.7 | I26: 1.2351 | J26: 0.7992 | K26: 1.0535 | L26: 427 | M26: 279 | N26: 814
A27: 2008 | B27: plomo-zinc | C27: L3 | D27: semimanufactura | E27: 331490 | F27: Laminación secundaria de otros metales no ferros | G27: comp | H27: 23564.1 | I27: 1.7144 | J27: 1.1093 | K27: 1.2706 | L27: 295 | M27: 37 | N27: 814
A28: 2008 | B28: silice | C28: L1 | D28: extraccion | E28: 212324 | F28: Minería de sílice | G28: si | H28: 1216.6 | I28: 2.4723 | J28: 1.5997 | K28: 0.8948 | L28: 69 | M28: 605 | N28: 814
A29: 2008 | B29: silice | C29: L2 | D29: refinacion | E29: 325180 | F29: Fabricación de otros productos químicos básicos | G29: no | H29: 27627.8 | I29: 2.0753 | J29: 1.3428 | K29: 1.125 | L29: 184 | M29: 156 | N29: 814
A30: 2008 | B30: silice | C30: L3 | D30: semimanufactura | E30: 327211 | F30: Fabricación de vidrio | G30: no | H30: 13476.5 | I30: 1.7157 | J30: 1.1101 | K30: 1.2158 | L30: 293 | M30: 61 | N30: 814
... A32: 2013 | B32: barita | C32: L2 | D32: refinacion | E32: 325180 | F32: FabricaciÃ³n de otros productos quÃ­micos bÃ¡sic | G32: no | H32: 29781.2 | I32: 2.1251 | J32: 1.3438 | K32: 0.9934 | L32: 174 | M32: 398 | N32: 822
A33: 2013 | B33: barita | C33: L3 | D33: semimanufactura | F33: (sin clase separable) | G33: - | N33: 822
A34: 2013 | B34: cobre | C34: L1 | D34: extraccion | E34: 212231 | F34: MinerÃ­a de cobre | G34: si | H34: 39971.4 | I34: 1.8677 | J34: 1.1811 | K34: 0.8882 | L34: 283 | M34: 634 | N34: 822
A35: 2013 | B35: cobre | C35: L2 | D35: refinacion | E35: 331411 | F35: FundiciÃ³n y refinaciÃ³n de cobre | G35: si | H35: 29375.5 | I35: 1.875 | J35: 1.1857 | K35: 1.0386 | L35: 281 | M35: 320 | N35: 822
A36: 2013 | B36: cobre | C36: L3 | D36: semimanufactura | E36: 331420 | F36: LaminaciÃ³n secundaria de cobre | G36: si | H36: 48774.4 | I36: 1.9255 | J36: 1.2176 | K36: 1.2146 | L36: 270 | M36: 71 | N36: 822
A37: 2013 | B37: fluorita | C37: L1 | D37: extraccion | E37: 212395 | F37: MinerÃ­a de fluorita | G37: si | H37: 2218.2 | I37: 1.3766 | J37: 0.8705 | K37: 0.8517 | L37: 383 | M37: 682 | N37: 822
A38: 2013 | B38: fluorita | C38: L2 | D38: refinacion | E38: 325180 | F38: FabricaciÃ³n de otros productos quÃ­micos bÃ¡sic | G38: no | H38: 29781.2 | I38: 2.1251 | J38: 1.3438 | K38: 0.9934 | L38: 174 | M38: 398 | N38: 822
A39: 2013 | B39: fluorita | C39: L3 | D39: semimanufactura | E39: 325211 | F39: FabricaciÃ³n de resinas sintÃ©ticas | G39: no | H39: 78302.2 | I39: 1.789 | J39: 1.1313 | K39: 1.012 | L39: 296 | M39: 369 | N39: 822
A40: 2013 | B40: grafito | C40: L1 | D40: extraccion | E40: 212396 | F40: MinerÃ­a de grafito | G40: si | H40: 164.1 | I40: 1.9547 | J40: 1.2361 | K40: 0.8366 | L40: 257 | M40: 700 | N40: 822
A41: 2013 | B41: grafito | C41: L2 | D41: refinacion | E41: 325180 | F41: FabricaciÃ³n de otros productos quÃ­micos bÃ¡sic | G41: no | H41: 29781.2 | I41: 2.1251 | J41: 1.3438 | K41: 0.9934 | L41: 174 | M41: 398 | N41: 822
A42: 2013 | B42: grafito | C42: L3 | D42: semimanufactura | E42: 327999 | F42: FabricaciÃ³n de otros productos a base de minera | G42: no | H42: 13582.9 | I42: 2.5563 | J42: 1.6165 | K42: 1.2691 | L42: 68 | M42: 34 | N42: 822
A43: 2013 | B43: manganeso | C43: L1 | D43: extraccion | E43: 212291 | F43: MinerÃ­a de manganeso | G43: si | H43: 486 | I43: 2.8289 | J43: 1.7889 | K43: 0.8294 | L43: 34 | M43: 709 | N43: 822
A44: 2013 | B44: manganeso | C44: L2 | D44: refinacion | E44: 331112 | F44: FabricaciÃ³n de desbastes primarios y ferroaleac | G44: comp | H44: 39821.9 | I44: 2.6033 | J44: 1.6462 | K44: 1.0538 | L44: 62 | M44: 287 | N44: 822
A45: 2013 | B45: manganeso | C45: L3 | D45: semimanufactura | F45: (sin clase separable) | G45: - | N45: 822
A46: 2013 | B46: oro | C46: L1 | D46: extraccion | E46: 212221 | F46: MinerÃ­a de oro | G46: si | H46: 49607.2 | I46: 2.1296 | J46: 1.3467 | K46: 0.9183 | L46: 173 | M46: 570 | N46: 822
A47: 2013 | B47: oro | C47: L2 | D47: refinacion | E47: 331412 | F47: FundiciÃ³n y refinaciÃ³n de metales preciosos | G47: comp | H47: 143518.8 | I47: 1.0401 | J47: 0.6577 | K47: 1.3573 | L47: 559 | M47: 19 | N47: 822
A48: 2013 | B48: oro | C48: L3 | D48: semimanufactura | E48: 331490 | F48: LaminaciÃ³n secundaria de otros metales no ferro | G48: comp | H48: 10404.9 | I48: 2.0707 | J48: 1.3095 | K48: 1.2316 | L48: 200 | M48: 60 | N48: 822
A49: 2013 | B49: plata | C49: L1 | D49: extraccion | E49: 212222 | F49: MinerÃ­a de plata | G49: si | H49: 44680.4 | I49: 2.0579 | J49: 1.3014 | K49: 0.9118 | L49: 206 | M49: 578 | N49: 822
A50: 2013 | B50: plata | C50: L2 | D50: refinacion | E50: 331412 | F50: FundiciÃ³n y refinaciÃ³n de metales preciosos | G50: comp | H50: 143518.8 | I50: 1.0401 | J50: 0.6577 | K50: 1.3573 | L50: 559 | M50: 19 | N50: 822
A51: 2013 | B51: plata | C51: L3 | D51: semimanufactura | E51: 331490 | F51: LaminaciÃ³n secundaria de otros metales no ferro | G51: comp | H51: 10404.9 | I51: 2.0707 | J51: 1.3095 | K51: 1.2316 | L51: 200 | M51: 60 | N51: 822
A52: 2013 | B52: plomo-zinc | C52: L1 | D52: extraccion | E52: 212232 | F52: MinerÃ­a de plomo y zinc | G52: si | H52: 20045.8 | I52: 1.1314 | J52: 0.7154 | K52: 0.8935 | L52: 479 | M52: 623 | N52: 822
A53: 2013 | B53: plomo-zinc | C53: L2 | D53: refinacion | E53: 331419 | F53: FundiciÃ³n y refinaciÃ³n de otros metales no fer | G53: comp | H53: 11583.1 | I53: 1.0521 | J53: 0.6653 | K53: 1.13 | L53: 538 | M53: 148 | N53: 822
A54: 2013 | B54: plomo-zinc | C54: L3 | D54: semimanufactura | E54: 331490 | F54: LaminaciÃ³n secundaria de otros metales no ferro | G54: comp | H54: 10404.9 | I54: 2.0707 | J54: 1.3095 | K54: 1.2316 | L54: 200 | M54: 60 | N54: 822
A55: 2013 | B55: silice | C55: L1 | D55: extraccion | E55: 212324 | F55: MinerÃ­a de sÃ­lice | G55: si | H55: 4898.3 | I55: 2.8412 | J55: 1.7967 | K55: 0.9106 | L55: 31 | M55: 581 | N55: 822
A56: 2013 | B56: silice | C56: L2 | D56: refinacion | E56: 325180 | F56: FabricaciÃ³n de otros productos quÃ­micos bÃ¡sic | G56: no | H56: 29781.2 | I56: 2.1251 | J56: 1.3438 | K56: 0.9934 | L56: 174 | M56: 398 | N56: 822
A57: 2013 | B57: silice | C57: L3 | D57: semimanufactura | E57: 327211 | F57: FabricaciÃ³n de vidrio | G57: no | H57: 23027.1 | I57: 1.947 | J57: 1.2312 | K57: 0.9702 | L57: 261 | M57: 449 | N57: 822
... A59: 2018 | B59: barita | C59: L2 | D59: refinacion | E59: 325180 | F59: FabricaciÃ³n de otros productos quÃ­micos bÃ¡sic | G59: no | H59: 67911 | I59: 2.3289 | J59: 1.4404 | K59: 1.0444 | L59: 132 | M59: 280 | N59: 834
A60: 2018 | B60: barita | C60: L3 | D60: semimanufactura | F60: (sin clase separable) | G60: - | N60: 834
A61: 2018 | B61: cobre | C61: L1 | D61: extraccion | E61: 212231 | F61: MinerÃ­a de cobre | G61: si | H61: 92893 | I61: 2.1683 | J61: 1.3411 | K61: 0.9397 | L61: 185 | M61: 516 | N61: 834
A62: 2018 | B62: cobre | C62: L2 | D62: refinacion | E62: 331411 | F62: FundiciÃ³n y refinaciÃ³n de cobre | G62: si | H62: 80889.3 | I62: 2.2155 | J62: 1.3702 | K62: 1.2742 | L62: 170 | M62: 37 | N62: 834
A63: 2018 | B63: cobre | C63: L3 | D63: semimanufactura | E63: 331420 | F63: LaminaciÃ³n secundaria de cobre | G63: si | H63: 35975.3 | I63: 1.542 | J63: 0.9537 | K63: 1.0035 | L63: 375 | M63: 368 | N63: 834
A64: 2018 | B64: fluorita | C64: L1 | D64: extraccion | E64: 212395 | F64: MinerÃ­a de fluorita | G64: si | H64: 5861.8 | I64: 2.1194 | J64: 1.3109 | K64: 0.9729 | L64: 200 | M64: 433 | N64: 834
A65: 2018 | B65: fluorita | C65: L2 | D65: refinacion | E65: 325180 | F65: FabricaciÃ³n de otros productos quÃ­micos bÃ¡sic | G65: no | H65: 67911 | I65: 2.3289 | J65: 1.4404 | K65: 1.0444 | L65: 132 | M65: 280 | N65: 834
A66: 2018 | B66: fluorita | C66: L3 | D66: semimanufactura | E66: 325211 | F66: FabricaciÃ³n de resinas sintÃ©ticas | G66: no | H66: 120223.1 | I66: 2.1105 | J66: 1.3053 | K66: 1.0489 | L66: 204 | M66: 267 | N66: 834
A67: 2018 | B67: grafito | C67: L1 | D67: extraccion | E67: 212396 | F67: MinerÃ­a de grafito | G67: si | H67: 719.8 | I67: 2.7625 | J67: 1.7085 | K67: 0.8727 | L67: 43 | M67: 683 | N67: 834
A68: 2018 | B68: grafito | C68: L2 | D68: refinacion | E68: 325180 | F68: FabricaciÃ³n de otros productos quÃ­micos bÃ¡sic | G68: no | H68: 67911 | I68: 2.3289 | J68: 1.4404 | K68: 1.0444 | L68: 132 | M68: 280 | N68: 834
A69: 2018 | B69: grafito | C69: L3 | D69: semimanufactura | E69: 327999 | F69: FabricaciÃ³n de otros productos a base de minera | G69: no | H69: 26305.9 | I69: 2.0021 | J69: 1.2383 | K69: 1.1595 | L69: 253 | M69: 114 | N69: 834
A70: 2018 | B70: manganeso | C70: L1 | D70: extraccion | E70: 212291 | F70: MinerÃ­a de manganeso | G70: si | H70: 635 | I70: 2.4909 | J70: 1.5406 | K70: 1.0543 | L70: 77 | M70: 256 | N70: 834
A71: 2018 | B71: manganeso | C71: L2 | D71: refinacion | E71: 331112 | F71: FabricaciÃ³n de desbastes primarios y ferroaleac | G71: comp | H71: 46575.4 | I71: 2.1604 | J71: 1.3362 | K71: 1.0275 | L71: 190 | M71: 316 | N71: 834
A72: 2018 | B72: manganeso | C72: L3 | D72: semimanufactura | F72: (sin clase separable) | G72: - | N72: 834
A73: 2018 | B73: oro | C73: L1 | D73: extraccion | E73: 212221 | F73: MinerÃ­a de oro | G73: si | H73: 69491.1 | I73: 1.9672 | J73: 1.2167 | K73: 1.0261 | L73: 271 | M73: 321 | N73: 834
A74: 2018 | B74: oro | C74: L2 | D74: refinacion | E74: 331412 | F74: FundiciÃ³n y refinaciÃ³n de metales preciosos | G74: comp | H74: 178982.4 | I74: 1.0012 | J74: 0.6192 | K74: 1.4174 | L74: 711 | M74: 6 | N74: 834
A75: 2018 | B75: oro | C75: L3 | D75: semimanufactura | E75: 331490 | F75: LaminaciÃ³n secundaria de otros metales no ferro | G75: comp | H75: 11397.4 | I75: 1.6431 | J75: 1.0162 | K75: 0.9894 | L75: 346 | M75: 397 | N75: 834
A76: 2018 | B76: plata | C76: L1 | D76: extraccion | E76: 212222 | F76: MinerÃ­a de plata | G76: si | H76: 49784.4 | I76: 1.8995 | J76: 1.1748 | K76: 0.9932 | L76: 288 | M76: 389 | N76: 834
A77: 2018 | B77: plata | C77: L2 | D77: refinacion | E77: 331412 | F77: FundiciÃ³n y refinaciÃ³n de metales preciosos | G77: comp | H77: 178982.4 | I77: 1.0012 | J77: 0.6192 | K77: 1.4174 | L77: 711 | M77: 6 | N77: 834
A78: 2018 | B78: plata | C78: L3 | D78: semimanufactura | E78: 331490 | F78: LaminaciÃ³n secundaria de otros metales no ferro | G78: comp | H78: 11397.4 | I78: 1.6431 | J78: 1.0162 | K78: 0.9894 | L78: 346 | M78: 397 | N78: 834
A79: 2018 | B79: plomo-zinc | C79: L1 | D79: extraccion | E79: 212232 | F79: MinerÃ­a de plomo y zinc | G79: si | H79: 34724.7 | I79: 1.1438 | J79: 0.7074 | K79: 0.9885 | L79: 527 | M79: 401 | N79: 834
A80: 2018 | B80: plomo-zinc | C80: L2 | D80: refinacion | E80: 331419 | F80: FundiciÃ³n y refinaciÃ³n de otros metales no fer | G80: comp | H80: 14421.6 | I80: 1.025 | J80: 0.634 | K80: 1.2493 | L80: 638 | M80: 51 | N80: 834
A81: 2018 | B81: plomo-zinc | C81: L3 | D81: semimanufactura | E81: 331490 | F81: LaminaciÃ³n secundaria de otros metales no ferro | G81: comp | H81: 11397.4 | I81: 1.6431 | J81: 1.0162 | K81: 0.9894 | L81: 346 | M81: 397 | N81: 834
A82: 2018 | B82: silice | C82: L1 | D82: extraccion | E82: 212324 | F82: MinerÃ­a de sÃ­lice | G82: si | H82: 6959.1 | I82: 3.0978 | J82: 1.9159 | K82: 0.9381 | L82: 18 | M82: 521 | N82: 834
A83: 2018 | B83: silice | C83: L2 | D83: refinacion | E83: 325180 | F83: FabricaciÃ³n de otros productos quÃ­micos bÃ¡sic | G83: no | H83: 67911 | I83: 2.3289 | J83: 1.4404 | K83: 1.0444 | L83: 132 | M83: 280 | N83: 834
A84: 2018 | B84: silice | C84: L3 | D84: semimanufactura | E84: 327211 | F84: FabricaciÃ³n de vidrio | G84: no | H84: 28332.7 | I84: 2.1674 | J84: 1.3405 | K84: 1.2169 | L84: 186 | M84: 69 | N84: 834

Sheet 16 Demanda interm
A1: MIP nacional - demanda intermedia domestica (sectores compradores)
A2: share_del_di = valor del comprador / DI_total del mineral (demanda intermedia total de ese mineral-anio, de la hoja 14). La columna 'DI_total_mineral' se trae como insumo; la verde recomputa share = valor / DI_total y su diferencia vs script (~0).
A3: anio | B3: mineral_codigo | C3: mineral | D3: comprador_codigo | E3: comprador | F3: valor_mmpesos | G3: share_del_di | H3: DI_total_mineral | I3: share_del_di (=formula) | J3: dif
A4: 2013 | B4: 212393 | C4: barita | D4: 336340 | E4: FabricaciÃ³n de partes de sistemas de frenos para vehÃ­culos automotri | F4: 64.719 | G4: 1 | H4: 64.719 | I4: =IF(H4=0,"",ROUND(F4/H4,4)) | J4: =IF(ISNUMBER(I4),ROUND(I4-G4,4),"")
A5: 2013 | B5: 212231 | C5: cobre | D5: 331411 | E5: FundiciÃ³n y refinaciÃ³n de cobre | F5: 9485.867 | G5: 0.519 | H5: 18276.824 | I5: =IF(H5=0,"",ROUND(F5/H5,4)) | J5: =IF(ISNUMBER(I5),ROUND(I5-G5,4),"")
A6: 2013 | B6: 212231 | C6: cobre | D6: 331420 | E6: LaminaciÃ³n secundaria de cobre | F6: 8288.794 | G6: 0.4535 | H6: 18276.824 | I6: =IF(H6=0,"",ROUND(F6/H6,4)) | J6: =IF(ISNUMBER(I6),ROUND(I6-G6,4),"")
A7: 2013 | B7: 212231 | C7: cobre | D7: 212231 | E7: MinerÃ­a de cobre | F7: 502.163 | G7: 0.0275 | H7: 18276.824 | I7: =IF(H7=0,"",ROUND(F7/H7,4)) | J7: =IF(ISNUMBER(I7),ROUND(I7-G7,4),"")
A8: 2013 | B8: 212395 | C8: fluorita | D8: 327310 | E8: FabricaciÃ³n de cemento y productos a base de cemento en plantas integ | F8: 194.483 | G8: 0.3973 | H8: 489.471 | I8: =IF(H8=0,"",ROUND(F8/H8,4)) | J8: =IF(ISNUMBER(I8),ROUND(I8-G8,4),"")
A9: 2013 | B9: 212395 | C9: fluorita | D9: 327112 | E9: FabricaciÃ³n de muebles de baÃ±o | F9: 191.133 | G9: 0.3905 | H9: 489.471 | I9: =IF(H9=0,"",ROUND(F9/H9,4)) | J9: =IF(ISNUMBER(I9),ROUND(I9-G9,4),"")
A10: 2013 | B10: 212395 | C10: fluorita | D10: 212395 | E10: MinerÃ­a de fluorita | F10: 40.993 | G10: 0.0837 | H10: 489.471 | I10: =IF(H10=0,"",ROUND(F10/H10,4)) | J10: =IF(ISNUMBER(I10),ROUND(I10-G10,4),"")
A11: 2013 | B11: 212395 | C11: fluorita | D11: 327123 | E11: FabricaciÃ³n de productos refractarios | F11: 39.808 | G11: 0.0813 | H11: 489.471 | I11: =IF(H11=0,"",ROUND(F11/H11,4)) | J11: =IF(ISNUMBER(I11),ROUND(I11-G11,4),"")
A12: 2013 | B12: 212395 | C12: fluorita | D12: 212325 | E12: MinerÃ­a de caolÃ­n | F12: 12.31 | G12: 0.0251 | H12: 489.471 | I12: =IF(H12=0,"",ROUND(F12/H12,4)) | J12: =IF(ISNUMBER(I12),ROUND(I12-G12,4),"")
A13: 2013 | B13: 212395 | C13: fluorita | D13: 327219 | E13: FabricaciÃ³n de otros productos de vidrio | F13: 6.462 | G13: 0.0132 | H13: 489.471 | I13: =IF(H13=0,"",ROUND(F13/H13,4)) | J13: =IF(ISNUMBER(I13),ROUND(I13-G13,4),"")
A14: 2013 | B14: 212395 | C14: fluorita | D14: 327215 | E14: FabricaciÃ³n de artÃ­culos de vidrio de uso domÃ©stico | F14: 3.87 | G14: 0.0079 | H14: 489.471 | I14: =IF(H14=0,"",ROUND(F14/H14,4)) | J14: =IF(ISNUMBER(I14),ROUND(I14-G14,4),"")
A15: 2013 | B15: 212395 | C15: fluorita | D15: 333991 | E15: FabricaciÃ³n de equipo para soldar y soldaduras | F15: 0.349 | G15: 0.0007 | H15: 489.471 | I15: =IF(H15=0,"",ROUND(F15/H15,4)) | J15: =IF(ISNUMBER(I15),ROUND(I15-G15,4),"")
... A105: 2018 | B105: 212324 | C105: silice | D105: 325180 | E105: FabricaciÃ³n de otros productos quÃ­micos bÃ¡sicos inorgÃ¡nicos | F105: 43.089 | G105: 0.0062 | H105: 6895.377 | I105: =IF(H105=0,"",ROUND(F105/H105,4)) | J105: =IF(ISNUMBER(I105),ROUND(I105-G105,4),"")

Sheet 17 Georref extraccion
A1: Georreferenciacion cuantitativa de la extraccion (share estatal 2024, SGM)
A2: share_2024 = produccion_estado / (suma nacional del mineral) x 100. Columna verde recomputa con SUMIFS. Esta hoja alimenta el HHI geografico de la hoja '17b'.
A3: mineral | B3: estado | C3: produccion_2024 | D3: unidad | E3: share_2024_pct | F3: fuente | G3: share (=formula) % | H3: dif
A4: cobre | B4: Sonora | C4: 544345.8 | D4: toneladas | E4: 70.05 | F4: SGM Anuario 2025 p.100 | G4: =ROUND(C4/SUMIFS($C$4:$C$96,$A$4:$A$96,A4)*100,2) | H4: =ROUND(G4-E4,2)
A5: cobre | B5: Zacatecas | C5: 121335.8 | D5: toneladas | E5: 15.61 | F5: SGM Anuario 2025 p.100 | G5: =ROUND(C5/SUMIFS($C$4:$C$96,$A$4:$A$96,A5)*100,2) | H5: =ROUND(G5-E5,2)
A6: cobre | B6: San Luis Potosi | C6: 33479.99 | D6: toneladas | E6: 4.31 | F6: SGM Anuario 2025 p.100 | G6: =ROUND(C6/SUMIFS($C$4:$C$96,$A$4:$A$96,A6)*100,2) | H6: =ROUND(G6-E6,2)
A7: cobre | B7: Chihuahua | C7: 19844.46 | D7: toneladas | E7: 2.55 | F7: SGM Anuario 2025 p.100 | G7: =ROUND(C7/SUMIFS($C$4:$C$96,$A$4:$A$96,A7)*100,2) | H7: =ROUND(G7-E7,2)
A8: cobre | B8: Coahuila | C8: 15000 | D8: toneladas | E8: 1.93 | F8: SGM Anuario 2025 p.100 | G8: =ROUND(C8/SUMIFS($C$4:$C$96,$A$4:$A$96,A8)*100,2) | H8: =ROUND(G8-E8,2)
A9: cobre | B9: Baja California Sur | C9: 13978 | D9: toneladas | E9: 1.8 | F9: SGM Anuario 2025 p.100 | G9: =ROUND(C9/SUMIFS($C$4:$C$96,$A$4:$A$96,A9)*100,2) | H9: =ROUND(G9-E9,2)
A10: cobre | B10: Guerrero | C10: 10881.03 | D10: toneladas | E10: 1.4 | F10: SGM Anuario 2025 p.100 | G10: =ROUND(C10/SUMIFS($C$4:$C$96,$A$4:$A$96,A10)*100,2) | H10: =ROUND(G10-E10,2)
A11: cobre | B11: Durango | C11: 6934.01 | D11: toneladas | E11: 0.89 | F11: SGM Anuario 2025 p.100 | G11: =ROUND(C11/SUMIFS($C$4:$C$96,$A$4:$A$96,A11)*100,2) | H11: =ROUND(G11-E11,2)
A12: cobre | B12: Hidalgo | C12: 3245.92 | D12: toneladas | E12: 0.42 | F12: SGM Anuario 2025 p.100 | G12: =ROUND(C12/SUMIFS($C$4:$C$96,$A$4:$A$96,A12)*100,2) | H12: =ROUND(G12-E12,2)
A13: cobre | B13: Michoacan | C13: 2081.43 | D13: toneladas | E13: 0.27 | F13: SGM Anuario 2025 p.100 | G13: =ROUND(C13/SUMIFS($C$4:$C$96,$A$4:$A$96,A13)*100,2) | H13: =ROUND(G13-E13,2)
A14: cobre | B14: Jalisco | C14: 1578.62 | D14: toneladas | E14: 0.2 | F14: SGM Anuario 2025 p.100 | G14: =ROUND(C14/SUMIFS($C$4:$C$96,$A$4:$A$96,A14)*100,2) | H14: =ROUND(G14-E14,2)
A15: cobre | B15: Queretaro | C15: 1544 | D15: toneladas | E15: 0.2 | F15: SGM Anuario 2025 p.100 | G15: =ROUND(C15/SUMIFS($C$4:$C$96,$A$4:$A$96,A15)*100,2) | H15: =ROUND(G15-E15,2)
... A96: silice | B96: Chihuahua | C96: 80.82 | D96: toneladas | E96: 0 | F96: SGM Anuario 2025 p.162 | G96: =ROUND(C96/SUMIFS($C$4:$C$96,$A$4:$A$96,A96)*100,2) | H96: =ROUND(G96-E96,2)

Sheet 17b HHI geografico
A1: HHI geografico de la extraccion + co-localizacion con transformacion
A2: hhi_geografico = suma_estado (share_estado)^2. Columna verde lo recomputa con SUMPRODUCT sobre los shares de la hoja '17 Georref extraccion' y lo compara con el valor del script. tiene_eslabon_E2 / colocalizado = mapa cualitativo.
A3: mineral | B3: hhi_geografico | C3: n_estados | D3: estado_extraccion_lider | E3: share_lider_pct | F3: estados_transformacion | G3: tiene_eslabon_E2 | H3: colocalizado_extraccion_E2 | I3: HHI_geo (=formula) | J3: dif
A4: cobre | B4: 5186 | C4: 16 | D4: Sonora | E4: 70 | F4: Ciudad de México; Sonora | G4: si | H4: si | I4: =ROUND(SUMPRODUCT(('17 Georref extraccion'!$A$4:$A$96=A4)*('17 Georref extraccion'!$E$4:$E$96)^2),0) | J4: =ROUND(I4-B4,0)
A5: plomo | B5: 5318 | C5: 12 | D5: Zacatecas | E5: 71 | F5: Coahuila; San Luis Potosí | G5: si | H5: no | I5: =ROUND(SUMPRODUCT(('17 Georref extraccion'!$A$4:$A$96=A5)*('17 Georref extraccion'!$E$4:$E$96)^2),0) | J5: =ROUND(I5-B5,0)
A6: zinc | B6: 3436 | C6: 13 | D6: Zacatecas | E6: 56 | F6: Coahuila; San Luis Potosí | G6: si | H6: no | I6: =ROUND(SUMPRODUCT(('17 Georref extraccion'!$A$4:$A$96=A6)*('17 Georref extraccion'!$E$4:$E$96)^2),0) | J6: =ROUND(I6-B6,0)
A7: manganeso | B7: 10000 | C7: 1 | D7: Hidalgo | E7: 100 | F7: Durango; Puebla; Veracruz | G7: si | H7: no | I7: =ROUND(SUMPRODUCT(('17 Georref extraccion'!$A$4:$A$96=A7)*('17 Georref extraccion'!$E$4:$E$96)^2),0) | J7: =ROUND(I7-B7,0)
A8: oro | B8: 2476 | C8: 16 | D8: Sonora | E8: 32 | F8: Coahuila | G8: si | H8: no | I8: =ROUND(SUMPRODUCT(('17 Georref extraccion'!$A$4:$A$96=A8)*('17 Georref extraccion'!$E$4:$E$96)^2),0) | J8: =ROUND(I8-B8,0)
A9: plata | B9: 3022 | C9: 16 | D9: Zacatecas | E9: 50 | F9: Coahuila | G9: si | H9: no | I9: =ROUND(SUMPRODUCT(('17 Georref extraccion'!$A$4:$A$96=A9)*('17 Georref extraccion'!$E$4:$E$96)^2),0) | J9: =ROUND(I9-B9,0)
A10: fluorita | B10: 9158 | C10: 3 | D10: San Luis Potosi | E10: 96 | F10: Tamaulipas | G10: si | H10: no | I10: =ROUND(SUMPRODUCT(('17 Georref extraccion'!$A$4:$A$96=A10)*('17 Georref extraccion'!$E$4:$E$96)^2),0) | J10: =ROUND(I10-B10,0)
A11: grafito | B11: 10000 | C11: 1 | D11: Sonora | E11: 100 | F11: Michoacán | G11: no | H11: no | I11: =ROUND(SUMPRODUCT(('17 Georref extraccion'!$A$4:$A$96=A11)*('17 Georref extraccion'!$E$4:$E$96)^2),0) | J11: =ROUND(I11-B11,0)
A12: barita | B12: 4907 | C12: 9 | D12: Nuevo Leon | E12: 59 | F12: Campeche | G12: no | H12: no | I12: =ROUND(SUMPRODUCT(('17 Georref extraccion'!$A$4:$A$96=A12)*('17 Georref extraccion'!$E$4:$E$96)^2),0) | J12: =ROUND(I12-B12,0)
A13: silice | B13: 4258 | C13: 6 | D13: Coahuila | E13: 52 | F13: Nuevo León | G13: si | H13: no | I13: =ROUND(SUMPRODUCT(('17 Georref extraccion'!$A$4:$A$96=A13)*('17 Georref extraccion'!$E$4:$E$96)^2),0) | J13: =ROUND(I13-B13,0)

Sheet 17c Ghosh estatal
A1: Ghosh estatal de la mineria (MIP Estatal INEGI 2018, intra-estatal)
A2: Ghosh-Rasmussen intra-estatal por entidad (metodo identico al nacional, inversa de Ghosh sobre la MIP estatal; media estado=1). fuga_export_share = fraccion del arrastre del producto minero que sale del estado (de la descomposicion Ghosh, no un cociente simple). share_vbp_estatal_pct = peso de la mineria en la economia de CADA estado (no cuota del total nacional). Resultado del script; validado como el nacional.
A3: estado | B3: abrev | C3: vbp_mineria_mdp | D3: share_vbp_estatal_pct | E3: forward_rowsum | F3: forward_rasmussen | G3: rank_forward_de_35 | H3: backward_rasmussen | I3: fuga_export_share | J3: usa_intra_interm_mdp | K3: exporta_mdp
A4: Sonora | B4: son | C4: 140608.2 | D4: 9.556 | E4: 1.7627 | F4: 1.4051 | G4: 2 | H4: 0.812 | I4: 0.3863 | J4: 78693.8 | K4: 54312.9
A5: Coahuila | B5: coah | C5: 42338.9 | D5: 1.973 | E5: 1.9454 | F5: 1.6145 | G5: 1 | H5: 0.868 | I5: 0.3166 | J5: 28625.3 | K5: 13402.9
A6: Durango | B6: dgo | C6: 36058.7 | D6: 7.017 | E6: 1.2177 | F6: 1.0292 | G6: 9 | H6: 0.9867 | I6: 0.7697 | J6: 7148.7 | K6: 27754.9
A7: Zacatecas | B7: zac | C7: 34470.9 | D7: 10.215 | E7: 1.1265 | F7: 1.0446 | G7: 9 | H7: 0.8923 | I7: 0.8442 | J7: 4000.4 | K7: 29101.9
A8: Chihuahua | B8: chih | C8: 23906.3 | D8: 1.334 | E8: 1.126 | F8: 0.9647 | G8: 13 | H8: 0.9996 | I8: 0.8932 | J8: 2422.6 | K8: 21353.7
A9: San Luis Potosi | B9: slp | C9: 19628.6 | D9: 1.779 | E9: 1.6528 | F9: 1.3956 | G9: 1 | H9: 0.8783 | I9: 0.526 | J9: 9151.8 | K9: 10324.8
A10: Jalisco | B10: jal | C10: 12982.8 | D10: 0.422 | E10: 1.2432 | F10: 1.0282 | G10: 13 | H10: 1.0094 | I10: 0.8043 | J10: 2512.5 | K10: 10442
A11: Nuevo Leon | B11: nl | C11: 11947.1 | D11: 0.328 | E11: 1.0725 | F11: 0.8828 | G11: 28 | H11: 1.0486 | I11: 0.9458 | J11: 635 | K11: 11299.2
A12: Guerrero | B12: gro | C12: 11208.4 | D12: 2.508 | E12: 1.1465 | F12: 1.0506 | G12: 9 | H12: 0.9135 | I12: 0.8658 | J12: 1432.6 | K12: 9704.7
A13: Aguascalientes | B13: ags | C13: 9530.5 | D13: 1.486 | E13: 1.388 | F13: 1.2137 | G13: 3 | H13: 0.9116 | I13: 0.6966 | J13: 2807 | K13: 6639.1
A14: Baja California Sur | B14: bcs | C14: 8986.8 | D14: 3.381 | E14: 1.2446 | F14: 1.1271 | G14: 6 | H14: 0.8914 | I14: 0.7696 | J14: 1944.7 | K14: 6916.2
A15: Michoacan | B15: mich | C15: 8896.6 | D15: 0.967 | E15: 1.2382 | F15: 1.1046 | G15: 5 | H15: 0.9799 | I15: 0.7839 | J15: 1893.8 | K15: 6974.2
... A35: Ciudad de Mexico | B35: cdmx | C35: 429.5 | D35: 0.008 | E35: 1.0004 | F35: 0.8863 | G35: 32 | H35: 1.2263 | I35: 0.9952 | J35: 0.2 | K35: 427.5
A38: Ghosh INTER-ESTATAL (MIP birregional 2018): descompone en intra / inter-estatal / final / export_abroad
A39: estado | B39: abrev | C39: vbp_mineria_mdp | D39: intra_share | E39: inter_estatal_share | F39: final_nacional_share | G39: export_abroad_share | H39: encad_nacional_share | I39: forward_rasmussen_br | J39: suma shares (=1?)
A40: Sonora | B40: son | C40: 140608.2 | D40: 0.5597 | E40: 0.1401 | F40: 0.0603 | G40: 0.2399 | H40: 0.6998 | I40: 1.3888 | J40: =ROUND(D40+E40+F40+G40,4)
A41: Coahuila | B41: coah | C41: 42338.9 | D41: 0.6761 | E41: 0.2498 | F41: 0.0323 | G41: 0.0418 | H41: 0.9259 | I41: 1.5885 | J41: =ROUND(D41+E41+F41+G41,4)
A42: Durango | B42: dgo | C42: 36058.7 | D42: 0.1983 | E42: 0.4587 | F42: 0.0547 | G42: 0.2884 | H42: 0.6569 | I42: 1.3046 | J42: =ROUND(D42+E42+F42+G42,4)
A43: Zacatecas | B43: zac | C43: 34470.9 | D43: 0.1161 | E43: 0.2975 | F43: 0.0564 | G43: 0.5301 | H43: 0.4135 | I43: 1.074 | J43: =ROUND(D43+E43+F43+G43,4)
A44: Chihuahua | B44: chih | C44: 23906.3 | D44: 0.1013 | E44: 0.1169 | F44: 0.0244 | G44: 0.7574 | H44: 0.2182 | I44: 0.9202 | J44: =ROUND(D44+E44+F44+G44,4)
A45: San Luis Potosi | B45: slp | C45: 19628.6 | D45: 0.4662 | E45: 0.4774 | F45: 0.0433 | G45: 0.013 | H45: 0.9437 | I45: 1.6501 | J45: =ROUND(D45+E45+F45+G45,4)
A46: Jalisco | B46: jal | C46: 12982.8 | D46: 0.1935 | E46: 0.7512 | F46: 0.0504 | G46: 0.0048 | H46: 0.9447 | I46: 1.6597 | J46: =ROUND(D46+E46+F46+G46,4)
A47: Nuevo Leon | B47: nl | C47: 11947.1 | D47: 0.0531 | E47: 0.9137 | F47: 0.0291 | G47: 0.0041 | H47: 0.9668 | I47: 1.6245 | J47: =ROUND(D47+E47+F47+G47,4)
A48: Guerrero | B48: gro | C48: 11208.4 | D48: 0.1278 | E48: 0.257 | F48: 0.027 | G48: 0.5881 | H48: 0.3848 | I48: 1.0758 | J48: =ROUND(D48+E48+F48+G48,4)
A49: Aguascalientes | B49: ags | C49: 9530.5 | D49: 0.2945 | E49: 0.6323 | F49: 0.0616 | G49: 0.0116 | H49: 0.9268 | I49: 1.6675 | J49: =ROUND(D49+E49+F49+G49,4)
A50: Baja California Sur | B50: bcs | C50: 8986.8 | D50: 0.2164 | E50: 0.4414 | F50: 0.0471 | G50: 0.2951 | H50: 0.6578 | I50: 1.3218 | J50: =ROUND(D50+E50+F50+G50,4)
A51: Michoacan | B51: mich | C51: 8896.6 | D51: 0.2129 | E51: 0.6408 | F51: 0.0407 | G51: 0.1056 | H51: 0.8537 | I51: 1.6094 | J51: =ROUND(D51+E51+F51+G51,4)
... A71: Ciudad de Mexico | B71: cdmx | C71: 429.5 | D71: 0.0004 | E71: 0.4019 | F71: 0.5977 | G71: 0 | H71: 0.4023 | I71: 1.077 | J71: =ROUND(D71+E71+F71+G71,4)

Sheet 18 Comercio posicion
A1: Comercio - posicion por etapa (X_share_crudo, 1992-2024)
A2: X_share_crudo = X_crudo (E1) / X_total. Columna verde recomputa con formula y su diferencia. Evidencia del truncamiento: se exporta E1 y se importa E3-E4. La serie larga por etapa/flujo esta en la hoja '18b'.
A3: anio | B3: mineral | C3: X_total_usd | D3: X_crudo_usd | E3: X_share_crudo | F3: X_share_crudo (=formula) | G3: dif
A4: 1992 | B4: barita | C4: 2815000 | D4: 1244000 | E4: 0.4419 | F4: =IF(C4=0,"",ROUND(D4/C4,4)) | G4: =IF(ISNUMBER(F4),ROUND(F4-E4,4),"")
A5: 1992 | B5: cobre | C5: 470519992 | D5: 31605000 | E5: 0.0672 | F5: =IF(C5=0,"",ROUND(D5/C5,4)) | G5: =IF(ISNUMBER(F5),ROUND(F5-E5,4),"")
A6: 1992 | B6: fluorita | C6: 100001000 | D6: 13929000 | E6: 0.1393 | F6: =IF(C6=0,"",ROUND(D6/C6,4)) | G6: =IF(ISNUMBER(F6),ROUND(F6-E6,4),"")
A7: 1992 | B7: grafito | C7: 30805000 | D7: 3073000 | E7: 0.0998 | F7: =IF(C7=0,"",ROUND(D7/C7,4)) | G7: =IF(ISNUMBER(F7),ROUND(F7-E7,4),"")
A8: 1992 | B8: manganeso | C8: 43053000 | D8: 6044000 | E8: 0.1404 | F8: =IF(C8=0,"",ROUND(D8/C8,4)) | G8: =IF(ISNUMBER(F8),ROUND(F8-E8,4),"")
A9: 1992 | B9: oro | C9: 41524000 | D9: 71000 | E9: 0.0017 | F9: =IF(C9=0,"",ROUND(D9/C9,4)) | G9: =IF(ISNUMBER(F9),ROUND(F9-E9,4),"")
A10: 1992 | B10: oro-plata (manufacturas) | C10: 43815000 | D10: 0 | E10: 0 | F10: =IF(C10=0,"",ROUND(D10/C10,4)) | G10: =IF(ISNUMBER(F10),ROUND(F10-E10,4),"")
A11: 1992 | B11: plata | C11: 206850992 | D11: 102000 | E11: 0.0005 | F11: =IF(C11=0,"",ROUND(D11/C11,4)) | G11: =IF(ISNUMBER(F11),ROUND(F11-E11,4),"")
A12: 1992 | B12: plomo | C12: 57849000 | D12: 1580000 | E12: 0.0273 | F12: =IF(C12=0,"",ROUND(D12/C12,4)) | G12: =IF(ISNUMBER(F12),ROUND(F12-E12,4),"")
A13: 1992 | B13: silice | C13: 870000 | D13: 624000 | E13: 0.7172 | F13: =IF(C13=0,"",ROUND(D13/C13,4)) | G13: =IF(ISNUMBER(F13),ROUND(F13-E13,4),"")
A14: 1992 | B14: zinc | C14: 141571000 | D14: 81135000 | E14: 0.5731 | F14: =IF(C14=0,"",ROUND(D14/C14,4)) | G14: =IF(ISNUMBER(F14),ROUND(F14-E14,4),"")
A15: 1993 | B15: barita | C15: 5909000 | D15: 4213000 | E15: 0.713 | F15: =IF(C15=0,"",ROUND(D15/C15,4)) | G15: =IF(ISNUMBER(F15),ROUND(F15-E15,4),"")
... A266: 2015 | B266: zinc | C266: 646857950 | D266: 365685096 | E266: 0.5653 | F266: =IF(C266=0,"",ROUND(D266/C266,4)) | G266: =IF(ISNUMBER(F266),ROUND(F266-E266,4),"")
A267: 2016 | B267: barita | C267: 0 | D267: 0 | F267: =IF(C267=0,"",ROUND(D267/C267,4)) | G267: =IF(ISNUMBER(F267),ROUND(F267-E267,4),"")
A268: 2016 | B268: cobre | C268: 2670487835 | D268: 1323559500 | E268: 0.4956 | F268: =IF(C268=0,"",ROUND(D268/C268,4)) | G268: =IF(ISNUMBER(F268),ROUND(F268-E268,4),"")
A269: 2016 | B269: fluorita | C269: 233300042 | D269: 62572145 | E269: 0.2682 | F269: =IF(C269=0,"",ROUND(D269/C269,4)) | G269: =IF(ISNUMBER(F269),ROUND(F269-E269,4),"")
A270: 2016 | B270: grafito | C270: 94732986 | D270: 3889142 | E270: 0.0411 | F270: =IF(C270=0,"",ROUND(D270/C270,4)) | G270: =IF(ISNUMBER(F270),ROUND(F270-E270,4),"")
A271: 2016 | B271: manganeso | C271: 34454134 | D271: 0 | E271: 0 | F271: =IF(C271=0,"",ROUND(D271/C271,4)) | G271: =IF(ISNUMBER(F271),ROUND(F271-E271,4),"")
A272: 2016 | B272: oro | C272: 3487693143 | D272: 248450033 | E272: 0.0712 | F272: =IF(C272=0,"",ROUND(D272/C272,4)) | G272: =IF(ISNUMBER(F272),ROUND(F272-E272,4),"")
A273: 2016 | B273: oro-plata (manufacturas) | C273: 431545958 | D273: 0 | E273: 0 | F273: =IF(C273=0,"",ROUND(D273/C273,4)) | G273: =IF(ISNUMBER(F273),ROUND(F273-E273,4),"")
A274: 2016 | B274: plata | C274: 1906842918 | D274: 25474960 | E274: 0.0134 | F274: =IF(C274=0,"",ROUND(D274/C274,4)) | G274: =IF(ISNUMBER(F274),ROUND(F274-E274,4),"")
A275: 2016 | B275: plomo | C275: 904677379 | D275: 780501188 | E275: 0.8627 | F275: =IF(C275=0,"",ROUND(D275/C275,4)) | G275: =IF(ISNUMBER(F275),ROUND(F275-E275,4),"")
A276: 2016 | B276: silice | C276: 7030524 | D276: 1864350 | E276: 0.2652 | F276: =IF(C276=0,"",ROUND(D276/C276,4)) | G276: =IF(ISNUMBER(F276),ROUND(F276-E276,4),"")
A277: 2016 | B277: zinc | C277: 780170054 | D277: 564250705 | E277: 0.7232 | F277: =IF(C277=0,"",ROUND(D277/C277,4)) | G277: =IF(ISNUMBER(F277),ROUND(F277-E277,4),"")
A278: 2017 | B278: barita | C278: 27260 | D278: 0 | E278: 0 | F278: =IF(C278=0,"",ROUND(D278/C278,4)) | G278: =IF(ISNUMBER(F278),ROUND(F278-E278,4),"")
A279: 2017 | B279: cobre | C279: 2978452379 | D279: 1568943333 | E279: 0.5268 | F279: =IF(C279=0,"",ROUND(D279/C279,4)) | G279: =IF(ISNUMBER(F279),ROUND(F279-E279,4),"")
... A288: 2017 | B288: zinc | C288: 948934970 | D288: 640110077 | E288: 0.6746 | F288: =IF(C288=0,"",ROUND(D288/C288,4)) | G288: =IF(ISNUMBER(F288),ROUND(F288-E288,4),"")
A289: 2018 | B289: barita | C289: 0 | D289: 0 | F289: =IF(C289=0,"",ROUND(D289/C289,4)) | G289: =IF(ISNUMBER(F289),ROUND(F289-E289,4),"")
A290: 2018 | B290: cobre | C290: 3793769125 | D290: 2318095785 | E290: 0.611 | F290: =IF(C290=0,"",ROUND(D290/C290,4)) | G290: =IF(ISNUMBER(F290),ROUND(F290-E290,4),"")
A291: 2018 | B291: fluorita | C291: 235504574 | D291: 73420659 | E291: 0.3118 | F291: =IF(C291=0,"",ROUND(D291/C291,4)) | G291: =IF(ISNUMBER(F291),ROUND(F291-E291,4),"")
A292: 2018 | B292: grafito | C292: 193908081 | D292: 5558473 | E292: 0.0287 | F292: =IF(C292=0,"",ROUND(D292/C292,4)) | G292: =IF(ISNUMBER(F292),ROUND(F292-E292,4),"")
A293: 2018 | B293: manganeso | C293: 42123346 | D293: 0 | E293: 0 | F293: =IF(C293=0,"",ROUND(D293/C293,4)) | G293: =IF(ISNUMBER(F293),ROUND(F293-E293,4),"")
A294: 2018 | B294: oro | C294: 3382362728 | D294: 181351369 | E294: 0.0536 | F294: =IF(C294=0,"",ROUND(D294/C294,4)) | G294: =IF(ISNUMBER(F294),ROUND(F294-E294,4),"")
A295: 2018 | B295: oro-plata (manufacturas) | C295: 353650296 | D295: 0 | E295: 0 | F295: =IF(C295=0,"",ROUND(D295/C295,4)) | G295: =IF(ISNUMBER(F295),ROUND(F295-E295,4),"")
A296: 2018 | B296: plata | C296: 1708727482 | D296: 36656445 | E296: 0.0215 | F296: =IF(C296=0,"",ROUND(D296/C296,4)) | G296: =IF(ISNUMBER(F296),ROUND(F296-E296,4),"")
A297: 2018 | B297: plomo | C297: 984746524 | D297: 770645599 | E297: 0.7826 | F297: =IF(C297=0,"",ROUND(D297/C297,4)) | G297: =IF(ISNUMBER(F297),ROUND(F297-E297,4),"")
A298: 2018 | B298: silice | C298: 8701400 | D298: 1977646 | E298: 0.2273 | F298: =IF(C298=0,"",ROUND(D298/C298,4)) | G298: =IF(ISNUMBER(F298),ROUND(F298-E298,4),"")
A299: 2018 | B299: zinc | C299: 1235254525 | D299: 795496776 | E299: 0.644 | F299: =IF(C299=0,"",ROUND(D299/C299,4)) | G299: =IF(ISNUMBER(F299),ROUND(F299-E299,4),"")
A300: 2019 | B300: barita | C300: 0 | D300: 0 | F300: =IF(C300=0,"",ROUND(D300/C300,4)) | G300: =IF(ISNUMBER(F300),ROUND(F300-E300,4),"")
A301: 2019 | B301: cobre | C301: 3686036107 | D301: 2339268612 | E301: 0.6346 | F301: =IF(C301=0,"",ROUND(D301/C301,4)) | G301: =IF(ISNUMBER(F301),ROUND(F301-E301,4),"")
A302: 2019 | B302: fluorita | C302: 287110902 | D302: 107197953 | E302: 0.3734 | F302: =IF(C302=0,"",ROUND(D302/C302,4)) | G302: =IF(ISNUMBER(F302),ROUND(F302-E302,4),"")
A303: 2019 | B303: grafito | C303: 223269302 | D303: 0 | E303: 0 | F303: =IF(C303=0,"",ROUND(D303/C303,4)) | G303: =IF(ISNUMBER(F303),ROUND(F303-E303,4),"")
A304: 2019 | B304: manganeso | C304: 45973453 | D304: 0 | E304: 0 | F304: =IF(C304=0,"",ROUND(D304/C304,4)) | G304: =IF(ISNUMBER(F304),ROUND(F304-E304,4),"")
A305: 2019 | B305: oro | C305: 3485870435 | D305: 217719396 | E305: 0.0625 | F305: =IF(C305=0,"",ROUND(D305/C305,4)) | G305: =IF(ISNUMBER(F305),ROUND(F305-E305,4),"")
A306: 2019 | B306: oro-plata (manufacturas) | C306: 311536967 | D306: 0 | E306: 0 | F306: =IF(C306=0,"",ROUND(D306/C306,4)) | G306: =IF(ISNUMBER(F306),ROUND(F306-E306,4),"")
A307: 2019 | B307: plata | C307: 1913567877 | D307: 31927356 | E307: 0.0167 | F307: =IF(C307=0,"",ROUND(D307/C307,4)) | G307: =IF(ISNUMBER(F307),ROUND(F307-E307,4),"")
A308: 2019 | B308: plomo | C308: 931389128 | D308: 739121732 | E308: 0.7936 | F308: =IF(C308=0,"",ROUND(D308/C308,4)) | G308: =IF(ISNUMBER(F308),ROUND(F308-E308,4),"")
A309: 2019 | B309: silice | C309: 9380304 | D309: 1588593 | E309: 0.1694 | F309: =IF(C309=0,"",ROUND(D309/C309,4)) | G309: =IF(ISNUMBER(F309),ROUND(F309-E309,4),"")
A310: 2019 | B310: zinc | C310: 1045767424 | D310: 655723459 | E310: 0.627 | F310: =IF(C310=0,"",ROUND(D310/C310,4)) | G310: =IF(ISNUMBER(F310),ROUND(F310-E310,4),"")
A311: 2020 | B311: barita | C311: 0 | D311: 0 | F311: =IF(C311=0,"",ROUND(D311/C311,4)) | G311: =IF(ISNUMBER(F311),ROUND(F311-E311,4),"")
A312: 2020 | B312: cobre | C312: 4207498332 | D312: 2878626776 | E312: 0.6842 | F312: =IF(C312=0,"",ROUND(D312/C312,4)) | G312: =IF(ISNUMBER(F312),ROUND(F312-E312,4),"")
A313: 2020 | B313: fluorita | C313: 221874264 | D313: 77026577 | E313: 0.3472 | F313: =IF(C313=0,"",ROUND(D313/C313,4)) | G313: =IF(ISNUMBER(F313),ROUND(F313-E313,4),"")
A314: 2020 | B314: grafito | C314: 153575037 | D314: 0 | E314: 0 | F314: =IF(C314=0,"",ROUND(D314/C314,4)) | G314: =IF(ISNUMBER(F314),ROUND(F314-E314,4),"")
A315: 2020 | B315: manganeso | C315: 20023807 | D315: 0 | E315: 0 | F315: =IF(C315=0,"",ROUND(D315/C315,4)) | G315: =IF(ISNUMBER(F315),ROUND(F315-E315,4),"")
A316: 2020 | B316: oro | C316: 3810267884 | D316: 321417297 | E316: 0.0844 | F316: =IF(C316=0,"",ROUND(D316/C316,4)) | G316: =IF(ISNUMBER(F316),ROUND(F316-E316,4),"")
A317: 2020 | B317: oro-plata (manufacturas) | C317: 262580578 | D317: 0 | E317: 0 | F317: =IF(C317=0,"",ROUND(D317/C317,4)) | G317: =IF(ISNUMBER(F317),ROUND(F317-E317,4),"")
A318: 2020 | B318: plata | C318: 2302879794 | D318: 146951579 | E318: 0.0638 | F318: =IF(C318=0,"",ROUND(D318/C318,4)) | G318: =IF(ISNUMBER(F318),ROUND(F318-E318,4),"")
A319: 2020 | B319: plomo | C319: 1641373694 | D319: 1482644734 | E319: 0.9033 | F319: =IF(C319=0,"",ROUND(D319/C319,4)) | G319: =IF(ISNUMBER(F319),ROUND(F319-E319,4),"")
A320: 2020 | B320: silice | C320: 8791940 | D320: 1391684 | E320: 0.1583 | F320: =IF(C320=0,"",ROUND(D320/C320,4)) | G320: =IF(ISNUMBER(F320),ROUND(F320-E320,4),"")
A321: 2020 | B321: zinc | C321: 994375109 | D321: 646136225 | E321: 0.6498 | F321: =IF(C321=0,"",ROUND(D321/C321,4)) | G321: =IF(ISNUMBER(F321),ROUND(F321-E321,4),"")
A322: 2021 | B322: barita | C322: 19124233 | D322: 19124233 | E322: 1 | F322: =IF(C322=0,"",ROUND(D322/C322,4)) | G322: =IF(ISNUMBER(F322),ROUND(F322-E322,4),"")
A323: 2021 | B323: cobre | C323: 4985400522 | D323: 3420948513 | E323: 0.6862 | F323: =IF(C323=0,"",ROUND(D323/C323,4)) | G323: =IF(ISNUMBER(F323),ROUND(F323-E323,4),"")
... A365: 2024 | B365: zinc | C365: 725457434 | D365: 577061971 | E365: 0.7954 | F365: =IF(C365=0,"",ROUND(D365/C365,4)) | G365: =IF(ISNUMBER(F365),ROUND(F365-E365,4),"")

Sheet 18b Comercio por etapa
A1: Comercio por etapa (serie larga, valor por mineral x etapa x flujo, 1992-2024)
A2: Insumo de la posicion (hoja 18). Etapas E1-E4 segun la concordancia HS (hoja 18c). Caveat: cambian versiones HS a lo largo del periodo -> leer como tendencia.
A3: anio | B3: mineral | C3: etapa | D3: flujo | E3: valor_usd
A4: 1992 | B4: barita | C4: E1 Crudo/molido | D4: M | E4: 1032000
A5: 1992 | B5: barita | C5: E1 Crudo/molido | D5: X | E5: 1244000
A6: 1992 | B6: barita | C6: E2 Quimicos de bario | D6: M | E6: 360000
A7: 1992 | B7: barita | C7: E2 Quimicos de bario | D7: X | E7: 1571000
A8: 1992 | B8: cobre | C8: E1 Mena/concentrado | D8: M | E8: 27437000
A9: 1992 | B9: cobre | C9: E1 Mena/concentrado | D9: X | E9: 31605000
A10: 1992 | B10: cobre | C10: E2 Metal en bruto/refinado | D10: M | E10: 100243000
A11: 1992 | B11: cobre | C11: E2 Metal en bruto/refinado | D11: X | E11: 287704992
A12: 1992 | B12: cobre | C12: E3 Semimanufacturas | D12: M | E12: 184950000
A13: 1992 | B13: cobre | C13: E3 Semimanufacturas | D13: X | E13: 127642000
A14: 1992 | B14: cobre | C14: E4 Manufacturas | D14: M | E14: 96622000
A15: 1992 | B15: cobre | C15: E4 Manufacturas | D15: X | E15: 23568000
... A1902: 2024 | B1902: zinc | C1902: E4 Manufacturas | D1902: X | E1902: 5516170

Sheet 18c Concordancia HS
A1: Concordancia mineral x etapa x fraccion HS
A2: Operacionalizacion que asigna cada fraccion HS a una etapa E1-E4. Base de todo el analisis de comercio por grado de transformacion.
A3: mineral | B3: etapa | C3: fracciones_hs
A4: cobre | B4: E1 Mena/concentrado | C4: 2603
A5: cobre | B5: E2 Metal en bruto/refinado | C5: 7401;7402;7403;7405
A6: cobre | B6: E3 Semimanufacturas | C6: 7407;7408;7409;7410;7411;7412;7413
A7: cobre | B7: E4 Manufacturas | C7: 7415;7418;7419
A8: plomo | B8: E1 Mena/concentrado | C8: 2607
A9: plomo | B9: E2 Metal en bruto/refinado | C9: 7801
A10: plomo | B10: E3 Semimanufacturas | C10: 7804
A11: plomo | B11: E4 Manufacturas | C11: 7806
A12: zinc | B12: E1 Mena/concentrado | C12: 2608
A13: zinc | B13: E2 Metal en bruto/refinado | C13: 7901
A14: zinc | B14: E3 Semimanufacturas | C14: 7903;7904;7905
... A32: silice | B32: E2 Silicio/ferrosilicio/SiO2 | C32: 280461;280469;720221;720229;281122

Sheet 19 Comercio destinos
A1: Comercio - destinos de exportacion (serie 1992-2024)
A2: Por mineral-etapa-anio: destino principal y share de China/EUA. Resultado a partir del crudo por socio de Comtrade (share = valor_destino/valor_total). Hallazgo: los concentrados se desplazan de Norteamerica (1990s) a China. Detalle acumulado por socio en la hoja '19b'.
A3: anio | B3: mineral | C3: etapa | D3: valor_total_usd | E3: destino_principal | F3: share_principal | G3: share_china | H3: share_eua | I3: n_destinos
A4: 1992 | B4: barita | C4: E1 Crudo/molido | D4: 1244000 | E4: Estados Unidos | F4: 1 | G4: 0 | H4: 1 | I4: 1
A5: 1992 | B5: barita | C5: E2 Quimicos de bario | D5: 1571000 | E5: Estados Unidos | F5: 0.9955 | G5: 0 | H5: 0.9955 | I5: 3
A6: 1992 | B6: cobre | C6: E1 Mena/concentrado | D6: 31605000 | E6: Estados Unidos | F6: 0.7624 | G6: 0 | H6: 0.7624 | I6: 2
A7: 1992 | B7: cobre | C7: E2 Metal en bruto/refinado | D7: 287704992 | E7: Estados Unidos | F7: 0.487 | G7: 0 | H7: 0.487 | I7: 11
A8: 1992 | B8: cobre | C8: E3 Semimanufacturas | D8: 127642000 | E8: Estados Unidos | F8: 0.6947 | G8: 0 | H8: 0.6947 | I8: 32
A9: 1992 | B9: cobre | C9: E4 Manufacturas | D9: 23568000 | E9: Estados Unidos | F9: 0.9123 | G9: 0.0003 | H9: 0.9123 | I9: 31
A10: 1992 | B10: fluorita | C10: E1 Espato fluor (crudo) | D10: 13929000 | E10: Estados Unidos | F10: 0.6031 | G10: 0 | H10: 0.6031 | I10: 10
A11: 1992 | B11: fluorita | C11: E2 Fluoroquimica | D11: 86072000 | E11: Estados Unidos | F11: 0.7152 | G11: 0 | H11: 0.7152 | I11: 7
A12: 1992 | B12: grafito | C12: E1 Grafito natural | D12: 3073000 | E12: Estados Unidos | F12: 0.9307 | G12: 0 | H12: 0.9307 | I12: 2
A13: 1992 | B13: grafito | C13: E2 Grafito artificial/prep. | D13: 12300000 | E13: Estados Unidos | F13: 0.9893 | G13: 0.0018 | H13: 0.9893 | I13: 5
A14: 1992 | B14: grafito | C14: E3 Electrodos/articulos de carbono | D14: 15432000 | E14: Colombia | F14: 0.2506 | G14: 0 | H14: 0.1973 | I14: 19
A15: 1992 | B15: manganeso | C15: E1 Mena/concentrado | D15: 6044000 | E15: Estados Unidos | F15: 0.2631 | G15: 0 | H15: 0.2631 | I15: 11
... A896: 2024 | B896: zinc | C896: E4 Manufacturas | D896: 973514 | E896: Guatemala | F896: 0.2211 | G896: 0.0152 | H896: 0 | I896: 17

Sheet 19b Destinos acumulado
A1: Comercio - destinos por mineral x etapa (acumulado 2019-2024)
A2: share_etapa = valor a ese destino / valor total de la etapa. Hallazgo: concentrado de cobre 94.7% a China.
A3: mineral | B3: etapa | C3: pais_destino | D3: m49 | E3: valor_usd_2019_2024 | F3: share_etapa
A4: barita | B4: E1 Crudo/molido | C4: Estados Unidos | D4: 842 | E4: 85527052 | F4: 1
A5: cobre | B5: E1 Mena/concentrado | C5: China | D5: 156 | E5: 20416199679 | F5: 0.9474
A6: cobre | B6: E1 Mena/concentrado | C6: Japon | D6: 392 | E6: 307267119 | F6: 0.0143
A7: cobre | B7: E1 Mena/concentrado | C7: Estados Unidos | D7: 842 | E7: 276483277 | F7: 0.0128
A8: cobre | B8: E1 Mena/concentrado | C8: Corea del Sur | D8: 410 | E8: 262700070 | F8: 0.0122
A9: cobre | B9: E1 Mena/concentrado | C9: Canada | D9: 124 | E9: 177848284 | F9: 0.0083
A10: cobre | B10: E1 Mena/concentrado | C10: socio_490 | D10: 490 | E10: 87855057 | F10: 0.0041
A11: cobre | B11: E1 Mena/concentrado | C11: Peru | D11: 604 | E11: 19447858 | F11: 0.0009
A12: cobre | B12: E1 Mena/concentrado | C12: Singapur | D12: 702 | E12: 2005694 | F12: 0.0001
A13: cobre | B13: E1 Mena/concentrado | C13: Hong Kong | D13: 344 | E13: 386207 | F13: 0
A14: cobre | B14: E1 Mena/concentrado | C14: Vietnam | D14: 704 | E14: 328432 | F14: 0
A15: cobre | B15: E2 Metal en bruto/refinado | C15: Estados Unidos | D15: 842 | E15: 3295684924 | F15: 0.6914
... A288: zinc | B288: E4 Manufacturas | C288: Alemania | D288: 276 | E288: 33 | F288: 0

Sheet 20 Empresas transform
A1: Cadena local - empresas de transformacion (19 firmas)
A2: Directorio de procesadoras/usuarias domesticas por eslabon, con rol, ubicacion, propiedad y nivel de CONFIANZA (sourced-USGS / verificado-web / preliminar). Corrige el dato sectorial: buena parte de la cadena ocurre intra-firma, invisible en la MIP.
A3: mineral | B3: eslabon | C3: empresa | D3: rol | E3: ubicacion | F3: propiedad | G3: confianza | H3: fuente
A4: cobre | B4: E2 fundición/refinación | C4: Grupo México (Mexicana de Cobre) | D4: Fundición y refinería La Caridad | E4: Nacozari, Son. | F4: nacional | G4: sourced-USGS Tabla 2
A5: cobre | B5: E2 fundición | C5: Grupo México (Mexicana de Cananea/Buenavista) | D5: Fundición | E5: Cananea, Son. | F5: nacional | G5: sourced-USGS Tabla 2
A6: cobre | B6: E2 refinación | C6: Cobre de México, S.A. | D6: Refinería primaria | E6: Ciudad de México | F6: nacional | G6: sourced-USGS Tabla 2
A7: cobre | B7: E3 semis (alambre/cable) | C7: Viakable (Grupo Xignux) | D7: Mayor fabricante de conductores de cobre; plantas Monterrey y S.L.P. | E7: Monterrey, N.L. / S.L.P. | F7: nacional | G7: verificado-web | H7: viakable.com
A8: cobre | B8: E3 semis (alambre/cable) | C8: Condumex (Grupo Carso) | D8: Conductores de cobre (Condumex, Latincasa); desde 1954 | E8: Vallejo, CDMX / varias | F8: nacional | G8: verificado-web | H8: grupocarso.com
A9: oro-plata | B9: E2 refinación metales preciosos | C9: Met-Mex Peñoles | D9: Refinería de oro y plata | E9: Torreón, Coah. | F9: nacional | G9: sourced-USGS Tabla 2
A10: plomo-zinc | B10: E2 fundición/refinación | C10: Met-Mex Peñoles | D10: Refinería de plomo, zinc, plata y oro | E10: Torreón, Coah. | F10: nacional | G10: sourced-USGS Tabla 2
A11: plomo-zinc | B11: E2 refinación zinc | C11: Grupo México (IMMSA) | D11: Refinería de zinc | E11: San Luis Potosí, S.L.P. | F11: nacional | G11: sourced-USGS Tabla 2
A12: plomo-zinc | B12: E4 baterías | C12: Clarios (marca LTH) | D12: Baterías plomo-ácido + reciclaje (~184 mil t Pb/año recuperado) | E12: Nuevo León | F12: extranjera (marca nacional LTH, 1928) | G12: verificado-web | H12: clarios.com
A13: manganeso | B13: E2 ferroaleaciones | C13: Compañía Minera Autlán | D13: Ferro- y silicomanganeso (Tamós, Teziutlán, Gómez Palacio); ~225 mil t/año | E13: Veracruz / Puebla / Durango | F13: nacional | G13: verificado-web | H13: autlan.com.mx
A14: fluorita | B14: E2 fluoroquímica (HF) | C14: Koura (Orbia) | D14: Planta de ácido fluorhídrico más grande del mundo; integrada con mina Las Cuevas | E14: Matamoros, Tamps. | F14: nacional | G14: verificado-web | H14: kouraglobal.com
A15: fluorita | B15: E4 fluoropolímeros | C15: (no se produce en México) | D15: PTFE/fluoropolímeros importados (~30-40 MM USD/año) | E15: — | F15: — | G15: verificado-comercio (ausente)
A16: fluorita | B16: usuario (cemento) | C16: CEMEX; Holcim México; Cruz Azul; GCC | D16: Fluorita como mineralizador del clínker (baja 60-100°C la clinkerización) | E16: varias | F16: nacional/extranjera | G16: verificado-web | H16: scielo/CEMEX
A17: silice | B17: usuario (vidrio) | C17: Vitro; Owens-Illinois de México | D17: Vidrio (funde arena sílica); O-I opera además extracción de arena | E17: Monterrey / varias | F17: nacional/extranjera | G17: verificado-web | H17: vitro.com / o-i.com
A18: silice | B18: usuario (cemento/cerámica) | C18: CEMEX; Holcim México; GCC | D18: Insumo de cemento y cerámica | E18: varias | F18: nacional/extranjera | G18: verificado-web | H18: cemexmexico.com
A19: silice | B19: E2 silicio/ferrosilicio | C19: (mayormente importado) | D19: Silicio metálico/ferrosilicio importados (importador neto) | E19: — | F19: — | G19: verificado-comercio
A20: grafito | B20: E4 siderurgia (EAF) | C20: Ternium; ArcelorMittal; DeAcero; Gerdau Corsa (CANACERO) | D20: Acero por horno de arco eléctrico (96.7%): electrodos de grafito, refractarios, recarburación | E20: varias | F20: nacional/extranjera | G20: verificado-web | H20: canacero.org.mx
A21: grafito | B21: E3 electrodos | C21: (mayormente importado) | D21: Electrodos de grafito importados (importador neto) | E21: — | F21: — | G21: verificado-comercio
A22: barita | B22: usuario (perforación) | C22: PEMEX (+ servicios: Halliburton, Baker Hughes, SLB) | D22: Barita grado API como densificante de lodos; PEMEX se abastece de Coahuila y Sonora | E22: Cuenca de Campeche / Golfo | F22: estatal + extranjera (servicios) | G22: verificado-web | H22: PEMEX/QuimiNet

Sheet 20b Fichas por eslabon
A1: Cadena local - fichas L0-L4 cuantificadas (VBP/PIB/empleo 2013-2018, X/M)
A2: Cada mercado por eslabon con VBP/PIB/empleo de la MIP donde la clase SCIAN es atribuible, y X/M por etapa. Solo el cobre tiene clases SCIAN dedicadas a su transformacion; el resto comparte clase -> ese valor NO se atribuye (nota).
A3: mineral | B3: eslabon | C3: etapa | D3: scian | E3: atribuible_mip | F3: vbp_mmp_2013 | G3: pib_mmp_2013 | H3: empleo_2013 | I3: vbp_mmp_2018 | J3: pib_mmp_2018 | K3: empleo_2018 | L3: nota_clase_no_atribuible | M3: X_musd_1823 | N3: M_musd_1823
A4: cobre | B4: L1 | C4: E1 | D4: 212231 | E4: si | F4: 39971.4 | G4: 28083.9 | H4: 12523 | I4: 92893 | J4: 62412.4 | K4: 8718 | M4: 2968.41 | N4: 672.48
A5: cobre | B5: L2 | C5: E2 | D5: 331411 | E5: si | F5: 29375.5 | G5: 10251.4 | H5: 2064 | I5: 80889.3 | J5: 15418.1 | K5: 6301 | M5: 772.89 | N5: 966.08
A6: cobre | B6: L3 | C6: E3 | D6: 331420 | E6: si | F6: 48774.4 | G6: 13000.4 | H6: 9208 | I6: 35975.3 | J6: 10146.8 | K6: 7204 | M6: 528.65 | N6: 2099.93
A7: cobre | B7: L4 | C7: E4 | D7: 335999 | E7: no | L7: VBP clase agregada 2013=51,081 mmp; VBP clase agregada 2018=103,839 mmp; | M7: 68.93 | N7: 401.88
A8: fluorita | B8: L1 | C8: E1 | D8: 212395 | E8: si | F8: 2218.2 | G8: 1562.8 | H8: 1713 | I8: 5861.8 | J8: 3717.5 | K8: 740 | M8: 78.52 | N8: 0.04
A9: fluorita | B9: L2 | C9: E2 | D9: 325180 | E9: no | L9: VBP clase agregada 2013=29,781 mmp; VBP clase agregada 2018=67,911 mmp; | M9: 86.51 | N9: 40.84
A10: fluorita | B10: L3 | C10: E3 | D10: 325190 | E10: no | L10: VBP clase agregada 2013=52,511 mmp; VBP clase agregada 2018=92,697 mmp;
A11: fluorita | B11: L4 | C11: E4 | D11: 325211 | E11: no | L11: VBP clase agregada 2013=78,302 mmp; VBP clase agregada 2018=120,223 mmp;
A12: oro | B12: L1 | C12: E1 | D12: 212221 | E12: si | F12: 49607.2 | G12: 32499 | H12: 12310 | I12: 69491.1 | J12: 39301.9 | K12: 4931 | M12: 128.39 | N12: 0
A13: oro | B13: L2 | C13: E2 | D13: 331412 | E13: comp:oro+plata | F13: 143518.8 | G13: 32829.4 | H13: 5839 | I13: 178982.4 | J13: 41461.3 | K13: 4622 | L13: CLASE COMPARTIDA (oro+plata): VBP no separable por mineral | M13: 3312.85 | N13: 123.35
A14: oro | B14: L4 | C14: E4 | D14: 339910 | E14: no | L14: VBP clase agregada 2013=0 mmp; VBP clase agregada 2018=0 mmp;
A15: plata | B15: L1 | C15: E1 | D15: 212222 | E15: si | F15: 44680.4 | G15: 29754.2 | H15: 17983 | I15: 49784.4 | J15: 30917.3 | K15: 7598 | M15: 75.18 | N15: 0.15
A16: plata | B16: L2 | C16: E2 | D16: 331412 | E16: comp:oro+plata | F16: 143518.8 | G16: 32829.4 | H16: 5839 | I16: 178982.4 | J16: 41461.3 | K16: 4622 | L16: CLASE COMPARTIDA (oro+plata): VBP no separable por mineral | M16: 2202.8 | N16: 106.11
A17: plata | B17: L4 | C17: E4 | D17: 339910 | E17: no | L17: VBP clase agregada 2013=0 mmp; VBP clase agregada 2018=0 mmp;
A18: plomo | B18: L1 | C18: E1 | D18: 212232 | E18: comp:plomo+zinc | F18: 20045.8 | G18: 13865.2 | H18: 10178 | I18: 34724.7 | J18: 21683.1 | K18: 11667 | L18: CLASE COMPARTIDA (plomo+zinc): VBP no separable por mineral | M18: 901.46 | N18: 24.45
A19: plomo | B19: L2 | C19: E2 | D19: 331419 | E19: comp:plomo+zinc+otros no ferrosos | F19: 11583.1 | G19: 4563 | H19: 4745 | I19: 14421.6 | J19: 1900.4 | K19: 1534 | L19: CLASE COMPARTIDA (plomo+zinc+otros no ferrosos): VBP no separable por mineral | M19: 175.85 | N19: 31.42
A20: plomo | B20: L3 | C20: E3 | D20: 331490 | E20: no | L20: VBP clase agregada 2013=10,405 mmp; VBP clase agregada 2018=11,397 mmp; | M20: 0.31 | N20: 0.64
A21: plomo | B21: L4 | C21: E4 | D21: 335910 | E21: no | L21: VBP clase agregada 2013=16,877 mmp; VBP clase agregada 2018=35,119 mmp; | M21: 1.25 | N21: 8.11
A22: zinc | B22: L1 | C22: E1 | D22: 212232 | E22: comp:plomo+zinc | F22: 20045.8 | G22: 13865.2 | H22: 10178 | I22: 34724.7 | J22: 21683.1 | K22: 11667 | L22: CLASE COMPARTIDA (plomo+zinc): VBP no separable por mineral | M22: 498.46 | N22: 23.74
A23: zinc | B23: L2 | C23: E2 | D23: 331419 | E23: comp:plomo+zinc+otros no ferrosos | F23: 11583.1 | G23: 4563 | H23: 4745 | I23: 14421.6 | J23: 1900.4 | K23: 1534 | L23: CLASE COMPARTIDA (plomo+zinc+otros no ferrosos): VBP no separable por mineral | M23: 352.4 | N23: 73.6
A24: zinc | B24: L3 | C24: E3 | D24: 331490 | E24: no | L24: VBP clase agregada 2013=10,405 mmp; VBP clase agregada 2018=11,397 mmp; | M24: 1.42 | N24: 48.05
A25: zinc | B25: L4 | C25: E4 | D25: 332810 | E25: no | L25: VBP clase agregada 2013=32,239 mmp; VBP clase agregada 2018=42,691 mmp; | M25: 8.84 | N25: 73.74
A26: manganeso | B26: L1 | C26: E1 | D26: 212291 | E26: si | F26: 486 | G26: 373.9 | H26: 672 | I26: 635 | J26: 309.3 | K26: 523 | M26: 0 | N26: 14.55
A27: manganeso | B27: L2 | C27: E2 | D27: 331112 | E27: comp:ferroaleaciones+acero+ferrosilicio | F27: 39821.9 | G27: 16179.8 | H27: 4365 | I27: 46575.4 | J27: 13604.5 | K27: 1884 | L27: CLASE COMPARTIDA (ferroaleaciones+acero+ferrosilicio): VBP no separable por mineral | M27: 24.28 | N27: 1.6
A28: manganeso | B28: L3 | C28: E3 | D28: 325180 | E28: no | L28: VBP clase agregada 2013=29,781 mmp; VBP clase agregada 2018=67,911 mmp; | M28: 0.18 | N28: 34.78
A29: grafito | B29: L1 | C29: E1 | D29: 212396 | E29: si | F29: 164.1 | G29: 123.7 | H29: 229 | I29: 719.8 | J29: 568.1 | K29: 627 | M29: 2.15 | N29: 3.69
A30: grafito | B30: L2 | C30: E2 | D30: 325180 | E30: no | L30: VBP clase agregada 2013=29,781 mmp; VBP clase agregada 2018=67,911 mmp; | M30: 53.43 | N30: 53.75
A31: grafito | B31: L3 | C31: E3 | D31: 327999 | E31: no | L31: VBP clase agregada 2013=13,583 mmp; VBP clase agregada 2018=26,306 mmp; | M31: 120.63 | N31: 178.18
A32: grafito | B32: L4 | C32: E4 | D32: 331111 | E32: no | L32: VBP clase agregada 2013=123,100 mmp; VBP clase agregada 2018=164,669 mmp;
A33: silice | B33: L1 | C33: E1 | D33: 212324 | E33: si | F33: 4898.3 | G33: 3154.1 | H33: 2863 | I33: 6959.1 | J33: 4388.1 | K33: 5642 | M33: 2.08 | N33: 73.73
A34: silice | B34: L2 | C34: E2 | D34: 331112 | E34: no | L34: VBP clase agregada 2013=39,822 mmp; VBP clase agregada 2018=46,575 mmp; | M34: 8.22 | N34: 263.76
A35: silice | B35: L4 | C35: E4 | D35: 327211 | E35: no | L35: VBP clase agregada 2013=23,027 mmp; VBP clase agregada 2018=28,333 mmp;
A36: barita | B36: L1 | C36: E1 | D36: 212393 | E36: si | F36: 368.3 | G36: 222.8 | H36: 1003 | I36: 685.6 | J36: 452.4 | K36: 1713 | M36: 12.07 | N36: 4.67
A37: barita | B37: L2 | C37: E2 | D37: 325180 | E37: no | L37: VBP clase agregada 2013=29,781 mmp; VBP clase agregada 2018=67,911 mmp; | M37: 0 | N37: 3.59
A38: barita | B38: L4 | C38: E4 | D38: 213111 | E38: no | L38: VBP clase agregada 2013=156,155 mmp; VBP clase agregada 2018=136,811 mmp;

Sheet 20c Tipologia ABCD
A1: Cadena local - tipologia A/B/C/D
A2: Clasifica los 10 mercados por grado de transformacion domestica (A desarrollada / B truncada en refinado / C usuario con eslabon importado / D exportacion en bruto), con los criterios que la sustentan (actores, espejo, Ghosh/DI).
A3: mineral | B3: tipo | C3: eslabon_ruptura | D3: criterio_actores | E3: criterio_espejo | F3: criterio_ghosh_di | G3: justificacion
A4: cobre | B4: B | C4: L2->L3 | D4: L1,L2,L3 con actores nacionales; L4 no atribuible | E4: X_share_crudo 0.61->0.81; semis importador neto | F4: forward 1.34 realizado como export de metal | G4: Cadena hasta metal refinado; no profundiza a semis/manufactura (importadas); mineral sale como concentrado
A5: fluorita | B5: A | C5: L2->L3 | D5: L1 + L2 (HF Koura clase mundial); L3-L4 ausentes | E5: historicamente procesado; retroceso a crudo 2021-23 (0.83-0.93) | F5: forward 1.31; DI local=cemento 82%, HF exporta | G5: La mas integrada no metalica (HF); limite A/B: fluoropolimeros importados y HF como enclave de exportacion
A6: oro | B6: B | C6: L2->L4 | D6: L1 disperso + L2 Penoles; L4 joyeria sin produccion | E6: exporta metal refinado (proc 0.99); joyeria importada | F6: DI 99.5% refinacion; forward 1.22 moderado | G6: Se refina y exporta como metal/dore; joyeria importada; cadena se cierra en el lingote
A7: plata | B7: B | C7: L2->L4 | D7: L1 disperso + L2 Penoles; L4 joyeria sin produccion | E7: exporta plata refinada (proc 0.98); joyeria importada | F7: DI 99% refinacion; forward 1.17 | G7: 1o productor mundial; cadena se cierra en el metal refinado, no en la manufactura
A8: plomo | B8: B | C8: L1->L2 | D8: L1,L2 Penoles,L4 baterias Clarios; L3 marginal | E8: X_share_crudo 0.78->0.86 (exporta concentrado) | F8: forward 0.71 (muy bajo); DI 79.5% no ferrosos | G8: Refinacion y baterias existen pero desacopladas; primario sale como concentrado; baterias usan reciclado
A9: zinc | B9: B | C9: L1->L2 | D9: L1,L2 IMMSA/Penoles; L3-L4 debiles | E9: X_share_crudo 0.64->0.80; semis importador neto | F9: forward 0.71 (bajo) | G9: Refinacion nacional presente pero exporta concentrado e importa semis/galvanizado
A10: manganeso | B10: A | C10: L2->L3 | D10: Autlan integra L1+L2 (ferroaleacion) | E10: exporta procesado, no mena (crudo=0) | F10: forward 1.54 (alto); insumo siderurgico | G10: Cadena metalica desarrollada con capital nacional; exporta ferroaleacion; ruptura en la quimica fina de Mn
A11: grafito | B11: C | C11: L1->L2 | D11: usuarios (acerias EAF) presentes; sin productor del insumo | E11: importador neto de procesado/electrodos | F11: forward 1.71 (alto), todo a siderurgia | G11: Industria usuaria robusta pero grafito procesado y electrodos importados; mina decreciente
A12: silice | B12: C | C12: L1->L2 | D12: usuarios (vidrio,cemento) presentes; sin productor de silicio | E12: importador neto de silicio/ferrosilicio (M~264 MUSD) | F12: forward 1.92 (el mas alto); vidrio+cemento | G12: Cadena de bajo grado local (arena->vidrio/cemento) real; eslabon de silicio de alto valor importado
A13: barita | B13: D | C13: L1->L2 | D13: solo extraccion/molienda + uso petrolero; sin quimica | E13: exporta en bruto (crudo 100%) | F13: forward 0.64 (muy bajo); insumo petrolero | G13: Extraer y usar en bruto; sin transformacion quimica del bario en el pais

Sheet 21 ICIO comparacion
A1: Comparacion internacional - encadenamientos de mineria (OECD ICIO 2023, 8 paises)
A2: Ghosh (forward) y Leontief (backward) del sector mineria de 8 paises, 3-4 cortes. Sector comparable = B07_08 (mineria no energetica). Resultado del script sobre la matriz inter-pais; comparar POSICION relativa (ISIC != SCIAN), no niveles absolutos. Mexico 1.51 ~ China 1.53.
A3: anio | B3: pais | C3: pais_nombre | D3: sector | E3: sector_nombre | F3: vbp_musd | G3: share_vbp_pct | H3: backward_L_colsum | I3: forward_G_rowsum | J3: backward_rasmussen | K3: forward_rasmussen | L3: rank_backward | M3: rank_forward | N3: n_industrias
A4: 2008 | B4: MEX | C4: Mexico | D4: B05_06 | E4: mineria energeticos | F4: 94774.7 | G4: 4.928 | H4: 1.1795 | I4: 2.1193 | J4: 0.7409 | K4: 1.3657 | L4: 42 | M4: 7 | N4: 45
A5: 2008 | B5: MEX | C5: Mexico | D5: B07_08 | E5: mineria no energetica (metales+otra) | F5: 13243.4 | G5: 0.689 | H5: 1.5305 | I5: 2.5606 | J5: 0.9614 | K5: 1.65 | L5: 24 | M5: 1 | N5: 45
A6: 2008 | B6: MEX | C6: Mexico | D6: B09 | E6: servicios apoyo mineria | F6: 11605.6 | G6: 0.603 | H6: 1.5855 | I6: 1.2749 | J6: 0.9959 | K6: 0.8215 | L6: 21 | M6: 31 | N6: 45
A7: 2008 | B7: CHL | C7: Chile | D7: B05_06 | E7: mineria energeticos | F7: 496.5 | G7: 0.135 | H7: 1.6674 | I7: 2.9297 | J7: 0.9592 | K7: 1.6369 | L7: 28 | M7: 1 | N7: 45
A8: 2008 | B8: CHL | C8: Chile | D8: B07_08 | E8: mineria no energetica (metales+otra) | F8: 56714.8 | G8: 15.388 | H8: 1.8356 | I8: 1.5845 | J8: 1.056 | K8: 0.8853 | L8: 18 | M8: 27 | N8: 45
A9: 2008 | B9: CHL | C9: Chile | D9: B09 | E9: servicios apoyo mineria | F9: 107.1 | G9: 0.029 | H9: 1.4488 | I9: 1.8695 | J9: 0.8335 | K9: 1.0445 | L9: 39 | M9: 23 | N9: 45
A10: 2008 | B10: AUS | C10: Australia | D10: B05_06 | E10: mineria energeticos | F10: 80664 | G10: 4.07 | H10: 1.4455 | I10: 1.862 | J10: 0.771 | K10: 0.9683 | L10: 44 | M10: 24 | N10: 45
A11: 2008 | B11: AUS | C11: Australia | D11: B07_08 | E11: mineria no energetica (metales+otra) | F11: 59701.6 | G11: 3.012 | H11: 1.8272 | I11: 1.8409 | J11: 0.9746 | K11: 0.9573 | L11: 31 | M11: 25 | N11: 45
A12: 2008 | B12: AUS | C12: Australia | D12: B09 | E12: servicios apoyo mineria | F12: 12119.2 | G12: 0.611 | H12: 1.9483 | I12: 2.2204 | J12: 1.0391 | K12: 1.1547 | L12: 21 | M12: 19 | N12: 45
A13: 2008 | B13: FIN | C13: Finlandia | D13: B05_06 | E13: mineria energeticos | F13: 533.4 | G13: 0.096 | H13: 1.7158 | I13: 3.0549 | J13: 1.031 | K13: 1.7191 | L13: 20 | M13: 1 | N13: 45
A14: 2008 | B14: FIN | C14: Finlandia | D14: B07_08 | E14: mineria no energetica (metales+otra) | F14: 1877.8 | G14: 0.339 | H14: 1.7308 | I14: 2.5099 | J14: 1.04 | K14: 1.4124 | L14: 18 | M14: 2 | N14: 45
A15: 2008 | B15: FIN | C15: Finlandia | D15: B09 | E15: servicios apoyo mineria | F15: 38.9 | G15: 0.007 | H15: 1.7692 | I15: 1.9414 | J15: 1.0631 | K15: 1.0925 | L15: 13 | M15: 15 | N15: 45
... A90: 2020 | B90: SWE | C90: Suecia | D90: B09 | E90: servicios apoyo mineria | F90: 166.5 | G90: 0.017 | H90: 2.1415 | I90: 1.0182 | J90: 1.2533 | K90: 0.5899 | L90: 2 | M90: 44 | N90: 45

Sheet 21b ICIO DVA
A1: Comparacion internacional - DVA / crudo_share (el enclave en dinero)
A2: Descomposicion del valor agregado minero exportado: crudo_share = fraccion que sale en bruto a reprocesarse afuera. Columna verde comprueba la identidad crudo_share + reproc_domestico_share = 1 (validacion del script: 0 violaciones). Clave: Mexico crudo 0.38 vs China 0.07 con Ghosh casi igual.
A3: anio | B3: pais | C3: pais_nombre | D3: sector | E3: exgr_musd | F3: dva_share | G3: vax_mineria_musd | H3: reproc_domestico_share | I3: crudo_share | J3: foreign_abs_share | K3: crudo+reproc (=1?)
A4: 1995 | B4: MEX | C4: Mexico | D4: B05_06 | E4: 7393.3 | F4: 0.9749 | G4: 8838.7 | H4: 0.2375 | I4: 0.7625 | J4: 0.4729 | K4: =ROUND(I4+H4,4)
A5: 1995 | B5: MEX | C5: Mexico | D5: B07_08 | E5: 212 | F5: 0.9359 | G5: 717.2 | H5: 0.7641 | I5: 0.2359 | J5: 0.215 | K5: =ROUND(I5+H5,4)
A6: 1995 | B6: MEX | C6: Mexico | D6: B09 | E6: 7.4 | F6: 0.9132 | G6: 52.1 | H6: 0.2274 | I6: 0.7726 | J6: 0.0953 | K6: =ROUND(I6+H6,4)
A7: 1995 | B7: CHL | C7: Chile | D7: B05_06 | E7: 0.1 | F7: 0.8336 | G7: 13.9 | H7: 0.7376 | I7: 0.2624 | J7: 0.2742 | K7: =ROUND(I7+H7,4)
A8: 1995 | B8: CHL | C8: Chile | D8: B07_08 | E8: 7763.9 | F8: 0.8756 | G8: 5107.7 | H8: 0.0014 | I8: 0.9986 | J8: 0.9956 | K8: =ROUND(I8+H8,4)
A9: 1995 | B9: CHL | C9: Chile | D9: B09 | E9: 6.5 | F9: 0.905 | G9: 4.6 | H9: 0.0084 | I9: 0.9916 | J9: 0.2548 | K9: =ROUND(I9+H9,4)
A10: 1995 | B10: AUS | C10: Australia | D10: B05_06 | E10: 7067.8 | F10: 0.9216 | G10: 5535.5 | H10: 0.1362 | I10: 0.8638 | J10: 0.687 | K10: =ROUND(I10+H10,4)
A11: 1995 | B11: AUS | C11: Australia | D11: B07_08 | E11: 4419.2 | F11: 0.8907 | G11: 5044.3 | H11: 0.4842 | I11: 0.5158 | J11: 0.6784 | K11: =ROUND(I11+H11,4)
A12: 1995 | B12: AUS | C12: Australia | D12: B09 | E12: 29.4 | F12: 0.9273 | G12: 710.1 | H12: 0.3082 | I12: 0.6918 | J12: 0.3545 | K12: =ROUND(I12+H12,4)
A13: 1995 | B13: FIN | C13: Finlandia | D13: B05_06 | E13: 9.6 | F13: 0.731 | G13: 38.5 | H13: 0.897 | I13: 0.103 | J13: 0.3481 | K13: =ROUND(I13+H13,4)
A14: 1995 | B14: FIN | C14: Finlandia | D14: B07_08 | E14: 117.5 | F14: 0.7516 | G14: 163.9 | H14: 0.6858 | I14: 0.3142 | J14: 0.5244 | K14: =ROUND(I14+H14,4)
A15: 1995 | B15: FIN | C15: Finlandia | D15: B09 | E15: 1.2 | F15: 0.7158 | G15: 0.7 | H15: 0.3963 | I15: 0.6037 | J15: 0.5272 | K15: =ROUND(I15+H15,4)
... A429: 2020 | B429: PER | C429: Peru | D429: B09 | E429: 2.4 | F429: 0.9157 | G429: 210.6 | H429: 0.1072 | I429: 0.8928 | J429: 0.5827 | K429: =ROUND(I429+H429,4)

Sheet 22 Criticidad
A1: Criticidad por producto
A2: Eslabon de mayor criticidad de cada mineral (estrategico > critico > medio > bajo) y si Mexico lo usa/exporta/importa. Base oficial USGS (2022/2025), UE (CRMA 2023), IEA. Muestra que la criticidad se concentra en productos y grados, no en el mineral.
A3: mineral | B3: etapa | C3: producto | D3: sector | E3: base_oficial | F3: nivel_criticidad | G3: mx_usa | H3: mx_exporta | I3: mx_importa
A4: cobre | B4: E1 | C4: concentrado de cobre | D4: insumo metalurgico (feed fundicion) | E4: UE-SRM;USGS2025 | F4: alto | G4: no | H4: si | I4: no
A5: cobre | B5: E2 | C5: catodo de cobre refinado | D5: electrificacion/red electrica/EV/construccion | E5: UE-SRM;USGS2025;IEA | F5: estrategico | G5: si | H5: si | I5: parcial
A6: cobre | B6: E3 | C6: alambron/laminados/tubos | D6: cableado electrico/plomeria | E6: derivado | F6: medio | G6: si | H6: parcial | I6: si
A7: cobre | B7: E4 | C7: cable y conductores | D7: electrico/automotriz | E7: derivado | F7: medio | G7: si | H7: no | I7: si
A8: fluorita | B8: E1 | C8: espato fluor grado acido (acidspar) | D8: precursor quimica del fluor | E8: UE-CRM;USGS | F8: alto | G8: si | H8: si | I8: no
A9: fluorita | B9: E1 | C9: espato fluor grado metalurgico (metspar) | D9: siderurgia/cemento (fundente) | E9: commodity | F9: bajo | G9: si | H9: si | I9: no
A10: fluorita | B10: E2 | C10: acido fluorhidrico HF | D10: aluminio(AlF3)/refrigerantes/semiconductores/precursor LiPF6 baterias | E10: UE-CRM;IEA | F10: estrategico | G10: si | H10: si | I10: no
A11: fluorita | B11: E3-E4 | C11: fluoropolimeros(PTFE)/refrigerantes/LiPF6 | D11: quimica avanzada/baterias/electronica | E11: UE;IEA | F11: estrategico | G11: no | H11: no | I11: si
A12: grafito | B12: E1 | C12: grafito natural amorfo/hojuela | D12: refractarios/fundicion/lubricantes | E12: USGS;UE | F12: medio | G12: si | H12: parcial | I12: no
A13: grafito | B13: E1 | C13: grafito natural grado bateria (esferico) | D13: anodos baterias Li-ion/EV | E13: UE-SRM;IEA | F13: estrategico | G13: no | H13: no | I13: no
A14: grafito | B14: E2-E3 | C14: grafito sintetico y electrodos | D14: acero EAF/baterias | E14: UE-SRM;USGS | F14: estrategico | G14: si(uso) | H14: no | I14: si
... A33: plata | B33: E4 | C33: plateria/joyeria | D33: consumo/industria | E33: uso-final | F33: bajo | G33: si(uso) | H33: no | I33: si

Sheet 23 HEM nacional
A1: Extraccion hipotetica (HEM) por mineral, 2013/2018
A2: HEM = % del VBP nacional que se perderia al extraer las compras (hacia atras) o ventas (hacia adelante) del mineral (Miller-Lahr 2001, casos 3/4; metodo de Morales-Lopez 2023). Inversion de matriz validada por Sherman-Morrison vs fuerza bruta a 1e-14 (script). Columna verde: hem_total recomputado = back + fwd; 'rank_*' = rango del mineral entre los n sectores. Mide PESO economico (complementa a Rasmussen, que mide intensidad).
A3: anio | B3: codigo | C3: mineral | D3: vbp_mmpesos | E3: hem_backward_pct | F3: hem_forward_pct | G3: hem_total_pct | H3: rank_backward | I3: rank_forward | J3: rank_total | K3: n_sectores | L3: hem_total (=formula) | M3: dif
A4: 2013 | B4: 212393 | C4: barita | D4: 368.345 | E4: 0.0006 | F4: 0.0003 | G4: 0.0009 | H4: 741 | I4: 587 | J4: 756 | K4: 822 | L4: =ROUND(E4+F4,4) | M4: =ROUND(L4-G4,4)
A5: 2013 | B5: 212231 | C5: cobre | D5: 39971.368 | E5: 0.0486 | F5: 0.1239 | G5: 0.1725 | H5: 162 | I5: 64 | J5: 101 | K5: 822 | L5: =ROUND(E5+F5,4) | M5: =ROUND(L5-G5,4)
A6: 2013 | B6: 212395 | C6: fluorita | D6: 2218.245 | E6: 0.0022 | F6: 0.003 | G6: 0.0052 | H6: 607 | I6: 449 | J6: 597 | K6: 822 | L6: =ROUND(E6+F6,4) | M6: =ROUND(L6-G6,4)
A7: 2013 | B7: 212396 | C7: grafito | D7: 164.102 | E7: 0.0002 | F7: 0.0006 | G7: 0.0007 | H7: 794 | I7: 554 | J7: 764 | K7: 822 | L7: =ROUND(E7+F7,4) | M7: =ROUND(L7-G7,4)
A8: 2013 | B8: 212291 | C8: manganeso | D8: 486.019 | E8: 0.0004 | F8: 0.0032 | G8: 0.0036 | H8: 761 | I8: 439 | J8: 641 | K8: 822 | L8: =ROUND(E8+F8,4) | M8: =ROUND(L8-G8,4)
A9: 2013 | B9: 212221 | C9: oro | D9: 49607.237 | E9: 0.0676 | F9: 0.198 | G9: 0.2656 | H9: 126 | I9: 33 | J9: 59 | K9: 822 | L9: =ROUND(E9+F9,4) | M9: =ROUND(L9-G9,4)
A10: 2013 | B10: 212222 | C10: plata | D10: 44680.402 | E10: 0.0599 | F10: 0.1686 | G10: 0.2285 | H10: 139 | I10: 45 | J10: 77 | K10: 822 | L10: =ROUND(E10+F10,4) | M10: =ROUND(L10-G10,4)
A11: 2013 | B11: 212232 | C11: plomo-zinc | D11: 20045.785 | E11: 0.0251 | F11: 0.0095 | G11: 0.0346 | H11: 247 | I11: 312 | J11: 304 | K11: 822 | L11: =ROUND(E11+F11,4) | M11: =ROUND(L11-G11,4)
A12: 2013 | B12: 212324 | C12: silice | D12: 4898.266 | E12: 0.0066 | F12: 0.0326 | G12: 0.0393 | H12: 474 | I12: 160 | J12: 278 | K12: 822 | L12: =ROUND(E12+F12,4) | M12: =ROUND(L12-G12,4)
A13: 2018 | B13: 212393 | C13: barita | D13: 685.596 | E13: 0.0006 | F13: 0.0001 | G13: 0.0007 | H13: 745 | I13: 680 | J13: 781 | K13: 834 | L13: =ROUND(E13+F13,4) | M13: =ROUND(L13-G13,4)
A14: 2018 | B14: 212231 | C14: cobre | D14: 92892.952 | E14: 0.0757 | F14: 0.2497 | G14: 0.3253 | H14: 106 | I14: 25 | J14: 46 | K14: 834 | L14: =ROUND(E14+F14,4) | M14: =ROUND(L14-G14,4)
A15: 2018 | B15: 212395 | C15: fluorita | D15: 5861.771 | E15: 0.0055 | F15: 0.0154 | G15: 0.0209 | H15: 475 | I15: 281 | J15: 395 | K15: 834 | L15: =ROUND(E15+F15,4) | M15: =ROUND(L15-G15,4)
... A21: 2018 | B21: 212324 | C21: silice | D21: 6959.054 | E21: 0.0058 | F21: 0.0347 | G21: 0.0406 | H21: 468 | I21: 170 | J21: 276 | K21: 834 | L21: =ROUND(E21+F21,4) | M21: =ROUND(L21-G21,4)

Sheet 24 HEM estatal
A1: Extraccion hipotetica (HEM) de la mineria por entidad, 2018
A2: HEM = % del VBP birregional (entidad + resto del pais) que se perderia al extraer la mineria de la entidad. MIP birregional INEGI 2018; inversion validada por Sherman-Morrison vs fuerza bruta a 1e-14. Columna verde: hem_total = back + fwd.
A3: estado | B3: abrev | C3: vbp_mineria_mdp | D3: hem_backward_pct | E3: hem_forward_pct | F3: hem_total_pct | G3: hem_total (=formula) | H3: dif
A4: Sonora | B4: son | C4: 140608.2 | D4: 0.1404 | E4: 0.3875 | F4: 0.5278 | G4: =ROUND(D4+E4,4) | H4: =ROUND(G4-F4,4)
A5: Coahuila | B5: coah | C5: 42338.9 | D5: 0.037 | E5: 0.1577 | F5: 0.1948 | G5: =ROUND(D5+E5,4) | H5: =ROUND(G5-F5,4)
A6: Durango | B6: dgo | C6: 36058.7 | D6: 0.0405 | E6: 0.0895 | F6: 0.13 | G6: =ROUND(D6+E6,4) | H6: =ROUND(G6-F6,4)
A7: San Luis Potosi | B7: slp | C7: 19628.6 | D7: 0.0149 | E7: 0.0768 | F7: 0.0917 | G7: =ROUND(D7+E7,4) | H7: =ROUND(G7-F7,4)
A8: Zacatecas | B8: zac | C8: 34470.9 | D8: 0.0342 | E8: 0.0547 | F8: 0.089 | G8: =ROUND(D8+E8,4) | H8: =ROUND(G8-F8,4)
A9: Jalisco | B9: jal | C9: 12982.8 | D9: 0.0117 | E9: 0.0498 | F9: 0.0616 | G9: =ROUND(D9+E9,4) | H9: =ROUND(G9-F9,4)
A10: Nuevo Leon | B10: nl | C10: 11947.1 | D10: 0.0105 | E10: 0.0457 | F10: 0.0562 | G10: =ROUND(D10+E10,4) | H10: =ROUND(G10-F10,4)
A11: Chihuahua | B11: chih | C11: 23906.3 | D11: 0.0256 | E11: 0.0192 | F11: 0.0449 | G11: =ROUND(D11+E11,4) | H11: =ROUND(G11-F11,4)
A12: Aguascalientes | B12: ags | C12: 9530.5 | D12: 0.0076 | E12: 0.0362 | F12: 0.0437 | G12: =ROUND(D12+E12,4) | H12: =ROUND(G12-F12,4)
A13: Michoacan | B13: mich | C13: 8896.6 | D13: 0.0077 | E13: 0.0302 | F13: 0.0379 | G13: =ROUND(D13+E13,4) | H13: =ROUND(G13-F13,4)
A14: Mexico | B14: mex | C14: 8584.5 | D14: 0.0052 | E14: 0.0319 | F14: 0.0372 | G14: =ROUND(D14+E14,4) | H14: =ROUND(G14-F14,4)
A15: Hidalgo | B15: hgo | C15: 7493.7 | D15: 0.0077 | E15: 0.0292 | F15: 0.0369 | G15: =ROUND(D15+E15,4) | H15: =ROUND(G15-F15,4)
... A35: Ciudad de Mexico | B35: cdmx | C35: 429.5 | D35: 0.0006 | E35: 0.0007 | F35: 0.0013 | G35: =ROUND(D35+E35,4) | H35: =ROUND(G35-F35,4)
